Workbook

Sheet 使用说明
A1: 产品成本测算报价表 · 使用说明
A3: 怎么用 | B3: 首页【报价汇总】只填：产品信息、成品尺寸与单台净重、每箱件数、是否带散热器、是否带组装结构、是否含整托、物流产品、目的地、每票件数。包装费、装配费与运费全部自动算。黄色底=必填待填，填完后自动变绿。
A4: 包装费 | B4: 首页【报价汇总】分别填写【是否带散热器】与【是否带组装结构】：任一为「是」→大板（EPE上下垫片+四角护角+纸箱+托盘+缠绕膜+打包带）；两项均为「否」→小板（防静电气泡袋+隔板+纸箱+护角+托盘+缠绕膜）。如有组装结构，填写装配节拍(秒/台)和工时费，装配费=节拍÷3600×工时费。单价与系数在《参数》页改。
A5: 运费 | B5: 依据《跨越费率》（源自青岛国创VIP报价表）按 实重/体积重取大→起重→分段单价 计算单票运费，再摊到单件。目的地在首页下拉选择，产品可选次日达/特惠普运。
A6: 物料明细/制费明细 | B6: 沿用原模板，硬件/结构件/辅助材料与加工费、工装分摊在此填写。
A7: 成本与报价 | B7: 总成本=材料+加工+工装+包装+运费+利润；建议报价=总成本/(1-目标毛利率)。毛利率/税率在《参数》页改。
A8: 注意 | B8: 跨越费率为参考价，可在《跨越费率》页直接改；金额默认不含税；包装费按方案清单自动算。
A9: 制费明细：P01~P07工程报价表格式，蓝色单元格按项目填写（元件个数/工序个数/用量/张数/预计订单数），默认预填003小板参考数据；辅料与BOM辅助材料二选一，避免重复计费。
A10: • 商空大功率驱动板套表：物料明细已导入 硬件272/结构件32/散热器1/包装8/辅料16/客供料8 共337行；损耗率留空使金额=用量×单价，与源表精确对账（硬件358.4632/结构416.4798/包装63.7765/辅料37.9431）。
A11: • 加工成本明细：综合口径13项构成→126.4283元/台（含人工82.0882+SMT/机插+折旧+水电+管理），附52行人工工时定额、16行工装治具明细；报价汇总「加工成本」直接引用其合计。
A12: • 散热器：源表未含，按68元未税单列（参数B49），物料明细分类「散热器」，报价汇总独立成本行。
A13: • 一次性费用：工装48700+EPS泡沫模具29499.115=78199.115元，直接向客户收取，不计入单台成本（报价汇总六）。
A14: • 运费：目的地填「青岛市」时跨越费率未覆盖山东→自动按运费率(参数B51=1.16%)回退估算；覆盖城市则用跨越费率精算。毛利率(参数B4)已对齐源表0.3。
A15: • 制费明细P01~P07为自下而上工序估算工具（商空项目已置0辅料/工装避免重复）；商空加工成本以「加工成本明细」综合表为准。
A16: • 风险检查（报价汇总七）：客供料清单8项与硬件BOM内8项单价0的客供标记一一对应，均不计入成本；未报价物料(非客供)应为0。客供料参考金额按用量×单价=565.138元/台，源表合计554.3197（源表口径差10.82，不影响报价）。
A17: • 包装费双口径：报价汇总取包装BOM实际63.7765元/台；包装计算表按几何模型估算约43.67元/件，两者互为校验，BOM优先。EPS泡沫模具16667元×2已列入一次性费用。
A18: • 成本差异1.35%(参数B50)与运费率1.16%(参数B51)均取自源表比例；小计含散热器68元后，成本差异与运费随之联动放大，符合"全部成本因素入表"的口径。

Sheet 报价汇总
A1: 产品成本测算报价表（包装费 + 运费自动计算）
A3: 一、产品基础信息（输入）
A4: 产品代码 | B4: N10305002124 | Z4: 福州市/厦门市/泉州市
A5: 产品名称 | B5: DRV-26P-NJTJ(RoHS)中央式空调控制器驱动板组件 | Z5: 宁德市/莆田市/漳州市
A6: 客户名称 | B6: 青岛国创智能家电研究院有限公司 | Z6: 龙岩市/三明市/南平市
A7: 报价日期 | B7: =TODAY() | Z7: 拉萨市
A8: 年需求量(PCS) | B8: 5000 | Z8: 日喀则市/山南市/林芝市/昌都市/那曲市/阿里地区
A9: MOQ(PCS) | B9: 50 | Z9: 贵阳市/遵义市/安顺市
A10: 备注 | B10: 工装、模具费直接向客户收取；已扣除8颗客供料核算成本；散热器68元未税另计；N10305002124与N10305002125共用模具 | Z10: 黔南布依族苗族自治州/黔东南苗族侗族自治州/铜仁市/毕节市/六盘水市/黔西南布依族苗族自治州
Z11: 广州市/深圳市/珠海市/中山市/东莞市
A12: 二、产品规格（输入，驱动包装费） | Z12: 江门市/惠州市/佛山市/肇庆市
A13: 成品长(mm,含散热器) | B13: 660 | Z13: 汕尾市/阳江市/揭阳市/茂名市/韶关市/梅州市/汕头市/湛江市/河源市/清远市/云浮市/潮州市
A14: 成品宽(mm) | B14: 390 | Z14: 武汉市/鄂州市
A15: 成品高(mm) | B15: 260 | Z15: 襄阳市/孝感市/黄石市/荆州市/宜昌市/神农架林区/十堰市/随州市/荆门市
A16: 单台净重(kg) | B16: 3.5 | Z16: 黄冈市/咸宁市/恩施土家族苗族自治州/潜江市/仙桃市/天门市
A17: 每箱件数N | B17: 2 | Z17: 株洲市/长沙市/湘潭市
A18: 是否含整托分摊 | B18: 是 | Z18: 益阳市
A19: 是否带散热器(是/否) | B19: 是 | D19: =IF(OR(B19="是",B20="是"),"自动→大板：EPE上下垫片+四角护角+纸箱+托盘+缠绕膜+打包带","自动→小板：防静电气泡袋+隔板+纸箱+护角+托盘+缠绕膜") | Z19: 岳阳市/衡阳市/郴州市/常德市/娄底市/邵阳市/湘西土家族苗族自治州/张家界市/怀化市/永州市
A20: 是否带组装结构(是/否) | B20: 是 | D20: 装配节拍(秒/台) | E20: 12 | F20: 工时费(元/小时) | G20: =参数!$B$46
A21: 三、物流（输入，驱动运费） | Z21: 重庆市
A22: 物流产品 | B22: 次日达 | Z22: 成都市/资阳市/眉山市
A23: 目的地 | B23: 青岛市 | Z23: 绵阳市
A24: 每票件数M | B24: 20 | Z24: 自贡市/南充市/达州市/遂宁市/广安市/巴中市/泸州市/宜宾市/内江市/乐山市/雅安市/德阳市/广元市
A25: 声明价值(元/票,可选) | Z25: 攀枝花市/凉山彝族自治州/甘孜藏族自治州/阿坝藏族羌族自治州
A26: 注 | B26: 物流产品选次日达/特惠普运；目的地只需填城市名（如“宁波”“杭州”），系统按所选产品自动匹配对应费率行；该产品不覆盖此城市时运费显示空白。 | Z26: 合肥市/芜湖市/马鞍山市
A27: 四、成本构成（未税/单台，自动计算） | Z27: 滁州市/蚌埠市/六安市
A28: 成本项目 | B28: 金额 | C28: 单位 | D28: 备注 | E28: 公式 | Z28: 淮南市/安庆市/宿州市/亳州市/阜阳市/黄山市/淮北市/铜陵市/宣城市/池州市
A29: 硬件材料 | B29: =SUMIFS(物料明细!$H:$H,物料明细!$B:$B,"硬件") | C29: 元/台 | D29: 物料明细·硬件(272项) | Z29: 乌鲁木齐市
A30: 结构件 | B30: =SUMIFS(物料明细!$H:$H,物料明细!$B:$B,"结构件") | C30: 元/台 | D30: 物料明细·结构件(32项，含组装结构) | Z30: 塔城地区/白杨市/新星市/哈密市/昆玉市/和田地区/北屯市/阿勒泰地区/克孜勒苏柯尔克孜自治州/双河市/博尔塔拉蒙古自治州/克拉玛依市/胡杨河市/石河子市/五家渠市/昌吉回族自治州/吐鲁番市/巴音郭楞蒙古自治州/铁门关市/阿克苏地区/阿拉尔市/图木舒克市/喀什地区/伊犁哈萨克自治州/可克达拉市
A31: 散热器 | B31: =SUMIFS(物料明细!$H:$H,物料明细!$B:$B,"散热器") | C31: 元/台 | D31: 单独采购68元未税(参数B49)，源表未含 | Z31: 南京市/无锡市/苏州市/常州市
A32: 包装材料 | B32: =SUMIFS(物料明细!$H:$H,物料明细!$B:$B,"包装材料") | C32: 元/台 | D32: ="包装BOM实际(商空方案8项)；包装计算模型估算="&TEXT(包装计算!$B$43,"0.00")&"元/件，可互校" | Z32: 镇江市/南通市/扬州市
A33: 辅助材料 | B33: =SUMIFS(物料明细!$H:$H,物料明细!$B:$B,"辅助材料") | C33: 元/台 | D33: 物料明细·辅料(锡丝/助焊剂等，16项) | Z33: 盐城市/徐州市/淮安市/连云港市/泰州市/宿迁市
A34: 加工成本 | B34: =加工成本明细!$C$18 | C34: 元/台 | D34: 综合口径：人工+SMT+机插+折旧+水电+管理(加工成本明细)
A35: 小计(料工费) | B35: =SUM(B29:B34) | C35: 元/台 | D35: 材料+加工(源表口径+散热器68) | Z35: 天津市
A36: 成本差异 | B36: =B35*参数!$B$50 | C36: 元/台 | D36: 制造损耗/差异缓冲(参数B50，默认1.35%) | Z36: 长春市
A37: 运费 | B37: =IF(ISNUMBER(运费计算!$B$33),运费计算!$B$33,B35*参数!$B$51) | C37: 元/台 | D37: =IF(ISNUMBER(运费计算!$B$33),"跨越费率自动计算(运费计算表)","跨越费率未覆盖该目的地，按参数B51运费率回退") | Z37: 吉林市
A38: 利润加成 | B38: =SUM(B35:B37)*参数!$B$52 | C38: 元/台 | D38: 成本内加成(参数B52，商空默认0) | Z38: 延边朝鲜族自治州/四平市/通化市/白城市/辽源市/松原市/白山市
A39: 总成本未税 | B39: =SUM(B35:B38) | C39: 元/台 | D39: 主营业务成本(单台) | Z39: 银川市
Z40: 石嘴山市/吴忠市/固原市/中卫市
A41: 五、自动报价结果 | Z41: 石家庄市/廊坊市
A42: 报价项目 | B42: 结果 | C42: 单位 | D42: 备注 | E42: 公式 | Z42: 邯郸市/保定市/雄安新区/唐山市/沧州市/秦皇岛市
A43: 目标毛利率 | B43: =参数!B4 | C43: % | D43: 参数页可改(商空对齐源表0.3) | Z43: 张家口市/承德市/衡水市/邢台市
A44: 建议报价未税 | B44: =IFERROR(B39/(1-B43),0) | C44: 元/台 | D44: 总成本/(1-毛利率) | Z44: 开封市/郑州市
A45: 税率 | B45: =参数!B3 | C45: % | D45: 参数页可改 | Z45: 新乡市/许昌市/信阳市/洛阳市/鹤壁市
A46: 建议报价含税 | B46: =B44*(1+B45) | C46: 元/台 | D46: 未税价×(1+税率) | Z46: 商丘市/安阳市/平顶山市/南阳市/焦作市/济源市/濮阳市/周口市/漯河市/驻马店市/三门峡市
A47: 客户目标价 | C47: 元/台 | D47: 手工填写 | Z47: 崇左市/南宁市
A48: 目标价差异 | B48: =IF(B47="","",B44-B47) | C48: 元/台 | D48: 建议价-目标价 | Z48: 柳州市/来宾市/桂林市
A49: 报价毛利率 | B49: =IFERROR((B44-B39)/B44,0) | C49: % | D49: 自动计算 | Z49: 防城港市/梧州市/贺州市/贵港市/玉林市/百色市/钦州市/河池市/北海市
A50: 年销售额未税 | B50: =B44*B8 | C50: 元/年 | D50: 自动计算 | Z50: 屯昌县/五指山市/白沙黎族自治县/东方市/保亭黎族苗族自治县/琼中黎族苗族自治县/定安县/临高县/陵水黎族自治县/文昌市/海口市/万宁市/乐东黎族自治县/琼海市/澄迈县/昌江黎族自治县/儋州市/三亚市/三沙市
A51: 年毛利额 | B51: =IFERROR((B44-B39)*B8,0) | C51: 元/年 | D51: 自动计算 | Z51: 上海市
Z52: 南昌市
A53: 六、一次性费用（直接向客户收取，不计入单台成本） | Z53: 九江市/吉安市/赣州市
A54: 费用项目 | B54: 金额 | C54: 单位 | D54: 备注 | E54: 公式 | Z54: 鹰潭市/新余市/上饶市/抚州市/宜春市/景德镇市/萍乡市
A55: 工装治具费 | B55: =参数!B54 | C55: 元 | D55: 装配/测试/波峰焊/ICT等工装(加工成本明细·三) | Z55: 昆明市
A56: EPS泡沫模具费 | B56: =参数!B53 | C56: 元 | D56: 左右侧泡沫模具，N10305002124/25共用 | Z56: 大理白族自治州/曲靖市/玉溪市/楚雄彝族自治州
A57: 一次性合计 | B57: =SUM(B55:B56) | C57: 元 | D57: 向客户单独收取 | Z57: 西双版纳傣族自治州/德宏傣族景颇族自治州/昭通市/红河哈尼族彝族自治州/保山市/文山壮族苗族自治州/普洱市/临沧市/怒江傈僳族自治州/迪庆藏族自治州/丽江市
Z58: 兰州市
A59: 七、风险检查与对账 | Z59: 临夏回族自治州/定西市/平凉市/庆阳市/金昌市/武威市/张掖市/嘉峪关市/酒泉市/天水市/陇南市/甘南藏族自治州/白银市
A60: 检查项 | B60: 数值 | C60: 单位 | D60: 备注 | E60: 公式 | Z60: 西安市/咸阳市
A61: 客供料品项(清单) | B61: =COUNTIF(物料明细!$B:$B,"客供料") | C61: 项 | D61: 源表客供料清单8颗，金额不计入成本 | Z61: 宝鸡市/铜川市
A62: BOM内客供标记项 | B62: =COUNTIFS(物料明细!$B:$B,"硬件",物料明细!$I:$I,"是") | C62: 项 | D62: 硬件BOM中单价为0的国创客供料，应与上行一致 | Z62: 延安市/榆林市/渭南市/商洛市/安康市/汉中市
A63: 未报价物料(非客供) | B63: =COUNTIFS(物料明细!$H:$H,0,物料明细!$I:$I,"否") | C63: 项 | D63: 金额为0且非客供的物料需补价，0为正常 | Z63: 杭州市/嘉兴市/宁波市
A64: 客供料参考金额(导入清单) | B64: =SUMPRODUCT((物料明细!$B$3:$B$339="客供料")*物料明细!$E$3:$E$339*物料明细!$F$3:$F$339) | C64: 元/台 | D64: 按导入清单用量×单价计算，仅供参考不计入成本 | Z64: 湖州市/绍兴市/金华市
A65: 源表客供合计(对照) | B65: =参数!B55 | C65: 元/台 | D65: 源表合计554.3197；与上行差异属源表口径差，不影响报价 | Z65: 台州市/温州市
Z66: 衢州市/丽水市/舟山市
Z67: 呼和浩特市
Z68: 包头市
Z69: 呼伦贝尔市/乌海市/乌兰察布市/通辽市/赤峰市/鄂尔多斯市/巴彦淖尔市/锡林郭勒盟/兴安盟/阿拉善盟
Z70: 西宁市
Z71: 海北藏族自治州/海东市/黄南藏族自治州/海南藏族自治州/果洛藏族自治州/玉树藏族自治州/海西蒙古族藏族自治州
Z72: 抚顺市/本溪市/铁岭市/沈阳市/大连市
Z73: 鞍山市
Z74: 丹东市/锦州市/营口市/阜新市/辽阳市/朝阳市/盘锦市/葫芦岛市
Z75: 哈尔滨市
Z76: 齐齐哈尔市/牡丹江市/佳木斯市/绥化市/黑河市/大兴安岭地区/伊春市/大庆市/七台河市/鸡西市/鹤岗市/双鸭山市
Z77: 北京市
... Z120: 邯郸市/石家庄市/保定市/雄安新区/张家口市/承德市/唐山市/沧州市/衡水市/邢台市/秦皇岛市

Sheet 物料明细
A1: 物料明细
A2: 序号 | B2: 物料分类 | C2: 物料编码 | D2: 物料名称规格 | E2: 单机用量 | F2: 未税单价 | G2: 损耗率 | H2: 金额 | I2: 是否客供 | J2: 备注
A3: =IF(C3<>"",ROW()-2,"") | B3: 硬件 | C3: 301H030491 | D3: 片式电阻 RC0805FR-07300KL/0805W8F3003T5E 1/8W,300KΩ,1%,0805(国巨/厚声)(编带)(RoHS) | E3: 18 | F3: 0.0045 | H3: =IF(I3="是",0,IF(OR(E3="",F3=""),0,E3*F3*(1+IF(G3="",0,G3)))) | I3: 否 | J3: 深圳市超利维实业有限公司
A4: =IF(C4<>"",ROW()-2,"") | B4: 硬件 | C4: 306110396 | D4: 高压陶瓷电容 HGK3AF103ZG3AW 10nF,1KV,P=7.5(万明)(编带)(RoHS) | E4: 1 | F4: 0.1331 | H4: =IF(I4="是",0,IF(OR(E4="",F4=""),0,E4*F4*(1+IF(G4="",0,G4)))) | I4: 否 | J4: 厦门万明电子有限公司
A5: =IF(C5<>"",ROW()-2,"") | B5: 硬件 | C5: 3155US1M | D5: 超快恢复二极管 US1M 1A,1KV,SMA(强茂)(编带)(RoHS) | E5: 1 | F5: 0.0274 | H5: =IF(I5="是",0,IF(OR(E5="",F5=""),0,E5*F5*(1+IF(G5="",0,G5)))) | I5: 否 | J5: 厦门镁富莱工贸有限公司
A6: =IF(C6<>"",ROW()-2,"") | B6: 硬件 | C6: 604B03VHZ51R | D6: 端子 B3P-VH (JST)(RoHS) | E6: 1 | F6: 0.222 | H6: =IF(I6="是",0,IF(OR(E6="",F6=""),0,E6*F6*(1+IF(G6="",0,G6)))) | I6: 否 | J6: 深圳市恒有电子有限公司
A7: =IF(C7<>"",ROW()-2,"") | B7: 硬件 | C7: 604B05VHZ51R | D7: 端子 B5P-VH (JST)(RoHS) | E7: 2 | F7: 0.322 | H7: =IF(I7="是",0,IF(OR(E7="",F7=""),0,E7*F7*(1+IF(G7="",0,G7)))) | I7: 否 | J7: 深圳市恒有电子有限公司
A8: =IF(C8<>"",ROW()-2,"") | B8: 硬件 | C8: N30101000615 | D8: 片式电阻 RC1206JR-0775RL/1206W4J0750T5E 1/4W,75Ω,5%,1206(国巨/厚声)(编带)(RoHS) | E8: 1 | F8: 0.0045 | H8: =IF(I8="是",0,IF(OR(E8="",F8=""),0,E8*F8*(1+IF(G8="",0,G8)))) | I8: 否 | J8: 厚声国际贸易（昆山）有限公司
A9: =IF(C9<>"",ROW()-2,"") | B9: 硬件 | C9: N30101000894 | D9: 片式电阻 RC1206FR-0722RL/1206W4F220JT5E 1/4W,22Ω,1%,1206(国巨/厚声)(编带)(RoHS) | E9: 2 | F9: 0.0058 | H9: =IF(I9="是",0,IF(OR(E9="",F9=""),0,E9*F9*(1+IF(G9="",0,G9)))) | I9: 否 | J9: 厚声国际贸易（昆山）有限公司
A10: =IF(C10<>"",ROW()-2,"") | B10: 硬件 | C10: N30101001049 | D10: 片式电阻 RC1206FR-076R8L/1206W4F680KT5E 1/4W,6.8Ω,1%,1206(国巨/厚声)(编带)(RoHS) | E10: 2 | F10: 0.0083 | H10: =IF(I10="是",0,IF(OR(E10="",F10=""),0,E10*F10*(1+IF(G10="",0,G10)))) | I10: 否 | J10: 厚声国际贸易（昆山）有限公司
A11: =IF(C11<>"",ROW()-2,"") | B11: 硬件 | C11: N30101005306 | D11: 片式电阻 GMR320HJCFAR100 7W,100mΩ,1%,2817(Rohm)(编带)(RoHS) | E11: 2 | F11: 2.38 | H11: =IF(I11="是",0,IF(OR(E11="",F11=""),0,E11*F11*(1+IF(G11="",0,G11)))) | I11: 否 | J11: 北天星电子(深圳)有限公司
A12: =IF(C12<>"",ROW()-2,"") | B12: 硬件 | C12: N30101005309 | D12: 片式电阻 1210W2F3003T5E 1/2W,300KΩ,1%,1210(厚声)(编带)(RoHS) | E12: 8 | F12: 0.023 | H12: =IF(I12="是",0,IF(OR(E12="",F12=""),0,E12*F12*(1+IF(G12="",0,G12)))) | I12: 否 | J12: 厚声国际贸易（昆山）有限公司
A13: =IF(C13<>"",ROW()-2,"") | B13: 硬件 | C13: N30103000520 | D13: 金属膜电阻 MF02SJJ0364A10 2WS,360KΩ,5%(厚声)(HF;RoHS) | E13: 3 | F13: 0.065 | H13: =IF(I13="是",0,IF(OR(E13="",F13=""),0,E13*F13*(1+IF(G13="",0,G13)))) | I13: 否 | J13: 厚声国际贸易（昆山）有限公司
A14: =IF(C14<>"",ROW()-2,"") | B14: 硬件 | C14: N30103000526 | D14: 金属膜电阻 MF01WFF3003A10 1W,300KΩ,1%(厚声)(编带)(HF;RoHS) | E14: 1 | F14: 0.0828 | H14: =IF(I14="是",0,IF(OR(E14="",F14=""),0,E14*F14*(1+IF(G14="",0,G14)))) | I14: 否 | J14: 厚声国际贸易（昆山）有限公司
... A306: =IF(C306<>"",ROW()-2,"") | B306: 结构件 | C306: N71014000080 | D306: 塑胶线夹 CHA-5 白色(插销式线夹)(罗克)(RoHS) | E306: 1 | F306: 0.12 | H306: =IF(I306="是",0,IF(OR(E306="",F306=""),0,E306*F306*(1+IF(G306="",0,G306)))) | I306: 否 | J306: 厦门罗克科技有限公司
A307: =IF(C307<>"",ROW()-2,"") | B307: 散热器 | C307: HS-DRV26P | D307: 散热器（商空大功率驱动板，单独采购，未税） | E307: 1 | F307: =参数!$B$49 | H307: =IF(I307="是",0,IF(OR(E307="",F307=""),0,E307*F307*(1+IF(G307="",0,G307)))) | I307: 否 | J307: 源表未含，按68元未税单列
A308: =IF(C308<>"",ROW()-2,"") | B308: 包装材料 | C308: 4013430R | D308: 塑胶线夹 3.6X300 (尼龙扣)(正顺达)(RoHS) | E308: 2 | F308: 0.099 | H308: =IF(I308="是",0,IF(OR(E308="",F308=""),0,E308*F308*(1+IF(G308="",0,G308)))) | I308: 否 | J308: 厦门正顺达电子有限公司
A309: =IF(C309<>"",ROW()-2,"") | B309: 包装材料 | C309: N40501000405 | D309: 纸箱 665X393X405 (RoHS) | E309: 1 | F309: 10.98 | H309: =IF(I309="是",0,IF(OR(E309="",F309=""),0,E309*F309*(1+IF(G309="",0,G309)))) | I309: 否 | J309: 厦门比瑞特包装科技有限公司
A310: =IF(C310<>"",ROW()-2,"") | B310: 包装材料 | C310: N40505000136 | D310: 塑料袋 355X245 (凹凸)(RoHS) | E310: 1 | F310: 0.25 | H310: =IF(I310="是",0,IF(OR(E310="",F310=""),0,E310*F310*(1+IF(G310="",0,G310)))) | I310: 否 | J310: 厦门比瑞特包装科技有限公司
A311: =IF(C311<>"",ROW()-2,"") | B311: 包装材料 | C311: N40505000140 | D311: 塑料袋 372X322X700 (防静电,厚度0.1mm)(RoHS) | E311: 1 | F311: 3.39 | H311: =IF(I311="是",0,IF(OR(E311="",F311=""),0,E311*F311*(1+IF(G311="",0,G311)))) | I311: 否 | J311: 厦门比瑞特包装科技有限公司
A312: =IF(C312<>"",ROW()-2,"") | B312: 包装材料 | C312: N40511000095 | D312: 泡沫 660×399×115 (EPS料,右侧，DRV-20P,26P包装用)(RoHS) | E312: 1 | F312: 22.1 | H312: =IF(I312="是",0,IF(OR(E312="",F312=""),0,E312*F312*(1+IF(G312="",0,G312)))) | I312: 否 | J312: 厦门鹏源鑫工贸有限公司；含EPS泡沫模具(见一次性费用)
A313: =IF(C313<>"",ROW()-2,"") | B313: 包装材料 | C313: N40511000096 | D313: 泡沫 660×399×146 (EPS料,左侧，DRV-20P,26P包装用)(RoHS) | E313: 1 | F313: 24.7 | H313: =IF(I313="是",0,IF(OR(E313="",F313=""),0,E313*F313*(1+IF(G313="",0,G313)))) | I313: 否 | J313: 厦门鹏源鑫工贸有限公司；含EPS泡沫模具(见一次性费用)
A314: =IF(C314<>"",ROW()-2,"") | B314: 包装材料 | C314: N40512000282 | D314: 泡沫棉 40X20X199 (右侧EVA棉块2)(高密度)(防静电)(RoHS) | E314: 2 | F314: 1.0619 | H314: =IF(I314="是",0,IF(OR(E314="",F314=""),0,E314*F314*(1+IF(G314="",0,G314)))) | I314: 否 | J314: 厦门市达唯工贸有限公司
A315: =IF(C315<>"",ROW()-2,"") | B315: 包装材料 | C315: N60703001395 | D315: 标签 BQ12080W001-HL (格式标签)(1寸卷芯,外径83mm)(RoHS) | E315: 1 | F315: 0.0347 | H315: =IF(I315="是",0,IF(OR(E315="",F315=""),0,E315*F315*(1+IF(G315="",0,G315)))) | I315: 否 | J315: 厦门亿华辉工贸有限公司（ZZ）
A316: =IF(C316<>"",ROW()-2,"") | B316: 辅助材料 | C316: N40716000018 | D316: 锡丝 BSD620-W Sn0.3Ag0.7Cu(φ3.0)(博士达)(RoHS) | E316: 0.001723778 | F316: 309.2832 | H316: =IF(I316="是",0,IF(OR(E316="",F316=""),0,E316*F316*(1+IF(G316="",0,G316)))) | I316: 否 | J316: KG
A317: =IF(C317<>"",ROW()-2,"") | B317: 辅助材料 | C317: N40716000015 | D317: 锡丝 YTW101 Sn0.7Cu,Flux2.4％(φ0.8)(亚通)(RoHS) | E317: 0.099898221 | F317: 265.4779 | H317: =IF(I317="是",0,IF(OR(E317="",F317=""),0,E317*F317*(1+IF(G317="",0,G317)))) | I317: 否 | J317: KG 按V3.0计算用量
A318: =IF(C318<>"",ROW()-2,"") | B318: 辅助材料 | C318: 458F007 | D318: 助焊剂 TF-328 (深圳同方)(RoHS) | E318: 0.005 | F318: 15.8828 | H318: =IF(I318="是",0,IF(OR(E318="",F318=""),0,E318*F318*(1+IF(G318="",0,G318)))) | I318: 否 | J318: L
A319: =IF(C319<>"",ROW()-2,"") | B319: 辅助材料 | C319: 409012 | D319: 导热硅脂 HZ-KS101 (百合花)(RoHS) | E319: 0.0049 | F319: 6.1538 | H319: =IF(I319="是",0,IF(OR(E319="",F319=""),0,E319*F319*(1+IF(G319="",0,G319)))) | I319: 否 | J319: BOT
... A339: =IF(C339<>"",ROW()-2,"") | B339: 客供料 | C339: 客供9 | D339: MCU R5F526T8ADFM/LQFP64 | E339: 2 | F339: 7.75 | H339: =IF(I339="是",0,IF(OR(E339="",F339=""),0,E339*F339*(1+IF(G339="",0,G339)))) | I339: 是 | J339: 客供不计入报价；瑞萨 新晔 12W

Sheet 制费明细
A1: 制费明细（工程报价表格式 P01~P07：自下而上工序估算工具）｜注：商空项目加工成本以「加工成本明细」综合表为准
A3: 客户 | B3: =报价汇总!B6 | C3: 机型 | D3: =报价汇总!B4 | E3: 预计订单(pcs) | G3: =报价汇总!B8 | H3: 联动报价汇总年需求量(B8)；夹具一次性费用分摊分母
A4: 人工费率(元/秒) | B4: 0.0089138889 | C4: 32.09元/小时÷3600 | D4: 宽放系数 | E4: 1.1 | F4: 烧录/成型/组装共用 | G4: 费率来源：003/009参考报价反推（0.0588元÷6.6s），可按实际改
A6: P01 SMT贴片（费用 = 工艺单价 × 元件个数）
A7: 项目 | B7: 工序名称 | C7: 元件类型 | D7: 工艺单价(元) | E7: 元件个数 | F7: 备注 | G7: 费用(元) | H7: 说明
A8: P01 | B8: SMT | C8: 0603/0402 | D8: 0.019 | E8: 56 | G8: =IFERROR(D8*E8,0)
C9: 1206/0805 | D9: 0.02 | E9: 4 | G9: =IFERROR(D9*E9,0)
C10: 二/三极管 | D10: 0.02 | E10: 0 | G10: =IFERROR(D10*E10,0)
C11: 按键/插座 | D11: 0.06 | E11: 4 | G11: =IFERROR(D11*E11,0)
C12: 电感/MOS管/EC等 | D12: 0.035 | E12: 1 | G12: =IFERROR(D12*E12,0)
C13: 贴片IC | D13: 0.018 | E13: 9 | F13: 每4个pin为1个元件 | G13: =IFERROR(D13*E13,0)
C14: 模块 | D14: 0.142 | E14: 0 | G14: =IFERROR(D14*E14,0)
C15: SMT成本(元) | G15: =SUM(G8:G14)
A17: P02 烧录（工序工时 = 工作时间 × 工序个数 × 宽放；成本 = 工时 × 人工费率）
A18: 项目 | B18: 工序名称 | C18: 工艺流程 | D18: 工作时间(s) | E18: 工序个数 | F18: 宽放系数 | G18: 工序工时(s) | H18: 费用(元)
A19: P02 | B19: SL | C19: 离线烧录 | D19: 6 | E19: 1 | F19: =$E$4 | G19: =D19*E19*F19 | H19: =G19*$B$4
C20: 在线烧录 | D20: 3 | E20: 0 | F20: =$E$4 | G20: =D20*E20*F20 | H20: =G20*$B$4
C21: 烧录成本(元) | H21: =SUM(H19:H20)
A23: P03 AI/RI 机插（费用 = 单价 × 个数 × 宽放）
A24: 项目 | B24: 工序名称 | C24: 元件类型 | D24: 工艺单价(元) | E24: 元件个数 | F24: 宽放系数 | G24: 费用(元) | H24: 说明
A25: P03 | B25: AI/RI | C25: 电阻/二极管 | D25: 0.025 | E25: 0 | F25: =$E$4 | G25: =IFERROR(D25*E25*F25,0)
C26: 跳线 | D26: 0.022 | E26: 0 | F26: =$E$4 | G26: =IFERROR(D26*E26*F26,0)
C27: RI | D27: 0.025 | E27: 0 | F27: =$E$4 | G27: =IFERROR(D27*E27*F27,0)
C28: AI成本(元) | G28: =SUM(G25:G27)
A30: P04 成型（工序工时 = 工作时间 × 元件数量 × 宽放；成本 = 工时 × 人工费率）
A31: 项目 | B31: 工序名称 | C31: 工艺流程 | D31: 工作时间(s) | E31: 元件数量 | F31: 宽放系数 | G31: 工序工时(s) | H31: 费用(元)
A32: P04 | B32: 成型 | C32: 电解电容 | D32: 1.2 | E32: 0 | F32: =$E$4 | G32: =D32*E32*F32 | H32: =G32*$B$4
C33: 贴板成型 | D33: 1.8 | E33: 0 | F33: =$E$4 | G33: =D33*E33*F33 | H33: =G33*$B$4
C34: 自动成型 | D34: 0.6 | E34: 0 | F34: =$E$4 | G34: =D34*E34*F34 | H34: =G34*$B$4
C35: 晶闸管成型 | D35: 6 | E35: 0 | F35: =$E$4 | G35: =D35*E35*F35 | H35: =G35*$B$4
C36: 散热器组装 | D36: 20 | E36: 0 | F36: =$E$4 | G36: =D36*E36*F36 | H36: =G36*$B$4
C37: 光敏电阻成型 | D37: 8 | E37: 0 | F37: =$E$4 | G37: =D37*E37*F37 | H37: =G37*$B$4
C38: 铆钉 | D38: 0.5 | E38: 0 | F38: =$E$4 | G38: =D38*E38*F38 | H38: =G38*$B$4
C39: 成型成本(元) | H39: =SUM(H32:H38)
A41: P05 组装（18道工序：工序工时 = 工作节拍 × 工序个数 × 宽放；成本 = 工时 × 人工费率）
A42: 项目 | B42: 工序名称 | C42: 工艺流程 | D42: 工作节拍(s) | E42: 工序个数 | F42: 宽放系数 | G42: 工序工时(s) | H42: 费用(元)
A43: P05 | B43: 组装 | C43: 安装过炉治具 | D43: 3 | E43: 1 | F43: =$E$4 | G43: =D43*E43*F43 | H43: =G43*$B$4
C44: 插件 | D44: 3 | E44: 1 | F44: =$E$4 | G44: =D44*E44*F44 | H44: =G44*$B$4
C45: 插件QC | D45: 3 | E45: 1 | F45: =$E$4 | G45: =D45*E45*F45 | H45: =G45*$B$4
C46: 卸送治具/AVI检测 | D46: 3 | E46: 2 | F46: =$E$4 | G46: =D46*E46*F46 | H46: =G46*$B$4
C47: 压件/执锡 | D47: 3 | E47: 2 | F47: =$E$4 | G47: =D47*E47*F47 | H47: =G47*$B$4
C48: 炉后QC/洗板 | D48: 3 | E48: 2 | F48: =$E$4 | G48: =D48*E48*F48 | H48: =G48*$B$4
C49: ICT | D49: 3 | E49: 1 | F49: =$E$4 | G49: =D49*E49*F49 | H49: =G49*$B$4
C50: 分板 | D50: 3 | E50: 1 | F50: =$E$4 | G50: =D50*E50*F50 | H50: =G50*$B$4
C51: FCT | D51: 3 | E51: 4 | F51: =$E$4 | G51: =D51*E51*F51 | H51: =G51*$B$4
C52: 点胶 | D52: 3 | E52: 0 | F52: =$E$4 | G52: =D52*E52*F52 | H52: =G52*$B$4
C53: 打螺钉 | D53: 3 | E53: 0 | F53: =$E$4 | G53: =D53*E53*F53 | H53: =G53*$B$4
C54: 喷漆/收板/补胶 | D54: 3 | E54: 4 | F54: =$E$4 | G54: =D54*E54*F54 | H54: =G54*$B$4
C55: 喷漆检查 | D55: 3 | E55: 1 | F55: =$E$4 | G55: =D55*E55*F55 | H55: =G55*$B$4
... C60: 助拉 | D60: 3 | E60: 1 | F60: =$E$4 | G60: =D60*E60*F60 | H60: =G60*$B$4
C61: 组装成本(元) | H61: =SUM(H43:H60)
A62: 加工费合计(元) | H62: =$G$15+$H$21+$G$28+$H$39+$H$61
A64: P06 辅料费｜注：商空项目辅料用量已置0，辅料已导入BOM「辅助材料」，此处避免与报价汇总重复计费
A65: 项目 | B65: 费用类型 | C65: 辅料类型 | D65: 单价(元/g) | E65: 单片用量(g) | F65: 宽放系数 | G65: 辅料费用(元) | H65: 说明
A66: P06 | B66: 辅料费用 | C66: 标签 | D66: 0.04 | E66: 0 | F66: 1 | G66: =IFERROR(D66*E66*F66,0) | H66: 元/个
C67: 助焊剂 | D67: 0.019 | E67: 0 | F67: 1.2 | G67: =IFERROR(D67*E67*F67,0)
C68: 锡条(g) | D68: 0.279 | E68: 0 | F68: 1.1 | G68: =IFERROR(D68*E68*F68,0)
C69: 锡丝(g) | D69: 0.196 | E69: 0 | F69: 1.2 | G69: =IFERROR(D69*E69*F69,0)
C70: 胶类(g) | D70: 0.04 | E70: 0 | F70: 1.1 | G70: =IFERROR(D70*E70*F70,0)
C71: 漆(g) | D71: 0.21 | E71: 0 | F71: 1.2 | G71: =IFERROR(D71*E71*F71,0) | H71: 三防漆
C72: A/B胶(g) | D72: 0.024 | E72: 0 | F72: 1.2 | G72: =IFERROR(D72*E72*F72,0)
C73: 辅料成本(元) | G73: =SUM(G66:G72)
A75: P07 治具/夹具费｜注：商空项目夹具张数已置0，工装48700元直接向客户收取，见报价汇总「六、一次性费用」，不计入单台成本
A76: 项目 | B76: 费用类型 | C76: 夹具类型 | D76: 单价(元) | E76: 个/张数 | F76: 备注 | G76: 夹具费用(元) | H76: 说明
A77: P07 | B77: 夹具费用 | C77: 钢网 | D77: 265 | E77: 0 | G77: =IFERROR(D77*E77,0)
C78: 印刷辅助治具 | D78: 1000 | E78: 0 | G78: =IFERROR(D78*E78,0)
C79: 过锡炉治具 | D79: 350 | E79: 0 | G79: =IFERROR(D79*E79,0)
C80: 焊接治具 | D80: 1500 | E80: 0 | G80: =IFERROR(D80*E80,0)
C81: 铆钉模具 | D81: 20000 | E81: 0 | G81: =IFERROR(D81*E81,0)
C82: 分板治具 | D82: 800 | E82: 0 | G82: =IFERROR(D82*E82,0)
C83: ICT治具 | D83: 8000 | E83: 0 | G83: =IFERROR(D83*E83,0)
C84: 烧录工装 | D84: 4000 | E84: 0 | G84: =IFERROR(D84*E84,0)
C85: FCT工装 | D85: 8000 | E85: 0 | G85: =IFERROR(D85*E85,0)
C86: OQC检验工装 | D86: 4000 | E86: 0 | G86: =IFERROR(D86*E86,0)
C87: 喷漆治具 | D87: 800 | E87: 0 | G87: =IFERROR(D87*E87,0)
C88: 灌胶治具 | D88: 300 | E88: 0 | G88: =IFERROR(D88*E88,0)
C89: 夹具一次性总费用(元) | G89: =SUM(G77:G88)
C90: 夹具单片分担费用(元) | G90: =IFERROR($G$89/$G$3,0) | H90: 单片分担=一次性总费用÷预计订单数(G3)
A91: 单片制造成本合计(元) | H91: =$H$62+$G$73+$G$90
A93: 制作： 审核： 核准： 批准日期：

Sheet 加工成本明细
A1: 加工成本明细（商空大功率驱动板·综合加工成本构成）
A3: 一、加工成本构成（元/台，综合口径：人工+制费+SMT/机插）
A4: 序号 | B4: 成本组成 | C4: 金额(元/台) | F4: 说明
A5: 1 | B5: 贴片加工成本 | C5: 6.1656 | F5: SMT贴片 1101.001点×0.0056
A6: 2 | B6: 机插加工成本 | C6: 0.2394 | F6: AI机插 14点×0.0171
A7: 3 | B7: 预烧写加工成本 | C7: 0 | F7: 本项目无
A8: 4 | B8: 人工成本 | C8: 82.0882 | F8: 插焊/测试/组装等直接人工（详见二）
A9: 5 | B9: 折旧（专用） | C9: 0.8424 | F9: 专用设备折旧
A10: 6 | B10: 折旧（公共） | C10: 2.2 | F10: 公共设备折旧分摊
A11: 7 | B11: 水电（专用） | C11: 1.4745 | F11: 专用水电
A12: 8 | B12: 水电（公共） | C12: 1.4776 | F12: 公共水电分摊
A13: 9 | B13: 工装 | C13: 0 | F13: 工装直接向客户收取（详见三），不计入单台
A14: 10 | B14: 低值易耗 | C14: 4.5477 | F14: 低值易耗品摊销
A15: 11 | B15: 管理人员工资 | C15: 21.3676 | F15: 制造管理费用分摊
A16: 12 | B16: 其他 | C16: 6.0253 | F16: 其他制造费用
A17: 13 | B17: 检验成本 | C17: 0 | F17: 本项目未单列
B18: 加工成本合计(元/台) | C18: =SUM(C5:C17) | F18: → 报价汇总「四、成本构成」加工成本行
A20: 二、人工工时定额明细（源表未提供逐行人工成本，人工成本合计82.0882元见上）
A21: 序号 | B21: 生产分段 | C21: 工序类别 | D21: 生产定额 | E21: 人数 | F21: 备注
A22: 1 | B22: 装配段 | C22: 装配 | D22: 12 | E22: 10
A23: 2 | B23: 装配段 | C23: FCT | D23: 12 | E23: 2
A24: 3 | B24: 装配段 | C24: 外观检验 | D24: 12 | E24: 2
A25: 4 | B25: 装配段 | C25: OQC | D25: 12 | E25: 0.24
A26: 5 | B26: 装配段 | C26: 产前准备 | D26: 12 | E26: 0.6
A27: 6 | B27: 装配段 | C27: 杂项设备 | D27: 12 | E27: 0.6
A28: 7 | B28: 装配段 | C28: 维修清尾 | D28: 12 | E28: 0.36
A29: 8 | B29: 装配段 | C29: 包装 | D29: 12 | E29: 2
A30: 9 | B30: 插焊段 | C30: 焊接 | D30: 80 | E30: 5
A31: 10 | B31: 插焊段 | C31: 插件 | D31: 80 | E31: 9
A32: 11 | B32: 插焊段 | C32: 维修清尾 | D32: 80 | E32: 0.5
A33: 12 | B33: 插焊段 | C33: 喷漆 | D33: 80 | E33: 0.6
... A73: 52 | B73: 插焊段 | C73: 产前准备 | D73: 240 | E73: 0.6
C74: 人工成本合计(元/台) | D74: 82.0882 | F74: 源表人工成本为汇总值，逐行成本不可拆分
A76: 三、工装治具明细（一次性，直接向客户收取，不计入单台成本）
A77: 序号 | B77: 工艺/名称 | C77: 数量 | D77: 单价(元) | E77: 金额(元) | F77: 年产能/单片分摊
A78: 1 | B78: 装配/装配工装 | C78: 2 | D78: 2000 | E78: 4000 | F78: 年5000/单片0.2667
A79: 2 | B79: 自动测试/测试工装 | C79: 2 | D79: 4000 | E79: 8000 | F79: 年5000/单片0.5333
A80: 3 | B80: 波峰焊/波峰焊托盘 | C80: 15 | D80: 300 | E80: 4500 | F80: 年5000/单片0.3
A81: 4 | B81: 双面喷漆/喷漆托盘 | C81: 0 | D81: 0 | E81: 0 | F81: 年5000/单片0
A82: 5 | B82: 自动测试/自动测试工装 | C82: 2 | D82: 4000 | E82: 8000 | F82: 年5000/单片0.5333
A83: 6 | B83: ICT/ICT针床 | C83: 1 | D83: 0 | E83: 0 | F83: 年5000/单片0
A84: 7 | B84: 装配/装配工装 | C84: 3 | D84: 0 | E84: 0 | F84: 年5000/单片0
A85: 8 | B85: 自动焊锡机/自动焊接 | C85: 3 | D85: 400 | E85: 1200 | F85: 年5000/单片0.08
A86: 9 | B86: 双面喷漆/喷漆托盘 | C86: 15 | D86: 0 | E86: 0 | F86: 年5000/单片0
A87: 10 | B87: ICT/ICT针床 | C87: 1 | D87: 0 | E87: 0 | F87: 年5000/单片0
A88: 11 | B88: 自动测试/自动测试 | C88: 3 | D88: 0 | E88: 0 | F88: 年5000/单片0
A89: 12 | B89: 波峰焊/波峰焊托盘 | C89: 0 | D89: 0 | E89: 0 | F89: 年0/单片0
... A93: 16 | B93: ICT/ICT针床 | C93: 1 | D93: 3500 | E93: 3500 | F93: 年5000/单片0.2333
B94: 工装治具合计(元) | E94: =SUM(E78:E93) | F94: 直接向客户收取 → 报价汇总「六、一次性费用」
A95: 制作： 审核： 核准： 批准日期：

Sheet 参数
A1: 参数设置
A2: 参数项 | B2: 参数值 | C2: 说明
A3: 税率 | B3: 0.13 | C3: 增值税率，默认13%
A4: 目标毛利率 | B4: 0.3 | C4: 报价目标毛利率
A5: 默认损耗率 | B5: 0.02 | C5: 物料未填损耗率时使用
A6: 默认分摊数量 | B6: 5000 | C6: 工装治具费用默认分摊数量
A8: 二、包装与整托参数
A9: 参数项 | B9: 参数值 | C9: 单位 | D9: 说明
A10: 防静电气泡袋单价 | B10: 2.5 | C10: 元/㎡
A11: 气泡袋单边余量 | B11: 30 | C11: mm
A12: 干燥剂单价 | B12: 0.1 | C12: 元/袋
A13: 湿度指示卡单价 | B13: 0.3 | C13: 元/张
A14: EPE珍珠棉单价 | B14: 1800 | C14: 元/m³
A15: EPE珍珠棉密度 | B15: 22 | C15: kg/m³
A16: 单瓦楞3层纸板 | B16: 2 | C16: 元/㎡
A17: 双瓦楞5层纸板 | B17: 3.2 | C17: 元/㎡
A18: 重型7层纸板 | B18: 5 | C18: 元/㎡
A19: 双瓦楞纸板克重 | B19: 700 | C19: g/㎡
A20: 纸箱制箱加工费 | B20: 1.5 | C20: 元/个
A21: 材料损耗率 | B21: 0.05 | C21: 比例
... A32: 每托层数 | B32: 4 | C32: 层
A34: 三、物流参数
A35: 参数项 | B35: 参数值 | C35: 单位 | D35: 说明
A36: 体积重系数 | B36: 6000 | C36: ㎝³/kg
A37: 保费费率 | B37: 0.004 | C37: ‰即0.4%
A38: 保费最低收费 | B38: 5 | C38: 元/票
A39: 是否计保费 | B39: 否 | C39: 是/否
A41: 四、包装方案参数（小板/大板）
A42: 参数项 | B42: 参数值 | C42: 单位 | D42: 说明
A43: 防静电气泡袋克重 | B43: 60 | C43: g/㎡ | D43: 气泡袋面密度
A44: 隔板单价 | B44: 0.3 | C44: 元/件 | D44: 小板每件隔板
A45: 隔板克重 | B45: 20 | C45: g/件 | D45: 小板隔板重量
A46: 默认装配工时费 | B46: 60 | C46: 元/小时 | D46: 首页可按项目覆盖
A48: 五、商空大功率项目专用参数
A49: 散热器单价(未税,元) | B49: 68
A50: 成本差异率(制造损耗缓冲) | B50: 0.0135
A51: 运费费率(跨越不覆盖时备用) | B51: 0.0116
A52: 成本内利润加成率(商空默认0) | B52: 0
A53: EPS泡沫模具费(一次性,元) | B53: 29499.115
A54: 工装治具费(一次性,直接收取,元) | B54: 48700
A55: 客供料合计(参考,不计入成本,元) | B55: 554.3197

Sheet 包装计算
A1: 包装费计算（自动，按包装方案清单）
A3: 一、输入（自动取自报价汇总）
A4: 成品长(mm) | B4: =报价汇总!B13
A5: 成品宽(mm) | B5: =报价汇总!B14
A6: 成品高(mm) | B6: =报价汇总!B15
A7: 每箱件数N | B7: =报价汇总!B17
A8: 是否含整托 | B8: =报价汇总!B18
A9: 包装方案(自动) | B9: =IF(OR(报价汇总!B19="是",报价汇总!B20="是"),"大板","小板")
A11: 二、包装几何（自动）
A12: 成品最大边长(mm) | B12: =MAX(B4:B6)
A13: 缓冲厚度t(mm) | B13: =VLOOKUP($B$12,$A$58:$D$61,3,TRUE())
A14: 箱内长(mm) | B14: =B4+2*B13+参数!$B$22
A15: 箱内宽(mm) | B15: =B5+2*B13+参数!$B$22
A16: 箱内高(mm) | B16: =B7*(B6+2*B13)+参数!$B$22
A17: 单箱体积(㎝³) | B17: =B14*B15*B16/1000
A19: 三、内包装材料费（单件）
A20: 气泡袋长(mm) | B20: =B4+B6+2*参数!$B$11
A21: 气泡袋宽(mm) | B21: =B5+B6+2*参数!$B$11
A22: 气泡袋面积(㎡) | B22: =B20*B21/10^6
A23: 气泡袋费(元/件) | B23: =B22*参数!$B$10
A24: 隔板费(元/件) | B24: =IF($B$9="小板",IF(OR($B$7="",$B$7=0),0,参数!$B$44*MAX($B$7-1,0)/$B$7),0)
A25: EPE体积(垫片+护角,㎥/件) | B25: =(2*B4*B5*B13+4*B13*B13*B6)/10^9
A26: EPE费(元/件) | B26: =B25*参数!$B$14
A27: 内包材料费(元/件) | B27: =IF($B$9="小板",B23+B24,B26)
A28: 纸箱用纸面积(㎡) | B28: =(B14+B15)*2*(B15+2*B16)/10^6*(1+参数!$B$21)
A29: 瓦楞类型 | B29: =VLOOKUP($B$12,$A$58:$D$61,4,TRUE())
A30: 纸板单价(元/㎡) | B30: =VLOOKUP(B29,$A$65:$B$67,2,FALSE())
A31: 纸箱费(元/箱) | B31: =B28*B30+参数!$B$20
A32: 纸箱费(元/件) | B32: =IF(OR(B7="",B7=0),0,B31/B7)
A33: 辅料费(元/件) | B33: =IF(OR(B7="",B7=0),0,(参数!$B$23+参数!$B$24)/B7)
A34: 内包装单件费(元) | B34: =B27+B32+B33
A36: 四、整托分摊（可选，勾选含整托生效）
A37: 每箱占地(㎡) | B37: =B14*B15/10^6
A38: 每托件数(件) | B38: =IF(OR(B37="",B37=0),0,ROUNDDOWN(参数!$B$31/B37,0)*参数!$B$32)
A39: 每托包装费(元/托) | B39: =参数!$B$29+参数!$B$25/参数!$B$26+参数!$B$27*参数!$B$28+IF($B$9="大板",参数!$B$30,0)
A40: 整托分摊(元/件) | B40: =IF(OR(B38="",B38=0),0,B39/B38)
A41: 包装增重(kg/件) | B41: =IF(OR(B7="",B7=0),0,IF($B$9="小板",B22*参数!$B$43/1000,B25*参数!$B$15)+B28*参数!$B$19/1000/B7+IF($B$9="小板",参数!$B$45/1000*MAX($B$7-1,0)/$B$7,0)+0.005)
A43: 包装费合计(元/件) | B43: =B34+IF($B$8="是",B40,0)
A45: 五、包装方案清单对照（√=该方案包含）
A46: 包装物料 | B46: 单位 | C46: 单价(元) | D46: 小板 | E46: 大板
A47: 防静电气泡袋 | B47: 元/㎡ | C47: =参数!$B$10 | D47: √ | E47: —
A48: 隔板 | B48: 元/件 | C48: =参数!$B$44 | D48: √ | E48: —
A49: EPE珍珠棉 | B49: 元/m³ | C49: =参数!$B$14 | D49: — | E49: √
A50: 纸箱 | B50: 元/箱 | C50: 按面积×瓦楞 | D50: √ | E50: √
A51: 护角 | B51: 元/套 | C51: =参数!$B$29 | D51: √ | E51: √
A52: 托盘 | B52: 元/托 | C52: =参数!$B$25/参数!$B$26 | D52: √ | E52: √
A53: 缠绕膜 | B53: 元/托 | C53: =参数!$B$27*参数!$B$28 | D53: √ | E53: √
A54: 打包带 | B54: 元/托 | C54: =参数!$B$30 | D54: — | E54: √
A55: 口径：气泡袋按袋面积×单价；隔板=(N-1)/N×单价；大板EPE=上下垫片(2×长×宽×t)+四角护角(4×t×t×高)体积×单价；纸箱按面积×单价÷N；护角/托盘/缠绕膜/打包带按整托费用÷每托件数。
A56: 六、成品最大边长档位表（自动匹配缓冲厚度/瓦楞）
A57: 下限mm | B57: 上限mm | C57: 缓冲厚度mm | D57: 瓦楞
A58: 0 | B58: 200 | C58: 15 | D58: 单瓦楞3层
A59: 200 | B59: 350 | C59: 20 | D59: 双瓦楞5层
A60: 350 | B60: 550 | C60: 25 | D60: 双瓦楞5层
A61: 550 | B61: 999999 | C61: 30 | D61: 重型7层
A63: 七、瓦楞单价映射
A64: 瓦楞类型 | B64: 纸板单价(元/㎡)
A65: 单瓦楞3层 | B65: =参数!$B$16
A66: 双瓦楞5层 | B66: =参数!$B$17
A67: 重型7层 | B67: =参数!$B$18

Sheet 跨越费率
A1: 跨越VIP运费费率（源自青岛国创VIP报价表，可按需改价）
A3: 产品 | B3: 目的省份 | C3: 目的地 | D3: 首重重量 | E3: 首重价格 | F3: 起重 | G3: 最低收费 | H3: 段1单价 | I3: 段2单价 | J3: 段3单价 | K3: 段4单价 | L3: 段5单价 | M3: 段6单价 | N3: 段7单价 | O3: 段8单价 | P3: 段9单价 | Q3: 匹配键
A4: 次日达 | B4: 福建省 | C4: 福州市/厦门市/泉州市 | D4: 1 | E4: 20 | F4: 30 | G4: 255 | H4: 8.1 | I4: 8.1 | J4: 8.1 | K4: 8.1 | L4: 7.2 | M4: 6.3 | N4: 6.3 | O4: 6.3 | P4: 6.3 | Q4: 次日达|福州市/厦门市/泉州市
A5: 次日达 | C5: 宁德市/莆田市/漳州市 | D5: 1 | E5: 20 | F5: 30 | G5: 255 | H5: 8.1 | I5: 8.1 | J5: 8.1 | K5: 8.1 | L5: 7.2 | M5: 6.3 | N5: 6.3 | O5: 6.3 | P5: 6.3 | Q5: 次日达|宁德市/莆田市/漳州市
A6: 次日达 | C6: 龙岩市/三明市/南平市 | D6: 1 | E6: 20 | F6: 30 | G6: 255 | H6: 8.1 | I6: 8.1 | J6: 8.1 | K6: 8.1 | L6: 7.2 | M6: 6.3 | N6: 6.3 | O6: 6.3 | P6: 6.3 | Q6: 次日达|龙岩市/三明市/南平市
A7: 次日达 | B7: 西藏自治区 | C7: 拉萨市 | D7: 1 | E7: 20 | F7: 30 | G7: 542 | H7: 18 | I7: 18 | J7: 18 | K7: 18 | L7: 18 | M7: 18 | N7: 18 | O7: 18 | P7: 18 | Q7: 次日达|拉萨市
A8: 次日达 | C8: 日喀则市/山南市/林芝市/昌都市/那曲市/阿里地区 | D8: 1 | E8: 25 | F8: 30 | G8: 678 | H8: 22.5 | I8: 22.5 | J8: 22.5 | K8: 22.5 | L8: 22.5 | M8: 22.5 | N8: 22.5 | O8: 22.5 | P8: 22.5 | Q8: 次日达|日喀则市/山南市/林芝市/昌都市/那曲市/阿里地区
A9: 次日达 | B9: 贵州省 | C9: 贵阳市/遵义市/安顺市 | D9: 1 | E9: 20 | F9: 30 | G9: 307 | H9: 9.9 | I9: 9.9 | J9: 9.9 | K9: 9 | L9: 9 | M9: 8.1 | N9: 8.1 | O9: 8.1 | P9: 8.1 | Q9: 次日达|贵阳市/遵义市/安顺市
A10: 次日达 | C10: 黔南布依族苗族自治州/黔东南苗族侗族自治州/铜仁市/毕节市/六盘水市/黔西南布依族苗族自治州 | D10: 1 | E10: 20 | F10: 30 | G10: 307 | H10: 9.9 | I10: 9.9 | J10: 9.9 | K10: 9 | L10: 9 | M10: 8.1 | N10: 8.1 | O10: 8.1 | P10: 8.1 | Q10: 次日达|黔南布依族苗族自治州/黔东南苗族侗族自治州/铜仁市/毕节市/六盘水市/黔西南布依族苗族自治州
A11: 次日达 | B11: 广东省 | C11: 广州市/深圳市/珠海市/中山市/东莞市 | D11: 1 | E11: 20 | F11: 15 | G11: 171 | H11: 10.8 | I11: 10.8 | J11: 10.8 | K11: 9.9 | L11: 9 | M11: 8.1 | N11: 8.1 | O11: 8.1 | P11: 8.1 | Q11: 次日达|广州市/深圳市/珠海市/中山市/东莞市
A12: 次日达 | C12: 江门市/惠州市/佛山市/肇庆市 | D12: 1 | E12: 20 | F12: 15 | G12: 171 | H12: 10.8 | I12: 10.8 | J12: 10.8 | K12: 9.9 | L12: 9 | M12: 8.1 | N12: 8.1 | O12: 8.1 | P12: 8.1 | Q12: 次日达|江门市/惠州市/佛山市/肇庆市
A13: 次日达 | C13: 汕尾市/阳江市/揭阳市/茂名市/韶关市/梅州市/汕头市/湛江市/河源市/清远市/云浮市/潮州市 | D13: 1 | E13: 20 | F13: 15 | G13: 171 | H13: 10.8 | I13: 10.8 | J13: 10.8 | K13: 9.9 | L13: 9 | M13: 8.1 | N13: 8.1 | O13: 8.1 | P13: 8.1 | Q13: 次日达|汕尾市/阳江市/揭阳市/茂名市/韶关市/梅州市/汕头市/湛江市/河源市/清远市/云浮市/潮州市
A14: 次日达 | B14: 湖北省 | C14: 武汉市/鄂州市 | D14: 1 | E14: 20 | F14: 30 | G14: 255 | H14: 8.1 | I14: 8.1 | J14: 8.1 | K14: 8.1 | L14: 7.2 | M14: 6.3 | N14: 6.3 | O14: 6.3 | P14: 6.3 | Q14: 次日达|武汉市/鄂州市
A15: 次日达 | C15: 襄阳市/孝感市/黄石市/荆州市/宜昌市/神农架林区/十堰市/随州市/荆门市 | D15: 1 | E15: 20 | F15: 30 | G15: 255 | H15: 8.1 | I15: 8.1 | J15: 8.1 | K15: 8.1 | L15: 7.2 | M15: 6.3 | N15: 6.3 | O15: 6.3 | P15: 6.3 | Q15: 次日达|襄阳市/孝感市/黄石市/荆州市/宜昌市/神农架林区/十堰市/随州市/荆门市
A16: 次日达 | C16: 黄冈市/咸宁市/恩施土家族苗族自治州/潜江市/仙桃市/天门市 | D16: 1 | E16: 20 | F16: 30 | G16: 307 | H16: 9.9 | I16: 9.9 | J16: 9.9 | K16: 9.9 | L16: 9 | M16: 8.1 | N16: 8.1 | O16: 8.1 | P16: 8.1 | Q16: 次日达|黄冈市/咸宁市/恩施土家族苗族自治州/潜江市/仙桃市/天门市
A17: 次日达 | B17: 湖南省 | C17: 株洲市/长沙市/湘潭市 | D17: 1 | E17: 20 | F17: 30 | G17: 255 | H17: 8.1 | I17: 8.1 | J17: 8.1 | K17: 8.1 | L17: 7.2 | M17: 6.3 | N17: 6.3 | O17: 6.3 | P17: 6.3 | Q17: 次日达|株洲市/长沙市/湘潭市
A18: 次日达 | C18: 益阳市 | D18: 1 | E18: 20 | F18: 30 | G18: 255 | H18: 8.1 | I18: 8.1 | J18: 8.1 | K18: 8.1 | L18: 7.2 | M18: 6.3 | N18: 6.3 | O18: 6.3 | P18: 6.3 | Q18: 次日达|益阳市
A19: 次日达 | C19: 岳阳市/衡阳市/郴州市/常德市/娄底市/邵阳市/湘西土家族苗族自治州/张家界市/怀化市/永州市 | D19: 1 | E19: 20 | F19: 30 | G19: 307 | H19: 9.9 | I19: 9.9 | J19: 9.9 | K19: 9.9 | L19: 9 | M19: 8.1 | N19: 8.1 | O19: 8.1 | P19: 8.1 | Q19: 次日达|岳阳市/衡阳市/郴州市/常德市/娄底市/邵阳市/湘西土家族苗族自治州/张家界市/怀化市/永州市
A20: 次日达 | B20: 重庆 | C20: 重庆市 | D20: 1 | E20: 20 | F20: 30 | G20: 255 | H20: 8.1 | I20: 8.1 | J20: 8.1 | K20: 8.1 | L20: 7.2 | M20: 7.2 | N20: 7.2 | O20: 7.2 | P20: 7.2 | Q20: 次日达|重庆市
A21: 次日达 | B21: 四川省 | C21: 成都市/资阳市/眉山市 | D21: 1 | E21: 20 | F21: 30 | G21: 255 | H21: 8.1 | I21: 8.1 | J21: 8.1 | K21: 8.1 | L21: 7.2 | M21: 7.2 | N21: 7.2 | O21: 7.2 | P21: 7.2 | Q21: 次日达|成都市/资阳市/眉山市
A22: 次日达 | C22: 绵阳市 | D22: 1 | E22: 20 | F22: 30 | G22: 255 | H22: 8.1 | I22: 8.1 | J22: 8.1 | K22: 8.1 | L22: 7.2 | M22: 7.2 | N22: 7.2 | O22: 7.2 | P22: 7.2 | Q22: 次日达|绵阳市
A23: 次日达 | C23: 自贡市/南充市/达州市/遂宁市/广安市/巴中市/泸州市/宜宾市/内江市/乐山市/雅安市/德阳市/广元市 | D23: 1 | E23: 20 | F23: 30 | G23: 307 | H23: 9.9 | I23: 9.9 | J23: 9.9 | K23: 9.9 | L23: 9 | M23: 9 | N23: 9 | O23: 9 | P23: 9 | Q23: 次日达|自贡市/南充市/达州市/遂宁市/广安市/巴中市/泸州市/宜宾市/内江市/乐山市/雅安市/德阳市/广元市
A24: 次日达 | C24: 攀枝花市/凉山彝族自治州/甘孜藏族自治州/阿坝藏族羌族自治州 | D24: 1 | E24: 20 | F24: 30 | G24: 385 | H24: 12.6 | I24: 12.6 | J24: 12.6 | K24: 12.6 | L24: 11.7 | M24: 11.7 | N24: 11.7 | O24: 11.7 | P24: 11.7 | Q24: 次日达|攀枝花市/凉山彝族自治州/甘孜藏族自治州/阿坝藏族羌族自治州
A25: 次日达 | B25: 安徽省 | C25: 合肥市/芜湖市/马鞍山市 | D25: 1 | E25: 20 | F25: 30 | G25: 255 | H25: 8.1 | I25: 8.1 | J25: 8.1 | K25: 8.1 | L25: 7.2 | M25: 6.3 | N25: 6.3 | O25: 6.3 | P25: 6.3 | Q25: 次日达|合肥市/芜湖市/马鞍山市
A26: 次日达 | C26: 滁州市/蚌埠市/六安市 | D26: 1 | E26: 20 | F26: 30 | G26: 281 | H26: 9 | I26: 9 | J26: 9 | K26: 9 | L26: 8.1 | M26: 7.2 | N26: 7.2 | O26: 7.2 | P26: 7.2 | Q26: 次日达|滁州市/蚌埠市/六安市
A27: 次日达 | C27: 淮南市/安庆市/宿州市/亳州市/阜阳市/黄山市/淮北市/铜陵市/宣城市/池州市 | D27: 1 | E27: 20 | F27: 30 | G27: 307 | H27: 9.9 | I27: 9.9 | J27: 9.9 | K27: 9.9 | L27: 9 | M27: 8.1 | N27: 8.1 | O27: 8.1 | P27: 8.1 | Q27: 次日达|淮南市/安庆市/宿州市/亳州市/阜阳市/黄山市/淮北市/铜陵市/宣城市/池州市
A28: 次日达 | B28: 新疆维吾尔自治区 | C28: 乌鲁木齐市 | D28: 1 | E28: 20 | F28: 30 | G28: 542 | H28: 18 | I28: 18 | J28: 18 | K28: 18 | L28: 18 | M28: 18 | N28: 18 | O28: 18 | P28: 18 | Q28: 次日达|乌鲁木齐市
A29: 次日达 | C29: 塔城地区/白杨市/新星市/哈密市/昆玉市/和田地区/北屯市/阿勒泰地区/克孜勒苏柯尔克孜自治州/双河市/博尔塔拉蒙古自治州/克拉玛依市/胡杨河市/石河子市/五家渠市/昌吉回族自治州/吐鲁番市/巴音郭楞蒙古自治州/铁门关市/阿克苏地区/阿拉尔市/图木舒克市/喀什地区/伊犁哈萨克自治州/可克达拉市 | D29: 1 | E29: 25 | F29: 30 | G29: 678 | H29: 22.5 | I29: 22.5 | J29: 22.5 | K29: 22.5 | L29: 22.5 | M29: 22.5 | N29: 22.5 | O29: 22.5 | P29: 22.5 | Q29: 次日达|塔城地区/白杨市/新星市/哈密市/昆玉市/和田地区/北屯市/阿勒泰地区/克孜勒苏柯尔克孜自治州/双河市/博尔塔拉蒙古自治州/克拉玛依市/胡杨河市/石河子市/五家渠市/昌吉回族自治州/吐鲁番市/巴音郭楞蒙古自治州/铁门关市/阿克苏地区/阿拉尔市/图木舒克市/喀什地区/伊犁哈萨克自治州/可克达拉市
A30: 次日达 | B30: 江苏省 | C30: 南京市/无锡市/苏州市/常州市 | D30: 1 | E30: 20 | F30: 15 | G30: 133 | H30: 8.1 | I30: 8.1 | J30: 8.1 | K30: 7.2 | L30: 6.3 | M30: 6.3 | N30: 6.3 | O30: 6.3 | P30: 6.3 | Q30: 次日达|南京市/无锡市/苏州市/常州市
A31: 次日达 | C31: 镇江市/南通市/扬州市 | D31: 1 | E31: 20 | F31: 15 | G31: 133 | H31: 8.1 | I31: 8.1 | J31: 8.1 | K31: 7.2 | L31: 6.3 | M31: 6.3 | N31: 6.3 | O31: 6.3 | P31: 6.3 | Q31: 次日达|镇江市/南通市/扬州市
A32: 次日达 | C32: 盐城市/徐州市/淮安市/连云港市/泰州市/宿迁市 | D32: 1 | E32: 20 | F32: 15 | G32: 133 | H32: 8.1 | I32: 8.1 | J32: 8.1 | K32: 7.2 | L32: 6.3 | M32: 6.3 | N32: 6.3 | O32: 6.3 | P32: 6.3 | Q32: 次日达|盐城市/徐州市/淮安市/连云港市/泰州市/宿迁市
A33: 次日达 | B33: 天津 | C33: 天津市 | D33: 1 | E33: 20 | F33: 20 | G33: 157 | H33: 7.2 | I33: 7.2 | J33: 7.2 | K33: 7.2 | L33: 6.3 | M33: 6.3 | N33: 6.3 | O33: 6.3 | P33: 6.3 | Q33: 次日达|天津市
A34: 次日达 | B34: 吉林省 | C34: 长春市 | D34: 1 | E34: 20 | F34: 30 | G34: 333 | H34: 10.8 | I34: 10.8 | J34: 10.8 | K34: 9.9 | L34: 9.9 | M34: 9 | N34: 9 | O34: 9 | P34: 9 | Q34: 次日达|长春市
A35: 次日达 | C35: 吉林市 | D35: 1 | E35: 20 | F35: 30 | G35: 359 | H35: 11.7 | I35: 11.7 | J35: 11.7 | K35: 10.8 | L35: 10.8 | M35: 9.9 | N35: 9.9 | O35: 9.9 | P35: 9.9 | Q35: 次日达|吉林市
A36: 次日达 | C36: 延边朝鲜族自治州/四平市/通化市/白城市/辽源市/松原市/白山市 | D36: 1 | E36: 20 | F36: 30 | G36: 412 | H36: 13.5 | I36: 13.5 | J36: 13.5 | K36: 12.6 | L36: 12.6 | M36: 11.7 | N36: 11.7 | O36: 11.7 | P36: 11.7 | Q36: 次日达|延边朝鲜族自治州/四平市/通化市/白城市/辽源市/松原市/白山市
A37: 次日达 | B37: 宁夏回族自治区 | C37: 银川市 | D37: 1 | E37: 20 | F37: 30 | G37: 490 | H37: 16.2 | I37: 16.2 | J37: 16.2 | K37: 14.4 | L37: 14.4 | M37: 14.4 | N37: 13.5 | O37: 13.5 | P37: 13.5 | Q37: 次日达|银川市
A38: 次日达 | C38: 石嘴山市/吴忠市/固原市/中卫市 | D38: 1 | E38: 20 | F38: 30 | G38: 542 | H38: 18 | I38: 18 | J38: 18 | K38: 16.2 | L38: 16.2 | M38: 16.2 | N38: 15.3 | O38: 15.3 | P38: 15.3 | Q38: 次日达|石嘴山市/吴忠市/固原市/中卫市
A39: 次日达 | B39: 河北省 | C39: 石家庄市/廊坊市 | D39: 1 | E39: 20 | F39: 30 | G39: 229 | H39: 7.2 | I39: 7.2 | J39: 7.2 | K39: 7.2 | L39: 7.2 | M39: 6.3 | N39: 6.3 | O39: 6.3 | P39: 6.3 | Q39: 次日达|石家庄市/廊坊市
A40: 次日达 | C40: 邯郸市/保定市/雄安新区/唐山市/沧州市/秦皇岛市 | D40: 1 | E40: 20 | F40: 30 | G40: 255 | H40: 8.1 | I40: 8.1 | J40: 8.1 | K40: 8.1 | L40: 8.1 | M40: 7.2 | N40: 7.2 | O40: 7.2 | P40: 7.2 | Q40: 次日达|邯郸市/保定市/雄安新区/唐山市/沧州市/秦皇岛市
A41: 次日达 | C41: 张家口市/承德市/衡水市/邢台市 | D41: 1 | E41: 20 | F41: 30 | G41: 281 | H41: 9 | I41: 9 | J41: 9 | K41: 9 | L41: 9 | M41: 8.1 | N41: 8.1 | O41: 8.1 | P41: 8.1 | Q41: 次日达|张家口市/承德市/衡水市/邢台市
A42: 次日达 | B42: 河南省 | C42: 开封市/郑州市 | D42: 1 | E42: 20 | F42: 30 | G42: 229 | H42: 7.2 | I42: 7.2 | J42: 7.2 | K42: 7.2 | L42: 7.2 | M42: 6.3 | N42: 6.3 | O42: 6.3 | P42: 6.3 | Q42: 次日达|开封市/郑州市
A43: 次日达 | C43: 新乡市/许昌市/信阳市/洛阳市/鹤壁市 | D43: 1 | E43: 20 | F43: 30 | G43: 255 | H43: 8.1 | I43: 8.1 | J43: 8.1 | K43: 8.1 | L43: 8.1 | M43: 7.2 | N43: 7.2 | O43: 7.2 | P43: 7.2 | Q43: 次日达|新乡市/许昌市/信阳市/洛阳市/鹤壁市
A44: 次日达 | C44: 商丘市/安阳市/平顶山市/南阳市/焦作市/济源市/濮阳市/周口市/漯河市/驻马店市/三门峡市 | D44: 1 | E44: 20 | F44: 30 | G44: 281 | H44: 9 | I44: 9 | J44: 9 | K44: 9 | L44: 9 | M44: 8.1 | N44: 8.1 | O44: 8.1 | P44: 8.1 | Q44: 次日达|商丘市/安阳市/平顶山市/南阳市/焦作市/济源市/濮阳市/周口市/漯河市/驻马店市/三门峡市
A45: 次日达 | B45: 广西壮族自治区 | C45: 崇左市/南宁市 | D45: 1 | E45: 20 | F45: 30 | G45: 307 | H45: 9.9 | I45: 9.9 | J45: 9.9 | K45: 9 | L45: 9 | M45: 8.1 | N45: 8.1 | O45: 8.1 | P45: 8.1 | Q45: 次日达|崇左市/南宁市
A46: 次日达 | C46: 柳州市/来宾市/桂林市 | D46: 1 | E46: 20 | F46: 30 | G46: 333 | H46: 10.8 | I46: 10.8 | J46: 10.8 | K46: 9.9 | L46: 9.9 | M46: 9 | N46: 9 | O46: 9 | P46: 9 | Q46: 次日达|柳州市/来宾市/桂林市
A47: 次日达 | C47: 防城港市/梧州市/贺州市/贵港市/玉林市/百色市/钦州市/河池市/北海市 | D47: 1 | E47: 20 | F47: 30 | G47: 385 | H47: 12.6 | I47: 12.6 | J47: 12.6 | K47: 11.7 | L47: 11.7 | M47: 10.8 | N47: 10.8 | O47: 10.8 | P47: 10.8 | Q47: 次日达|防城港市/梧州市/贺州市/贵港市/玉林市/百色市/钦州市/河池市/北海市
A48: 次日达 | B48: 海南省 | C48: 屯昌县/五指山市/白沙黎族自治县/东方市/保亭黎族苗族自治县/琼中黎族苗族自治县/定安县/临高县/陵水黎族自治县/文昌市/海口市/万宁市/乐东黎族自治县/琼海市/澄迈县/昌江黎族自治县/儋州市/三亚市/三沙市 | D48: 1 | E48: 20 | F48: 30 | G48: 281 | H48: 9 | I48: 9 | J48: 9 | K48: 8.1 | L48: 7.2 | M48: 7.2 | N48: 7.2 | O48: 7.2 | P48: 7.2 | Q48: 次日达|屯昌县/五指山市/白沙黎族自治县/东方市/保亭黎族苗族自治县/琼中黎族苗族自治县/定安县/临高县/陵水黎族自治县/文昌市/海口市/万宁市/乐东黎族自治县/琼海市/澄迈县/昌江黎族自治县/儋州市/三亚市/三沙市
A49: 次日达 | B49: 上海 | C49: 上海市 | D49: 1 | E49: 20 | F49: 15 | G49: 133 | H49: 8.1 | I49: 8.1 | J49: 8.1 | K49: 7.2 | L49: 6.3 | M49: 6.3 | N49: 6.3 | O49: 6.3 | P49: 6.3 | Q49: 次日达|上海市
A50: 次日达 | B50: 江西省 | C50: 南昌市 | D50: 1 | E50: 20 | F50: 30 | G50: 255 | H50: 8.1 | I50: 8.1 | J50: 8.1 | K50: 8.1 | L50: 7.2 | M50: 6.3 | N50: 6.3 | O50: 6.3 | P50: 6.3 | Q50: 次日达|南昌市
A51: 次日达 | C51: 九江市/吉安市/赣州市 | D51: 1 | E51: 20 | F51: 30 | G51: 255 | H51: 8.1 | I51: 8.1 | J51: 8.1 | K51: 8.1 | L51: 7.2 | M51: 6.3 | N51: 6.3 | O51: 6.3 | P51: 6.3 | Q51: 次日达|九江市/吉安市/赣州市
A52: 次日达 | C52: 鹰潭市/新余市/上饶市/抚州市/宜春市/景德镇市/萍乡市 | D52: 1 | E52: 20 | F52: 30 | G52: 307 | H52: 9.9 | I52: 9.9 | J52: 9.9 | K52: 9.9 | L52: 9 | M52: 8.1 | N52: 8.1 | O52: 8.1 | P52: 8.1 | Q52: 次日达|鹰潭市/新余市/上饶市/抚州市/宜春市/景德镇市/萍乡市
A53: 次日达 | B53: 云南省 | C53: 昆明市 | D53: 1 | E53: 20 | F53: 30 | G53: 307 | H53: 9.9 | I53: 9.9 | J53: 9.9 | K53: 9 | L53: 9 | M53: 8.1 | N53: 8.1 | O53: 8.1 | P53: 8.1 | Q53: 次日达|昆明市
A54: 次日达 | C54: 大理白族自治州/曲靖市/玉溪市/楚雄彝族自治州 | D54: 1 | E54: 20 | F54: 30 | G54: 307 | H54: 9.9 | I54: 9.9 | J54: 9.9 | K54: 9 | L54: 9 | M54: 8.1 | N54: 8.1 | O54: 8.1 | P54: 8.1 | Q54: 次日达|大理白族自治州/曲靖市/玉溪市/楚雄彝族自治州
A55: 次日达 | C55: 西双版纳傣族自治州/德宏傣族景颇族自治州/昭通市/红河哈尼族彝族自治州/保山市/文山壮族苗族自治州/普洱市/临沧市/怒江傈僳族自治州/迪庆藏族自治州/丽江市 | D55: 1 | E55: 20 | F55: 30 | G55: 307 | H55: 9.9 | I55: 9.9 | J55: 9.9 | K55: 9 | L55: 9 | M55: 8.1 | N55: 8.1 | O55: 8.1 | P55: 8.1 | Q55: 次日达|西双版纳傣族自治州/德宏傣族景颇族自治州/昭通市/红河哈尼族彝族自治州/保山市/文山壮族苗族自治州/普洱市/临沧市/怒江傈僳族自治州/迪庆藏族自治州/丽江市
A56: 次日达 | B56: 甘肃省 | C56: 兰州市 | D56: 1 | E56: 20 | F56: 30 | G56: 490 | H56: 16.2 | I56: 16.2 | J56: 16.2 | K56: 16.2 | L56: 16.2 | M56: 15.3 | N56: 14.4 | O56: 14.4 | P56: 14.4 | Q56: 次日达|兰州市
A57: 次日达 | C57: 临夏回族自治州/定西市/平凉市/庆阳市/金昌市/武威市/张掖市/嘉峪关市/酒泉市/天水市/陇南市/甘南藏族自治州/白银市 | D57: 1 | E57: 20 | F57: 30 | G57: 542 | H57: 18 | I57: 18 | J57: 18 | K57: 18 | L57: 17.1 | M57: 17.1 | N57: 16.2 | O57: 16.2 | P57: 16.2 | Q57: 次日达|临夏回族自治州/定西市/平凉市/庆阳市/金昌市/武威市/张掖市/嘉峪关市/酒泉市/天水市/陇南市/甘南藏族自治州/白银市
A58: 次日达 | B58: 陕西省 | C58: 西安市/咸阳市 | D58: 1 | E58: 20 | F58: 30 | G58: 255 | H58: 8.1 | I58: 8.1 | J58: 8.1 | K58: 8.1 | L58: 7.2 | M58: 7.2 | N58: 7.2 | O58: 7.2 | P58: 7.2 | Q58: 次日达|西安市/咸阳市
A59: 次日达 | C59: 宝鸡市/铜川市 | D59: 1 | E59: 20 | F59: 30 | G59: 281 | H59: 9 | I59: 9 | J59: 9 | K59: 9 | L59: 8.1 | M59: 8.1 | N59: 8.1 | O59: 8.1 | P59: 8.1 | Q59: 次日达|宝鸡市/铜川市
A60: 次日达 | C60: 延安市/榆林市/渭南市/商洛市/安康市/汉中市 | D60: 1 | E60: 20 | F60: 30 | G60: 307 | H60: 9.9 | I60: 9.9 | J60: 9.9 | K60: 9.9 | L60: 9 | M60: 9 | N60: 9 | O60: 9 | P60: 9 | Q60: 次日达|延安市/榆林市/渭南市/商洛市/安康市/汉中市
A61: 次日达 | B61: 浙江省 | C61: 杭州市/嘉兴市/宁波市 | D61: 1 | E61: 20 | F61: 15 | G61: 133 | H61: 8.1 | I61: 8.1 | J61: 8.1 | K61: 7.2 | L61: 6.3 | M61: 6.3 | N61: 6.3 | O61: 6.3 | P61: 6.3 | Q61: 次日达|杭州市/嘉兴市/宁波市
A62: 次日达 | C62: 湖州市/绍兴市/金华市 | D62: 1 | E62: 20 | F62: 15 | G62: 133 | H62: 8.1 | I62: 8.1 | J62: 8.1 | K62: 7.2 | L62: 6.3 | M62: 6.3 | N62: 6.3 | O62: 6.3 | P62: 6.3 | Q62: 次日达|湖州市/绍兴市/金华市
A63: 次日达 | C63: 台州市/温州市 | D63: 1 | E63: 20 | F63: 15 | G63: 159 | H63: 9.9 | I63: 9.9 | J63: 9.9 | K63: 9 | L63: 8.1 | M63: 8.1 | N63: 8.1 | O63: 8.1 | P63: 8.1 | Q63: 次日达|台州市/温州市
A64: 次日达 | C64: 衢州市/丽水市/舟山市 | D64: 1 | E64: 20 | F64: 30 | G64: 281 | H64: 9 | I64: 9 | J64: 9 | K64: 8.1 | L64: 7.2 | M64: 6.3 | N64: 6.3 | O64: 6.3 | P64: 6.3 | Q64: 次日达|衢州市/丽水市/舟山市
A65: 次日达 | B65: 内蒙古自治区 | C65: 呼和浩特市 | D65: 1 | E65: 20 | F65: 30 | G65: 438 | H65: 14.4 | I65: 14.4 | J65: 14.4 | K65: 12.6 | L65: 12.6 | M65: 12.6 | N65: 12.6 | O65: 11.7 | P65: 11.7 | Q65: 次日达|呼和浩特市
A66: 次日达 | C66: 包头市 | D66: 1 | E66: 20 | F66: 30 | G66: 438 | H66: 14.4 | I66: 14.4 | J66: 14.4 | K66: 12.6 | L66: 12.6 | M66: 12.6 | N66: 12.6 | O66: 11.7 | P66: 11.7 | Q66: 次日达|包头市
A67: 次日达 | C67: 呼伦贝尔市/乌海市/乌兰察布市/通辽市/赤峰市/鄂尔多斯市/巴彦淖尔市/锡林郭勒盟/兴安盟/阿拉善盟 | D67: 1 | E67: 20 | F67: 30 | G67: 516 | H67: 17.1 | I67: 17.1 | J67: 17.1 | K67: 15.3 | L67: 15.3 | M67: 15.3 | N67: 15.3 | O67: 14.4 | P67: 14.4 | Q67: 次日达|呼伦贝尔市/乌海市/乌兰察布市/通辽市/赤峰市/鄂尔多斯市/巴彦淖尔市/锡林郭勒盟/兴安盟/阿拉善盟
A68: 次日达 | B68: 青海省 | C68: 西宁市 | D68: 1 | E68: 20 | F68: 30 | G68: 490 | H68: 16.2 | I68: 16.2 | J68: 16.2 | K68: 14.4 | L68: 14.4 | M68: 14.4 | N68: 13.5 | O68: 13.5 | P68: 13.5 | Q68: 次日达|西宁市
A69: 次日达 | C69: 海北藏族自治州/海东市/黄南藏族自治州/海南藏族自治州/果洛藏族自治州/玉树藏族自治州/海西蒙古族藏族自治州 | D69: 1 | E69: 20 | F69: 30 | G69: 542 | H69: 18 | I69: 18 | J69: 18 | K69: 16.2 | L69: 16.2 | M69: 16.2 | N69: 15.3 | O69: 15.3 | P69: 15.3 | Q69: 次日达|海北藏族自治州/海东市/黄南藏族自治州/海南藏族自治州/果洛藏族自治州/玉树藏族自治州/海西蒙古族藏族自治州
A70: 次日达 | B70: 辽宁省 | C70: 抚顺市/本溪市/铁岭市/沈阳市/大连市 | D70: 1 | E70: 20 | F70: 30 | G70: 255 | H70: 8.1 | I70: 8.1 | J70: 8.1 | K70: 8.1 | L70: 8.1 | M70: 8.1 | N70: 8.1 | O70: 8.1 | P70: 8.1 | Q70: 次日达|抚顺市/本溪市/铁岭市/沈阳市/大连市
A71: 次日达 | C71: 鞍山市 | D71: 1 | E71: 20 | F71: 30 | G71: 263 | H71: 9 | I71: 8.1 | J71: 8.1 | K71: 8.1 | L71: 7.2 | M71: 7.2 | N71: 7.2 | O71: 7.2 | P71: 7.2 | Q71: 次日达|鞍山市
A72: 次日达 | C72: 丹东市/锦州市/营口市/阜新市/辽阳市/朝阳市/盘锦市/葫芦岛市 | D72: 1 | E72: 20 | F72: 30 | G72: 307 | H72: 9.9 | I72: 9.9 | J72: 9.9 | K72: 9.9 | L72: 9.9 | M72: 9.9 | N72: 9.9 | O72: 9.9 | P72: 9.9 | Q72: 次日达|丹东市/锦州市/营口市/阜新市/辽阳市/朝阳市/盘锦市/葫芦岛市
A73: 次日达 | B73: 黑龙江省 | C73: 哈尔滨市 | D73: 1 | E73: 20 | F73: 30 | G73: 333 | H73: 10.8 | I73: 10.8 | J73: 10.8 | K73: 9.9 | L73: 9.9 | M73: 9 | N73: 9 | O73: 9 | P73: 9 | Q73: 次日达|哈尔滨市
A74: 次日达 | C74: 齐齐哈尔市/牡丹江市/佳木斯市/绥化市/黑河市/大兴安岭地区/伊春市/大庆市/七台河市/鸡西市/鹤岗市/双鸭山市 | D74: 1 | E74: 20 | F74: 30 | G74: 385 | H74: 12.6 | I74: 12.6 | J74: 12.6 | K74: 11.7 | L74: 11.7 | M74: 10.8 | N74: 10.8 | O74: 10.8 | P74: 10.8 | Q74: 次日达|齐齐哈尔市/牡丹江市/佳木斯市/绥化市/黑河市/大兴安岭地区/伊春市/大庆市/七台河市/鸡西市/鹤岗市/双鸭山市
A75: 次日达 | B75: 北京 | C75: 北京市 | D75: 1 | E75: 20 | F75: 20 | G75: 157 | H75: 7.2 | I75: 7.2 | J75: 7.2 | K75: 7.2 | L75: 6.3 | M75: 6.3 | N75: 6.3 | O75: 6.3 | P75: 6.3 | Q75: 次日达|北京市
A76: 次日达 | B76: 山西省 | C76: 太原市/晋中市 | D76: 1 | E76: 20 | F76: 30 | G76: 307 | H76: 9.9 | I76: 9.9 | J76: 9.9 | K76: 9 | L76: 9 | M76: 9 | N76: 9 | O76: 9 | P76: 9 | Q76: 次日达|太原市/晋中市
A77: 次日达 | C77: 朔州市/忻州市/大同市/阳泉市/长治市/晋城市/临汾市/吕梁市/运城市 | D77: 1 | E77: 20 | F77: 30 | G77: 359 | H77: 11.7 | I77: 11.7 | J77: 11.7 | K77: 10.8 | L77: 10.8 | M77: 10.8 | N77: 10.8 | O77: 10.8 | P77: 10.8 | Q77: 次日达|朔州市/忻州市/大同市/阳泉市/长治市/晋城市/临汾市/吕梁市/运城市
A78: 特惠普运 | B78: 广西壮族自治区 | C78: 崇左市/南宁市 | D78: 1 | E78: 10 | F78: 50 | G78: 108 | H78: 2 | I78: 2 | J78: 1.9 | K78: 1.9 | L78: 1.8 | M78: 1.7 | N78: 1.6 | O78: 1.5 | P78: 0 | Q78: 特惠普运|崇左市/南宁市
A79: 特惠普运 | C79: 防城港市/桂林市/贵港市/玉林市/钦州市/北海市 | D79: 1 | E79: 10 | F79: 50 | G79: 113 | H79: 2.1 | I79: 2.1 | J79: 2 | K79: 2 | L79: 1.9 | M79: 1.8 | N79: 1.7 | O79: 1.6 | P79: 0 | Q79: 特惠普运|防城港市/桂林市/贵港市/玉林市/钦州市/北海市
A80: 特惠普运 | B80: 福建省 | C80: 厦门市 | D80: 1 | E80: 10 | F80: 50 | G80: 98 | H80: 1.8 | I80: 1.8 | J80: 1.6 | K80: 1.6 | L80: 1.5 | M80: 1.45 | N80: 1.35 | O80: 1.25 | P80: 0 | Q80: 特惠普运|厦门市
A81: 特惠普运 | C81: 莆田市/泉州市/漳州市/龙岩市 | D81: 1 | E81: 10 | F81: 50 | G81: 98 | H81: 1.8 | I81: 1.8 | J81: 1.7 | K81: 1.7 | L81: 1.6 | M81: 1.5 | N81: 1.4 | O81: 1.4 | P81: 0 | Q81: 特惠普运|莆田市/泉州市/漳州市/龙岩市
A82: 特惠普运 | C82: 福州市 | D82: 1 | E82: 10 | F82: 50 | G82: 101 | H82: 1.85 | I82: 1.85 | J82: 1.7 | K82: 1.7 | L82: 1.6 | M82: 1.5 | N82: 1.4 | O82: 1.3 | P82: 0 | Q82: 特惠普运|福州市
A83: 特惠普运 | C83: 宁德市/三明市/南平市 | D83: 1 | E83: 10 | F83: 50 | G83: 106 | H83: 1.95 | I83: 1.95 | J83: 1.75 | K83: 1.75 | L83: 1.65 | M83: 1.6 | N83: 1.5 | O83: 1.4 | P83: 0 | Q83: 特惠普运|宁德市/三明市/南平市
A84: 特惠普运 | B84: 山西省/河北省 | C84: 邯郸市/保定市/雄安新区/衡水市/邢台市/阳泉市 | D84: 1 | E84: 10 | F84: 50 | G84: 88 | H84: 1.6 | I84: 1.6 | J84: 1.5 | K84: 1.5 | L84: 1.3 | M84: 1.2 | N84: 1.1 | O84: 1 | P84: 0 | Q84: 特惠普运|邯郸市/保定市/雄安新区/衡水市/邢台市/阳泉市
A85: 特惠普运 | B85: 湖南省/贵州省 | C85: 郴州市/张家界市/怀化市/永州市/铜仁市 | D85: 1 | E85: 10 | F85: 50 | G85: 103 | H85: 1.9 | I85: 1.9 | J85: 1.7 | K85: 1.7 | L85: 1.6 | M85: 1.5 | N85: 1.4 | O85: 1.3 | P85: 0 | Q85: 特惠普运|郴州市/张家界市/怀化市/永州市/铜仁市
A86: 特惠普运 | B86: 贵州省 | C86: 贵阳市 | D86: 1 | E86: 10 | F86: 50 | G86: 118 | H86: 2.2 | I86: 2.2 | J86: 2 | K86: 2 | L86: 1.9 | M86: 1.8 | N86: 1.7 | O86: 1.7 | P86: 0 | Q86: 特惠普运|贵阳市
A87: 特惠普运 | C87: 遵义市/安顺市 | D87: 1 | E87: 10 | F87: 50 | G87: 123 | H87: 2.3 | I87: 2.3 | J87: 2.1 | K87: 2.1 | L87: 2 | M87: 1.9 | N87: 1.8 | O87: 1.8 | P87: 0 | Q87: 特惠普运|遵义市/安顺市
A88: 特惠普运 | B88: 江西省 | C88: 南昌市 | D88: 1 | E88: 10 | F88: 50 | G88: 93 | H88: 1.7 | I88: 1.7 | J88: 1.5 | K88: 1.5 | L88: 1.4 | M88: 1.3 | N88: 1.2 | O88: 1.1 | P88: 0 | Q88: 特惠普运|南昌市
A89: 特惠普运 | C89: 鹰潭市/新余市/九江市/上饶市/抚州市/吉安市/赣州市/景德镇市 | D89: 1 | E89: 10 | F89: 50 | G89: 93 | H89: 1.7 | I89: 1.7 | J89: 1.6 | K89: 1.6 | L89: 1.5 | M89: 1.4 | N89: 1.3 | O89: 1.2 | P89: 0 | Q89: 特惠普运|鹰潭市/新余市/九江市/上饶市/抚州市/吉安市/赣州市/景德镇市
A90: 特惠普运 | B90: 湖北省 | C90: 武汉市 | D90: 1 | E90: 10 | F90: 50 | G90: 84 | H90: 1.5 | I90: 1.5 | J90: 1.4 | K90: 1.4 | L90: 1.3 | M90: 1.2 | N90: 1.1 | O90: 1 | P90: 0 | Q90: 特惠普运|武汉市
A91: 特惠普运 | C91: 襄阳市/荆州市/宜昌市/恩施土家族苗族自治州/神农架林区/十堰市/荆门市 | D91: 1 | E91: 10 | F91: 50 | G91: 93 | H91: 1.7 | I91: 1.7 | J91: 1.5 | K91: 1.5 | L91: 1.4 | M91: 1.3 | N91: 1.2 | O91: 1.1 | P91: 0 | Q91: 特惠普运|襄阳市/荆州市/宜昌市/恩施土家族苗族自治州/神农架林区/十堰市/荆门市
A92: 特惠普运 | B92: 湖南省 | C92: 株洲市/长沙市/湘潭市 | D92: 1 | E92: 10 | F92: 50 | G92: 91 | H92: 1.65 | I92: 1.65 | J92: 1.45 | K92: 1.45 | L92: 1.35 | M92: 1.3 | N92: 1.2 | O92: 1.1 | P92: 0 | Q92: 特惠普运|株洲市/长沙市/湘潭市
A93: 特惠普运 | B93: 河南省/湖北省 | C93: 信阳市/鄂州市/孝感市/黄冈市/黄石市/咸宁市/随州市/潜江市/仙桃市/天门市 | D93: 1 | E93: 10 | F93: 50 | G93: 88 | H93: 1.6 | I93: 1.6 | J93: 1.45 | K93: 1.45 | L93: 1.35 | M93: 1.25 | N93: 1.15 | O93: 1.05 | P93: 0 | Q93: 特惠普运|信阳市/鄂州市/孝感市/黄冈市/黄石市/咸宁市/随州市/潜江市/仙桃市/天门市
A94: 特惠普运 | B94: 重庆 | C94: 重庆市 | D94: 1 | E94: 10 | F94: 50 | G94: 96 | H94: 1.75 | I94: 1.75 | J94: 1.65 | K94: 1.6 | L94: 1.5 | M94: 1.4 | N94: 1.35 | O94: 1.25 | P94: 0 | Q94: 特惠普运|重庆市
A95: 特惠普运 | B95: 安徽省 | C95: 滁州市 | D95: 1 | E95: 10 | F95: 50 | G95: 84 | H95: 1.5 | I95: 1.5 | J95: 1.35 | K95: 1.35 | L95: 1.25 | M95: 1.15 | N95: 1.05 | O95: 0.95 | P95: 0 | Q95: 特惠普运|滁州市
A96: 特惠普运 | B96: 四川省 | C96: 绵阳市/乐山市/雅安市/德阳市/广元市 | D96: 1 | E96: 10 | F96: 50 | G96: 101 | H96: 1.85 | I96: 1.85 | J96: 1.75 | K96: 1.7 | L96: 1.65 | M96: 1.55 | N96: 1.45 | O96: 1.35 | P96: 0 | Q96: 特惠普运|绵阳市/乐山市/雅安市/德阳市/广元市
A97: 特惠普运 | C97: 自贡市/南充市/达州市/遂宁市/广安市/巴中市/泸州市/宜宾市/内江市 | D97: 1 | E97: 10 | F97: 50 | G97: 101 | H97: 1.85 | I97: 1.85 | J97: 1.75 | K97: 1.7 | L97: 1.6 | M97: 1.5 | N97: 1.45 | O97: 1.35 | P97: 0 | Q97: 特惠普运|自贡市/南充市/达州市/遂宁市/广安市/巴中市/泸州市/宜宾市/内江市
A98: 特惠普运 | C98: 成都市/资阳市/眉山市 | D98: 1 | E98: 10 | F98: 50 | G98: 96 | H98: 1.75 | I98: 1.75 | J98: 1.65 | K98: 1.6 | L98: 1.55 | M98: 1.45 | N98: 1.4 | O98: 1.3 | P98: 0 | Q98: 特惠普运|成都市/资阳市/眉山市
A99: 特惠普运 | B99: 陕西省 | C99: 西安市/咸阳市 | D99: 1 | E99: 10 | F99: 50 | G99: 86 | H99: 1.55 | I99: 1.55 | J99: 1.45 | K99: 1.45 | L99: 1.35 | M99: 1.3 | N99: 1.2 | O99: 1.1 | P99: 0 | Q99: 特惠普运|西安市/咸阳市
A100: 特惠普运 | B100: 江苏省 | C100: 盐城市 | D100: 1 | E100: 10 | F100: 50 | G100: 79 | H100: 1.4 | I100: 1.4 | J100: 1.3 | K100: 1.3 | L100: 1.2 | M100: 1.1 | N100: 1 | O100: 0.9 | P100: 0 | Q100: 特惠普运|盐城市
A101: 特惠普运 | C101: 无锡市 | D101: 1 | E101: 10 | F101: 50 | G101: 86 | H101: 1.55 | I101: 1.55 | J101: 1.35 | K101: 1.35 | L101: 1.25 | M101: 1.15 | N101: 1.05 | O101: 0.95 | P101: 0 | Q101: 特惠普运|无锡市
...

Sheet 运费计算
A1: 运费计算（跨越费率，实重/体积重取大）
A3: 一、输入与费率定位（自动）
A4: 物流产品 | B4: =报价汇总!B22
A5: 目的地 | B5: =报价汇总!B23
A6: 每票件数M | B6: =报价汇总!B24
A7: 单台毛重(kg) | B7: =IF(报价汇总!B16="","",报价汇总!B16+包装计算!$B$41)
A8: 单箱体积(㎝³) | B8: =包装计算!$B$17
A9: 每箱件数N | B9: =报价汇总!B17
A10: 箱数(票内) | B10: =IF(OR(B6="",B9="",B9=0),"",B6/B9)
A11: 匹配键 | B11: =IF($B$12="","",INDEX(跨越费率!$Q$4:$Q$300,$B$12))
A12: 费率行号 | B12: =IF(OR($B$4="",$B$5=""),"",IFERROR(MATCH(1,INDEX((跨越费率!$A$4:$A$300=$B$4)*(ISNUMBER(SEARCH($B$5,跨越费率!$Q$4:$Q$300))),0),0),""))
A14: 二、计费重量（自动）
A15: 单票实重(kg) | B15: =IF(OR(B7="",B6=""),"",B7*B6)
A16: 单票体积重(kg) | B16: =IF(OR(B8="",B10=""),"",B8*B10/参数!$B$36)
A17: 计费重量(kg) | B17: =IF(AND(ISNUMBER(B15),ISNUMBER(B16)),MAX(B15,B16),"")
A18: 起重(kg) | B18: =IF(B12="","",INDEX(跨越费率!$F$4:$F$300,B12))
A19: 计费重量起重后 | B19: =IF(OR(B17="",B18=""),"",MAX(B17,B18))
A21: 三、运费（自动）
A22: 首重重量 | B22: =IF(B12="","",INDEX(跨越费率!$D$4:$D$300,B12))
A23: 首重价格 | B23: =IF(B12="","",INDEX(跨越费率!$E$4:$E$300,B12))
A24: 段位置idx | B24: =IF(OR(B19="",B4=""),"",IF(B4="次日达",MATCH(B19,$B$26:$J$26,1),MATCH(B19,$B$27:$J$27,1)))
A25: 段单价 | B25: =IF(OR(B12="",B24=""),"",INDEX(跨越费率!$H$4:$P$300,B12,B24))
A26: 次日达段下限 | B26: 1 | C26: 10 | D26: 30 | E26: 50 | F26: 100 | G26: 300 | H26: 500 | I26: 1000 | J26: 2000
A27: 特惠段下限 | B27: 1 | C27: 50 | D27: 100 | E27: 200 | F27: 300 | G27: 500 | H27: 1000 | I27: 2000 | J27: 0
A28: 最低收费 | B28: =IF(B12="","",INDEX(跨越费率!$G$4:$G$300,B12))
A29: 单票运费 | B29: =IF(OR(B23="",B19="",B25="",B28=""),"",MAX(B23+(B19-B22)*B25,B28))
A30: 声明价值(元/票) | B30: =报价汇总!B25
A31: 保费(可选) | B31: =IF(参数!$B$39="是",IF(NOT(ISNUMBER(B30)),"",MAX(参数!$B$37*B30,参数!$B$38)),0)
A32: 单票运费合计 | B32: =IF(OR(B29="",B31=""),"",B29+B31)
A33: 单台运费(元/件) | B33: =IF(OR(B32="",B6="",B6=0),"",B32/B6)
A35: 运费口径：计费重量=MAX(实重,体积重)；体积重=箱体积(㎝³)/体积系数；运费=首重价格+(计费重量-首重重量)×段单价，最低不低于最低收费。
A36: 目的地需与所选物流产品匹配：次日达与特惠普运的目的地划分不同，选错时本表运费显示空白。
