Workbook

Sheet Sheet1
A1: 厦门华联电子股份有限公司智能控制器/汽车与工控 产品报价单
A2: 产品报价申请单流程编号 | B2: 销售公司/国内销售部/汽控国内部-产品报价成本核算申请单-2025-10-0713
A3: 产品信息 | B3: 1 | C3: 产品代码 | D3: N10305002124 | E3: N10305002124
B4: 2 | C4: 产品名称 | D4: DRV-26P-NJTJ(RoHS)中央式空调控制器驱动板组件(D5A13H000000) | E4: DRV-26P-NJTJ(RoHS)中央式空调控制器驱动板组件(D5A13H000000)
B5: 3 | C5: 客户名称 | D5: 青岛国创智能家电研究院有限公司 | E5: 青岛国创智能家电研究院有限公司
B6: 4 | C6: 报价日期 | D6: 45943.74 | E6: 2026/1/8更新包装，制造降本
B7: 5 | C7: 年需求量 | D7: 5000 | E7: 5000
B8: 6 | C8: MOQ | D8: 50 | E8: 50
B9: 7 | C9: MPQ
B10: 8 | C10: 备注 | D10: 工装、模具费直接向客户收取； 已扣除8颗客供料核算成本 | E10: 工装、模具费直接向客户收取；(N10305002124与N10305002125共用) 已扣除8颗客供料核算成本
A11: 成本及费用组成 | D11: 金额 | E11: 金额
A12: 材料成本 | B12: 1 | C12: 硬件 | D12: =[1]N10305002124原材料报价单!O288 -> 358.46316 | E12: =[1]N10305002124原材料报价单!O288 -> 358.46316
B13: 2 | C13: 结构件 | D13: =[1]N10305002124原材料报价单!O321 -> 416.4798 | E13: =[1]N10305002124原材料报价单!O321 -> 416.4798
B14: 3 | C14: 包装材料 | D14: =[1]N10305002124原材料报价单!O15 -> 96.6702 | E14: =[1]N10305002124原材料报价单!O355 -> 63.7765
B15: 4 | C15: 辅助材料 | D15: =[1]N10305002124原材料报价单!M342 -> 37.854901 | E15: =[1]N10305002124原材料报价单!M375 -> 37.943115
B16: 小计 | D16: =SUM(D12:D15) -> 909.46806 | E16: =SUM(E12:E15) -> 876.66258
A17: 加工成本 | B17: 5 | C17: 贴片加工成本 | D17: 6.1656 | E17: 6.1656
B18: 6 | C18: 机插加工成本 | D18: 0.2394 | E18: 0.2394
B19: 7 | C19: 预烧写加工成本 | D19: 0 | E19: 0
B20: 8 | C20: 人工成本 | D20: 111.0501 | E20: 82.0882
B21: 9 | C21: 折旧（专用） | D21: 0.8424 | E21: 0.8424
B22: 10 | C22: 折旧（公共） | D22: 2.9761 | E22: 2.2
B23: 11 | C23: 水电（专用） | D23: 1.4745 | E23: 1.4745
B24: 12 | C24: 水电（公共） | D24: 1.9989 | E24: 1.4776
B25: 13 | C25: 工装 | D25: 0 | E25: 0
B26: 14 | C26: 低耗 | D26: 6.1522 | E26: 4.5477
B27: 15 | C27: 管理人员工资 | D27: 31.9713 | E27: 21.3676
B28: 16 | C28: 其他 | D28: 8.1511 | E28: 6.0253
B29: 17 | C29: 检验成本 | D29: 0 | E29: 0
B30: 小计 | D30: =SUM(D17:D29) -> 171.0216 | E30: =SUM(E17:E29) -> 126.4283
A31: 其他费用 | B31: 18 | C31: 工装费 | D31: =[1]N10305002124制造成本!G86 -> 48700 | E31: =[1]N10305002124制造成本!P86 -> 48700
B32: 19 | C32: 模具费 | E32: =[1]N10305002124制造成本!N111 -> 29499.115
B33: 20 | C33: 认证费/实验费
B34: 21 | C34: 硬件开发费
B35: 22 | C35: 软件开发费
B36: 23 | C36: 认证费/实验费
B37: 直接向客户收费小计 | D37: =SUM(D31:D36) -> 48700 | E37: =SUM(E31:E36) -> 78199.115
B38: 24 | C38: 分摊在产品成本中
A39: 料工费成本（合计） | D39: =SUM(D16,D30,D38) -> 1080.4897 | E39: =SUM(E16,E30,E38) -> 1003.0909
B40: 成本差异 | D40: =D39*1.35% -> 14.58661 | E40: =E39*1.35% -> 13.541727
B41: 运费 | D41: =D39*1.1587794709673% -> 12.520492 | E41: =E39*1.1587794709673% -> 11.623611 | G41: 成本 | H41: 报价 | I41: 利润 | J41: 毛利
A42: 主营业务成本 | D42: =SUM(D39:D41) -> 1107.5968 | E42: =SUM(E39:E41) -> 1028.2562 | F42: 散热器+底托+螺丝105 | G42: =E42+103 -> 1131.2562 | H42: 1180 | I42: =H42-G42 -> 48.743786 | J42: =I42/H42 -> 0.041308293 | K42: 45931
A43: 建议毛利率 | D43: 0.3 | E43: 0.3 | F43: 原材料涨幅 66.09 | G43: =G42+66.09 -> 1197.3462 | H43: 1180 | I43: =H43-G43 -> -17.346214 | J43: =I43/H43 -> -0.014700181 | K43: 46174
A44: 建议售价 | D44: =D42/(1-D43) -> 1582.2811 | E44: =E42/(1-E43) -> 1468.9374 | H44: 1285 | I44: =H44-G43 -> 87.653786 | J44: =I44/H44 -> 0.068213063 | K44: 46204
A45: 备注
A46: ＜注意事项＞
A47: 1. 以上报价均为不含税价；
A48: 2. 软/硬件开发费用不包含设计源文件；
A49: 3. 因客户变更、原材料涨价、汇率变化等导致成本上涨，需重新报价；
A50: 4. 建议毛利率：以《年度事业部毛利率管控线》为准。
E53: 国创毛利 | F53: 当前成本 | G53: 华联 | H53: 客供 | I53: 合计 | J53: 成本（含税） | K53: 售价（含税）
F54: 26P总成本 | G54: 1180 | H54: 414.1146 | I54: =G54+H54 -> 1594.1146 | J54: =I54*1.13 -> 1801.3495 | K54: 2351.25 | L54: =1-J54/K54 -> 0.23387581
F55: 20P总成本 | G55: 1180 | H55: 385.796 | I55: =G55+H55 -> 1565.796 | J55: =I55*1.13 -> 1769.3495 | K55: 2313.25 | L55: =1-J55/K55 -> 0.23512397
E57: 国创毛利 | F57: 涨价后成本 | G57: 华联 | H57: 客供 | I57: 合计
F58: 26P总成本 | G58: =1180+95 -> 1275 | H58: 414.1146 | I58: =G58+H58 -> 1689.1146 | J58: =I58*1.13 -> 1908.6995 | K58: 2351.25 | L58: =1-J58/K58 -> 0.18821925
F59: 20P总成本 | G59: =1180+95 -> 1275 | H59: 385.796 | I59: =G59+H59 -> 1660.796 | J59: =I59*1.13 -> 1876.6995 | K59: 2313.25 | L59: =1-J59/K59 -> 0.1887174

Sheet 汇总情况
A1: 厦门华联电子股份有限公司智能控制器/汽车与工控 产品报价单
A2: 产品报价申请单流程编号 | B2: 销售公司/国内销售部/汽控国内部-产品报价成本核算申请单-2025-10-0713
A3: 产品信息 | B3: 1 | C3: 产品代码 | D3: N10305002124 | E3: N10305002124
B4: 2 | C4: 产品名称 | D4: DRV-26P-NJTJ(RoHS)中央式空调控制器驱动板组件(D5A13H000000) | E4: DRV-26P-NJTJ(RoHS)中央式空调控制器驱动板组件(D5A13H000000)
B5: 3 | C5: 客户名称 | D5: 青岛国创智能家电研究院有限公司 | E5: 青岛国创智能家电研究院有限公司
B6: 4 | C6: 报价日期 | D6: 45943.74 | E6: 2026/1/8更新包装，制造降本
B7: 5 | C7: 年需求量 | D7: 5000 | E7: 5000
B8: 6 | C8: MOQ | D8: 50 | E8: 50
B9: 7 | C9: MPQ
B10: 8 | C10: 备注 | D10: 工装、模具费直接向客户收取； 已扣除8颗客供料核算成本 | E10: 工装、模具费直接向客户收取；(N10305002124与N10305002125共用) 已扣除8颗客供料核算成本
A11: 成本及费用组成 | D11: 金额 | E11: 金额
A12: 材料成本 | B12: 1 | C12: 硬件 | D12: =[1]N10305002124原材料报价单!O288 -> 358.46316 | E12: =[1]N10305002124原材料报价单!O288 -> 358.46316
B13: 2 | C13: 结构件 | D13: =[1]N10305002124原材料报价单!O321 -> 416.4798 | E13: =[1]N10305002124原材料报价单!O321 -> 416.4798
B14: 3 | C14: 包装材料 | D14: =[1]N10305002124原材料报价单!O15 -> 96.6702 | E14: =[1]N10305002124原材料报价单!O355 -> 63.7765
B15: 4 | C15: 辅助材料 | D15: =[1]N10305002124原材料报价单!M342 -> 37.854901 | E15: =[1]N10305002124原材料报价单!M375 -> 37.943115
B16: 小计 | D16: =SUM(D12:D15) -> 909.46806 | E16: =SUM(E12:E15) -> 876.66258
A17: 加工成本 | B17: 5 | C17: 贴片加工成本 | D17: 6.1656 | E17: 6.1656
B18: 6 | C18: 机插加工成本 | D18: 0.2394 | E18: 0.2394
B19: 7 | C19: 预烧写加工成本 | D19: 0 | E19: 0
B20: 8 | C20: 人工成本 | D20: 111.0501 | E20: 82.0882
B21: 9 | C21: 折旧（专用） | D21: 0.8424 | E21: 0.8424
B22: 10 | C22: 折旧（公共） | D22: 2.9761 | E22: 2.2
B23: 11 | C23: 水电（专用） | D23: 1.4745 | E23: 1.4745
B24: 12 | C24: 水电（公共） | D24: 1.9989 | E24: 1.4776
B25: 13 | C25: 工装 | D25: 0 | E25: 0
B26: 14 | C26: 低耗 | D26: 6.1522 | E26: 4.5477
B27: 15 | C27: 管理人员工资 | D27: 31.9713 | E27: 21.3676
B28: 16 | C28: 其他 | D28: 8.1511 | E28: 6.0253
B29: 17 | C29: 检验成本 | D29: 0 | E29: 0
B30: 小计 | D30: =SUM(D17:D29) -> 171.0216 | E30: =SUM(E17:E29) -> 126.4283
A31: 其他费用 | B31: 18 | C31: 工装费 | D31: =[1]N10305002124制造成本!G86 -> 48700 | E31: =[1]N10305002124制造成本!P86 -> 48700
B32: 19 | C32: 模具费 | E32: =[1]N10305002124制造成本!N111 -> 29499.115
B33: 20 | C33: 认证费/实验费
B34: 21 | C34: 硬件开发费
B35: 22 | C35: 软件开发费
B36: 23 | C36: 认证费/实验费
B37: 直接向客户收费小计 | D37: =SUM(D31:D36) -> 48700 | E37: =SUM(E31:E36) -> 78199.115
B38: 24 | C38: 分摊在产品成本中
A39: 料工费成本（合计） | D39: =SUM(D16,D30,D38) -> 1080.4897 | E39: =SUM(E16,E30,E38) -> 1003.0909
B40: 成本差异 | D40: =D39*1.35% -> 14.58661 | E40: =E39*1.35% -> 13.541727
B41: 运费 | D41: =D39*1.1587794709673% -> 12.520492 | E41: =E39*1.1587794709673% -> 11.623611
A42: 主营业务成本 | D42: =SUM(D39:D41) -> 1107.5968 | E42: =SUM(E39:E41) -> 1028.2562
A43: 建议毛利率 | D43: 0.3 | E43: 0.3
A44: 建议售价 | D44: =D42/(1-D43) -> 1582.2811 | E44: =E42/(1-E43) -> 1468.9374
A47: 华联毛利 | B47: 成本 | C47: 报价 | D47: 利润 | E47: 毛利
A48: 散热器+底托+螺丝105 | B48: =E42+103 -> 1131.2562 | C48: 1180 | D48: 48.743786 | E48: 0.041308293 | F48: 45931
A49: 原材料涨幅 66.09 | B49: 1197.3462 | C49: 1180 | D49: -17.346214 | E49: -0.014700181 | F49: 46174
A50: 涨价105 | C50: 1285 | D50: 87.653786 | E50: 0.068213063 | F50: 46204
A52: 国创毛利
A53: 当前成本 | B53: 华联 | C53: 客供 | D53: 合计 | E53: 成本 （含税） | F53: 售价 （含税） | G53: 毛利率
A54: 26P总成本 | B54: 1180 | C54: 414.1146 | D54: =B54+C54 -> 1594.1146 | E54: =D54*1.13 -> 1801.3495 | F54: 2351.25 | G54: =1-E54/F54 -> 0.23387581
A55: 20P总成本 | B55: 1180 | C55: 385.796 | D55: =B55+C55 -> 1565.796 | E55: =D55*1.13 -> 1769.3495 | F55: 2313.25 | G55: =1-E55/F55 -> 0.23512397
A56: 国创毛利
A57: 涨价95 | B57: 华联 | C57: 客供 | D57: 合计 | E57: 成本 （含税） | F57: 售价 （含税） | G57: 毛利率
A58: 26P总成本 | B58: =1180+95 -> 1275 | C58: 414.1146 | D58: =B58+C58 -> 1689.1146 | E58: =D58*1.13 -> 1908.6995 | F58: 2351.25 | G58: =1-E58/F58 -> 0.18821925
A59: 20P总成本 | B59: =1180+95 -> 1275 | C59: 385.796 | D59: =B59+C59 -> 1660.796 | E59: =D59*1.13 -> 1876.6995 | F59: 2313.25 | G59: =1-E59/F59 -> 0.1887174
A60: 国创毛利
A61: 涨价80 | B61: 华联 | C61: 客供 | D61: 合计 | E61: 成本 （含税） | F61: 售价 （含税） | G61: 毛利率
A62: 26P总成本 | B62: =1180+80 -> 1260 | C62: 414.1146 | D62: =B62+C62 -> 1674.1146 | E62: =D62*1.13 -> 1891.7495 | F62: 2351.25 | G62: =1-E62/F62 -> 0.19542818
A63: 20P总成本 | B63: =1180+80 -> 1260 | C63: 385.796 | D63: =B63+C63 -> 1645.796 | E63: =D63*1.13 -> 1859.7495 | F63: 2313.25 | G63: =1-E63/F63 -> 0.19604475
A64: 国创毛利
A65: 涨价70 | B65: 华联 | C65: 客供 | D65: 合计 | E65: 成本 （含税） | F65: 售价 （含税） | G65: 毛利率
A66: 26P总成本 | B66: =1180+70 -> 1250 | C66: 414.1146 | D66: =B66+C66 -> 1664.1146 | E66: =D66*1.13 -> 1880.4495 | F66: 2351.25 | G66: =1-E66/F66 -> 0.20023413
A67: 20P总成本 | B67: =1180+70 -> 1250 | C67: 385.796 | D67: =B67+C67 -> 1635.796 | E67: =D67*1.13 -> 1848.4495 | F67: 2313.25 | G67: =1-E67/F67 -> 0.20092965

Sheet Sheet2
A1: 项目名称 | C1: 汽车与工控控制器-DRV-20P-NJTJ(RoHS)中央式空调控制器驱动板组件(D5A13G000000)--二次重新报价！！ | E1: 客户名称 | F1: 青岛国创智能家电研究院有限公司 | K1: 报价项目类型 | L1: 已立项产品报价 | O1: 王前良 | W1: 销售公司/国内销售部/汽控国内部
A2: 产品编码 | C2: N10305002124 | E2: 产品名称 | F2: DRV-26P-NJTJ(RoHS)中央式空调控制器驱动板组件(D5A13H000000) | K2: 硬件设计师 | L2: 李沁峰 | O2: 陈可璜 | W2: 45950
A3: 硬件 | E3: 结构件 | K3: 包装材料 | T3: 0 | X3: 0
A4: 序号 | B4: 物料类型 | C4: 物料编码 | D4: 物料名称 | E4: 物料级别 | F4: 装配形式 | G4: 单机用量 | H4: 最低价物料编码 | I4: 最低价物料名称 | J4: 采购员 | K4: 供应商代码 | L4: 供应商名称 | M4: 未税单价 | N4: 损耗率 | O4: 金额 | T4: 提前期 | U4: 最小订货量 | V4: 最小包装量 | W4: 模具费（含税13%） | X4: 价格说明 | Y4: 备注 | Z4: 位号 | AA4: 替代料编码1 | AB4: 替代料名称1 | AC4: 未税单价1 | AD4: 替代料编码2 | AE4: 替代料名称2 | AF4: 未税单价2 | AG4: 替代料编码3 | AH4: 替代料名称3 | AI4: 未税单价3
A5: 6 | B5: 包装组件 | C5: 4013430R | D5: 塑胶线夹 3.6X300 (尼龙扣)(正顺达)(RoHS) | E5: AB级替换 | F5: N/A | G5: 3 | H5: 4013430R | I5: 塑胶线夹 3.6X300 (尼龙扣)(RoHS) | J5: 沈艺聪 | K5: XMZSD | L5: 厦门正顺达电子有限公司 | M5: 0.099 | N5: 0 | O5: =G5*M5 -> 0.297 | T5: 21 | U5: 10000 | Y5: 2025-10-13包装方案
A6: 7 | B6: 包装组件 | C6: N40501000374 | D6: 纸箱 670X387X406 (RoHS) | E6: AB级替换 | F6: PKG | G6: 1 | H6: N40501000374 | I6: 纸箱 670X387X406 (RoHS) | J6: 512 | K6: 11363 | L6: 厦门比瑞特包装科技有限公司 | M6: 7.1593 | N6: 0 | O6: =G6*M6 -> 7.1593 | T6: 14 | U6: 1 | V6: 1
A7: 8 | B7: 包装组件 | C7: N40505000136 | D7: 塑料袋 355X245 (凹凸)(RoHS) | E7: AB级替换 | F7: PKG | G7: 1 | H7: N40505000136 | I7: 塑料袋 355X245 (凹凸)(RoHS) | J7: 512 | K7: 11363 | L7: 厦门比瑞特包装科技有限公司 | M7: 0.25 | N7: 0 | O7: =G7*M7 -> 0.25 | T7: 14 | U7: 1000 | V7: 1000
A8: 9 | B8: 包装组件 | C8: N40512000278 | D8: 泡沫棉 660X377X374 (泡沫盒底座)(防静电)(RoHS) | E8: AB级替换 | F8: PKG | G8: 1 | H8: N40512000278 | I8: 泡沫棉 660X377X374 (泡沫盒底座)(防静电)(RoHS) | J8: 512 | K8: 10379 | L8: 厦门市达唯工贸有限公司 | M8: 69.5575 | N8: 0 | O8: =G8*M8 -> 69.5575 | T8: 14 | U8: 1 | V8: 1
A9: 10 | B9: 包装组件 | C9: N40512000279 | D9: 泡沫棉 660X377X110 (泡沫盒上盖)(防静电)(RoHS) | E9: AB级替换 | F9: PKG | G9: 1 | H9: N40512000279 | I9: 泡沫棉 660X377X110 (泡沫盒上盖)(防静电)(RoHS) | J9: 512 | K9: 10379 | L9: 厦门市达唯工贸有限公司 | M9: 8.6726 | N9: 0 | O9: =G9*M9 -> 8.6726 | T9: 14 | U9: 1 | V9: 1
A10: 11 | B10: 包装组件 | C10: N40512000280 | D10: 泡沫棉 50X45X200 (左侧EVA棉块)(高密度)(防静电)(RoHS) | E10: AB级替换 | F10: PKG | G10: 1 | H10: N40512000280 | I10: 泡沫棉 50X45X200 (左侧EVA棉块)(高密度)(防静电)(RoHS) | J10: 512 | K10: 10379 | L10: 厦门市达唯工贸有限公司 | M10: 2.2655 | N10: 0 | O10: =G10*M10 -> 2.2655 | T10: 14 | U10: 1 | V10: 1
A11: 12 | B11: 包装组件 | C11: N40512000281 | D11: 泡沫棉 50X45X200 (右侧EVA棉块1)(高密度)(防静电)(RoHS) | E11: AB级替换 | F11: PKG | G11: 1 | H11: N40512000281 | I11: 泡沫棉 50X45X200 (右侧EVA棉块1)(高密度)(防静电)(RoHS) | J11: 512 | K11: 10379 | L11: 厦门市达唯工贸有限公司 | M11: 2.2655 | N11: 0 | O11: =G11*M11 -> 2.2655 | T11: 14 | U11: 1 | V11: 1
A12: 13 | B12: 包装组件 | C12: N40512000282 | D12: 泡沫棉 40X20X199 (右侧EVA棉块2)(高密度)(防静电)(RoHS) | E12: AB级替换 | F12: PKG | G12: 3 | H12: N40512000282 | I12: 泡沫棉 40X20X199 (右侧EVA棉块2)(高密度)(防静电)(RoHS) | J12: 512 | K12: 10379 | L12: 厦门市达唯工贸有限公司 | M12: 1.0619 | N12: 0 | O12: =G12*M12 -> 3.1857 | T12: 14 | U12: 1 | V12: 1
A13: 14 | B13: 包装组件 | C13: N40517000012 | D13: 纸护角 50X50X403 (RoHS) | E13: AB级替换 | F13: PKG | G13: 4 | H13: N40517000012 | I13: 纸护角 50X50X403 (RoHS) | J13: 512 | K13: 11363 | L13: 厦门比瑞特包装科技有限公司 | M13: 0.7456 | N13: 0 | O13: =G13*M13 -> 2.9824 | T13: 14 | U13: 1 | V13: 1
A14: 15 | B14: 包装组件 | C14: N60703001395 | D14: 标签 BQ12080W001-HL (格式标签)(1寸卷芯,外径83mm)(RoHS) | E14: AB级替换 | F14: 贴装 | G14: 1 | H14: N60703001395 | I14: 标签 BQ12080W001-HL (格式标签)(1寸卷芯,外径83mm)(宏鹭华)(RoHS) | J14: 吴桃春 | K14: DWQK2 | L14: 东莞市全科电子材料有限公司 | M14: 0.0347 | N14: 0 | O14: =G14*M14 -> 0.0347 | T14: 14 | U14: 3000
I15: 包装成本 | O15: =SUM(O5:O14) -> 96.6702
A16: 16 | B16: 硬件 | C16: 301H030491 | D16: 片式电阻 RC0805FR-07300KL/0805W8F3003T5E 1/8W,300KΩ,1%,0805(国巨/厚声)(编带)(RoHS) | E16: AB级替换 | F16: SMT | G16: 18 | H16: N30101005840 | I16: 片式电阻 RC0805FR-07300KL 1/8W,300KΩ,1%,0805(国巨)(编带)(RoHS) | J16: 196386 | K16: 10266 | L16: 深圳市超利维实业有限公司 | M16: 0.0045 | N16: 0 | O16: =G16*M16 -> 0.081 | T16: 56 | U16: 5000 | V16: 5000 | Z16: R163-168,178,179,182-191 | AA16: N30101007034 | AB16: 片式电阻 0805W8F3003T5E 1/8W,300KΩ,1%,0805(厚声)(编带)(RoHS) | AC16: 0.0049 | AD16: 301H030491 | AE16: 片式电阻 RC0805FR-07300KL/0805W8F3003T5E 1/8W,300KΩ,1%,0805(国巨/厚声)(编带)(RoHS) | AF16: 报价中
A17: 17 | B17: 硬件 | C17: 306110396 | D17: 高压陶瓷电容 HGK3AF103ZG3AW 10nF,1KV,P=7.5(万明)(编带)(RoHS) | E17: AB级替换 | F17: 插焊 | G17: 1 | H17: 306110396 | I17: 高压陶瓷电容 HGK3AF103ZG3AW 10nF,1KV,P=7.5(万明)(编带)(RoHS) | J17: 196386 | K17: 10423 | L17: 厦门万明电子有限公司 | M17: 0.1331 | N17: 0 | O17: =G17*M17 -> 0.1331 | T17: 50 | U17: 20000 | V17: 2000 | Y17: 生产后按万明回复交期出货，不接受按贵司需求数量出货 | Z17: C50A
A18: 18 | B18: 硬件 | C18: 3155US1M | D18: 超快恢复二极管 US1M 1A,1KV,SMA(强茂)(编带)(RoHS) | E18: AB级替换 | F18: SMT | G18: 1 | H18: N31511000061 | I18: 超快恢复二极管 US1M 1A,1KV,SMA(晶导微)(编带)(RoHS) | J18: 514 | K18: 10382 | L18: 厦门镁富莱工贸有限公司 | M18: 0.0274 | N18: 0 | O18: =G18*M18 -> 0.0274 | T18: 35 | U18: 1 | V18: 1 | Z18: V16 | AA18: 3155US1M | AB18: 超快恢复二极管 US1M 1A,1KV,SMA(强茂)(编带)(RoHS) | AC18: 0.084
A19: 19 | B19: 硬件 | C19: 604B03VHZ51R | D19: 端子 B3P-VH (JST)(RoHS) | E19: AB级替换 | F19: 插焊 | G19: 1 | H19: 604B03VHZ51R | I19: 端子 B3P-VH (JST)(RoHS) | J19: 王临泽 | K19: HYDZ2 | L19: 深圳市恒有电子有限公司 | M19: 0.222 | N19: 0 | O19: =G19*M19 -> 0.222 | T19: 150 | U19: 1000 | Z19: X5
A20: 20 | B20: 硬件 | C20: 604B05VHZ51R | D20: 端子 B5P-VH (JST)(RoHS) | E20: AB级替换 | F20: 插焊 | G20: 2 | H20: 604B05VHZ51R | I20: 端子 B5P-VH (JST)(RoHS) | J20: 王临泽 | K20: HYDZ2 | L20: 深圳市恒有电子有限公司 | M20: 0.322 | N20: 0 | O20: =G20*M20 -> 0.644 | T20: 112 | U20: 1000 | Z20: X12,16
A21: 21 | B21: 硬件 | C21: N30101000615 | D21: 片式电阻 RC1206JR-0775RL/1206W4J0750T5E 1/4W,75Ω,5%,1206(国巨/厚声)(编带)(RoHS) | E21: AB级替换 | F21: SMT | G21: 1 | H21: N30101006583 | I21: 片式电阻 1206W4J0750T5E 1/4W,75Ω,5%,1206(厚声)(编带)(RoHS) | J21: 罗城 | K21: 10648 | L21: 厚声国际贸易（昆山）有限公司 | M21: 0.0045 | N21: 0 | O21: =G21*M21 -> 0.0045 | T21: 56 | U21: 0 | V21: 5000 | Z21: R118 | AA21: N30101005467 | AB21: 片式电阻 RC1206JR-0775RL 1/4W,75Ω,5%,1206(国巨)(编带)(RoHS) | AC21: 0.0077 | AD21: N30101000615 | AE21: 片式电阻 RC1206JR-0775RL/1206W4J0750T5E 1/4W,75Ω,5%,1206(国巨/厚声)(编带)(RoHS) | AF21: 报价中
A22: 22 | B22: 硬件 | C22: N30101000894 | D22: 片式电阻 RC1206FR-0722RL/1206W4F220JT5E 1/4W,22Ω,1%,1206(国巨/厚声)(编带)(RoHS) | E22: AB级替换 | F22: SMT | G22: 2 | H22: N30101006783 | I22: 片式电阻 1206W4F220JT5E 1/4W,22Ω,1%,1206(厚声)(编带)(RoHS) | J22: 罗城 | K22: 10648 | L22: 厚声国际贸易（昆山）有限公司 | M22: 0.0058 | N22: 0 | O22: =G22*M22 -> 0.0116 | T22: 56 | U22: 0 | V22: 5000 | Z22: R10,30 | AA22: N30101005525 | AB22: 片式电阻 RC1206FR-0722RL 1/4W,22Ω,1%,1206(国巨)(编带)(RoHS) | AC22: 0.0086 | AD22: N30101000894 | AE22: 片式电阻 RC1206FR-0722RL/1206W4F220JT5E 1/4W,22Ω,1%,1206(国巨/厚声)(编带)(RoHS) | AF22: 报价中
A23: 23 | B23: 硬件 | C23: N30101001049 | D23: 片式电阻 RC1206FR-076R8L/1206W4F680KT5E 1/4W,6.8Ω,1%,1206(国巨/厚声)(编带)(RoHS) | E23: AB级替换 | F23: SMT | G23: 2 | H23: N30101006696 | I23: 片式电阻 1206W4F680KT5E 1/4W,6.8Ω,1%,1206(厚声)(编带)(RoHS) | J23: 罗城 | K23: 10648 | L23: 厚声国际贸易（昆山）有限公司 | M23: 0.0083 | N23: 0 | O23: =G23*M23 -> 0.0166 | T23: 56 | U23: 0 | V23: 5000 | Z23: R47,65 | AA23: N30101005600 | AB23: 片式电阻 RC1206FR-076R8L 1/4W,6.8Ω,1%,1206(国巨)(编带)(RoHS) | AC23: 0.0279 | AD23: N30101001049 | AE23: 片式电阻 RC1206FR-076R8L/1206W4F680KT5E 1/4W,6.8Ω,1%,1206(国巨/厚声)(编带)(RoHS) | AF23: 报价中
A24: 24 | B24: 硬件 | C24: N30101005306 | D24: 片式电阻 GMR320HJCFAR100 7W,100mΩ,1%,2817(Rohm)(编带)(RoHS) | E24: AB级替换 | F24: SMT | G24: 2 | H24: N30101005306 | I24: 片式电阻 GMR320HJCFAR100 7W,100mΩ,1%,2817(Rohm)(编带)(RoHS) | J24: 521 | K24: 10265 | L24: 北天星电子(深圳)有限公司 | M24: 2.38 | N24: 0 | O24: =G24*M24 -> 4.76 | T24: 120 | U24: 1 | V24: 1 | Z24: R92,241
A25: 25 | B25: 硬件 | C25: N30101005309 | D25: 片式电阻 1210W2F3003T5E 1/2W,300KΩ,1%,1210(厚声)(编带)(RoHS) | E25: AB级替换 | F25: SMT | G25: 8 | H25: N30101005309 | I25: 片式电阻 1210W2F3003T5E 1/2W,300KΩ,1%,1210(厚声)(编带)(RoHS) | J25: 罗城 | K25: 10648 | L25: 厚声国际贸易（昆山）有限公司 | M25: 0.023 | N25: 0 | O25: =G25*M25 -> 0.184 | T25: 91 | U25: 0 | V25: 20000 | Z25: R192-199
A26: 26 | B26: 硬件 | C26: N30103000520 | D26: 金属膜电阻 MF02SJJ0364A10 2WS,360KΩ,5%(厚声)(HF;RoHS) | E26: AB级替换 | F26: 插焊 | G26: 3 | H26: N30103000520 | I26: 金属膜电阻 MF02SJJ0364A10 2WS,360KΩ,5%(厚声)(HF;RoHS) | J26: 罗城 | K26: 10648 | L26: 厚声国际贸易（昆山）有限公司 | M26: 0.065 | N26: 0 | O26: =G26*M26 -> 0.195 | T26: 91 | U26: 0 | V26: 20000 | Z26: R295,296,365
A27: 27 | B27: 硬件 | C27: N30103000526 | D27: 金属膜电阻 MF01WFF3003A10 1W,300KΩ,1%(厚声)(编带)(HF;RoHS) | E27: AB级替换 | F27: 插焊 | G27: 1 | H27: N30103000526 | I27: 金属膜电阻 MF01WFF3003A10 1W,300KΩ,1%(厚声)(编带)(RoHS) | J27: 陈虹 | K27: HSMY2 | L27: 厚声国际贸易（昆山）有限公司 | M27: 0.0828 | N27: 0 | O27: =G27*M27 -> 0.0828 | T27: 42 | U27: 1000 | V27: 1000 | Z27: R11
A28: 28 | B28: 硬件 | C28: N30103000527 | D28: 金属膜电阻 MF02WJJ0753A10 2W,75KΩ,5%(厚声)(编带)(HF;RoHS) | E28: AB级替换 | F28: 插焊 | G28: 1 | H28: N30103000527 | I28: 金属膜电阻 MF02WJJ0753A10 2W,75KΩ,5%(厚声)(编带)(HF;RoHS) | J28: 罗城 | K28: 10648 | L28: 厚声国际贸易（昆山）有限公司 | M28: 0.092 | N28: 0 | O28: =G28*M28 -> 0.092 | T28: 91 | U28: 0 | V28: 20000 | Z28: R34
A29: 29 | B29: 硬件 | C29: N30111000138 | D29: 合金电阻 DSLR-K-7-3F 7W,3mΩ,1%,5930(业展)(编带)(REACH;RoHS) | E29: AB级替换 | F29: SMT | G29: 3 | H29: N30111000138 | I29: 合金电阻 DSLR-K-7-3F 7W,3mΩ,1%,5930(业展)(编带)(REACH;RoHS) | J29: 521 | K29: 10265 | L29: 北天星电子(深圳)有限公司 | M29: 0.9 | N29: 0 | O29: =G29*M29 -> 2.7 | T29: 120 | U29: 1 | V29: 1 | Z29: R87,89,90
A30: 30 | B30: 硬件 | C30: N30111000139 | D30: 合金电阻 LR123WF200LT4E 3W,200mΩ,1%,2512(厚声)(编带)(RoHS) | E30: AB级替换 | F30: SMT | G30: 8 | H30: N30111000139 | I30: 合金电阻 LR123WF200LT4E 3W,200mΩ,1%,2512(厚声)(编带)(RoHS) | J30: 521 | K30: 10648 | L30: 厚声国际贸易（昆山）有限公司 | M30: 0.22 | N30: 0 | O30: =G30*M30 -> 1.76 | T30: 1 | U30: 1 | V30: 4000 | Z30: R233-236,293,294,297,298
A31: 31 | B31: 硬件 | C31: N30199000015 | D31: 片式电阻 1/4W,0Ω,5%,1206(编带)(RoHS)(互换件) | E31: AB级替换 | F31: SMT | G31: 1 | H31: N30101002864 | I31: 片式电阻 RS-06000JT 1/4W,0Ω,5%,1206(风华)(编带)(RoHS) | J31: 陈虹 | K31: MHDZ2 | L31: 厦门美赫电子有限公司 | M31: 0.0042 | N31: 0 | O31: =G31*M31 -> 0.0042 | T31: 56 | U31: 5000 | Z31: R144 | AA31: N30101006682 | AB31: 片式电阻 1206W4J0000T5E 1/4W,0Ω,5%,1206(厚声)(编带)(RoHS) | AC31: 0.0042 | AD31: N30101005366 | AE31: 片式电阻 RC1206JR-070RL 1/4W,0Ω,5%,1206(国巨)(编带)(RoHS) | AF31: 0.0075 | AG31: N30101002359 | AH31: 片式电阻 CR1206J40000G 1/4W,0Ω,5%,1206(丽智)(编带)(RoHS) | AI31: 报价中
A32: 32 | B32: 硬件 | C32: N30199000022 | D32: 片式电阻 1/10W,10KΩ,1%,0603(编带)(RoHS)(互换件) | E32: AB级替换 | F32: SMT | G32: 49 | H32: N30101002483 | I32: 片式电阻 0603WAF1002T5E 1/10W,10KΩ,1%,0603(厚声)(编带)(RoHS) | J32: 陈虹 | K32: HSMY2 | L32: 厚声国际贸易（昆山）有限公司 | M32: 0.0018 | N32: 0 | O32: =G32*M32 -> 0.0882 | T32: 56 | U32: 5000 | Z32: R4,5,7,14,16,20,21,23,26,27,31,38,39,42,52,62,63,73,75,77,80,82,83,98-100,112-114,116,141-143,145,200-202,218-223,225-227,231,232,260 | AA32: N30101002583 | AB32: 片式电阻 RS-03K1002FT 1/10W,10KΩ,1%,0603(风华)(编带)(RoHS) | AC32: 0.0018 | AD32: 301H0103H1 | AE32: 片式电阻 RC0603FR-0710KL 1/10W,10KΩ,1%,0603(国巨)(编带)(RoHS) | AF32: 0.0025 | AG32: N30101002366 | AH32: 片式电阻 CR0603FA1002G 1/10W,10KΩ,1%,0603(丽智)(编带)(RoHS) | AI32: 报价中
A33: 33 | B33: 硬件 | C33: N30199000047 | D33: 片式电阻 1/10W,1KΩ,1%,0603(编带)(RoHS)(互换件) | E33: AB级替换 | F33: SMT | G33: 25 | H33: N30101002910 | I33: 片式电阻 RS-03K1001FT 1/10W,1KΩ,1%,0603(风华)(编带)(RoHS) | J33: 陈虹 | K33: MHDZ2 | L33: 厦门美赫电子有限公司 | M33: 0.0018 | N33: 0 | O33: =G33*M33 -> 0.045 | T33: 56 | U33: 5000 | Z33: R6,12,41,43-45,58,60,64,67-71,76,93-97,224,261,270,299,456 | AA33: N30101007519 | AB33: 片式电阻 0603WAF1001T5E 1/10W,1KΩ,1%,0603(厚声)(编带)(RoHS) | AC33: 0.0018 | AD33: N30101006259 | AE33: 片式电阻 RC0603FR-071KL 1/10W,1KΩ,1%,0603(国巨)(编带)(RoHS) | AF33: 0.0025 | AG33: N30101002909 | AH33: 片式电阻 CR0603FA1001G 1/10W,1KΩ,1%,0603(丽智)(编带)(RoHS) | AI33: 报价中
A34: 34 | B34: 硬件 | C34: N30199000075 | D34: 片式电阻 1/10W,4.7KΩ,1%,0603(编带)(RoHS)(互换件) | E34: AB级替换 | F34: SMT | G34: 9 | H34: N30101002965 | I34: 片式电阻 RS-03K4701FT 1/10W,4.7KΩ,1%,0603(风华)(编带)(RoHS) | J34: 陈虹 | K34: MHDZ2 | L34: 厦门美赫电子有限公司 | M34: 0.0018 | N34: 0 | O34: =G34*M34 -> 0.0162 | T34: 56 | U34: 5000 | Z34: R2,8,46,49-51,103-105 | AA34: N30101007321 | AB34: 片式电阻 0603WAF4701T5E 1/10W,4.7KΩ,1%,0603(厚声)(编带)(RoHS) | AC34: 0.0018 | AD34: N30101006127 | AE34: 片式电阻 RC0603FR-074K7L 1/10W,4.7KΩ,1%,0603(国巨)(编带)(RoHS) | AF34: 0.0026 | AG34: N30101002964 | AH34: 片式电阻 CR0603FA4701G 1/10W,4.7KΩ,1%,0603(丽智)(编带)(RoHS) | AI34: 报价中
A35: 35 | B35: 硬件 | C35: N30199000085 | D35: 片式电阻 1/10W,20KΩ,1%,0603(编带)(RoHS)(互换件) | E35: AB级替换 | F35: SMT | G35: 2 | H35: N30101002985 | I35: 片式电阻 RS-03K2002FT 1/10W,20KΩ,1%,0603(风华)(编带)(RoHS) | J35: 陈虹 | K35: MHDZ2 | L35: 厦门美赫电子有限公司 | M35: 0.0018 | N35: 0 | O35: =G35*M35 -> 0.0036 | T35: 56 | U35: 5000 | Z35: R74,81 | AA35: N30101007433 | AB35: 片式电阻 0603WAF2002T5E 1/10W,20KΩ,1%,0603(厚声)(编带)(RoHS) | AC35: 0.0018 | AD35: N30101006246 | AE35: 片式电阻 RC0603FR-0720KL 1/10W,20KΩ,1%,0603(国巨)(编带)(RoHS) | AF35: 0.0026 | AG35: N30101002984 | AH35: 片式电阻 CR0603FA2002G 1/10W,20KΩ,1%,0603(丽智)(编带)(RoHS) | AI35: 报价中
A36: 36 | B36: 硬件 | C36: N30199000101 | D36: 片式电阻 1/10W,2.2KΩ,1%,0603(编带)(RoHS)(互换件) | E36: AB级替换 | F36: SMT | G36: 7 | H36: N30101003017 | I36: 片式电阻 RS-03K2201FT 1/10W,2.2KΩ,1%,0603(风华)(编带)(RoHS) | J36: 陈虹 | K36: MHDZ2 | L36: 厦门美赫电子有限公司 | M36: 0.0018 | N36: 0 | O36: =G36*M36 -> 0.0126 | T36: 56 | U36: 5000 | Z36: R17,22,28,29,35,40,117 | AA36: N30101007423 | AB36: 片式电阻 0603WAF2201T5E 1/10W,2.2KΩ,1%,0603(厚声)(编带)(RoHS) | AC36: 0.0018 | AD36: N30101006208 | AE36: 片式电阻 RC0603FR-072K2L 1/10W,2.2KΩ,1%,0603(国巨)(编带)(RoHS) | AF36: 0.0025 | AG36: N30101003016 | AH36: 片式电阻 CR0603FA2201G 1/10W,2.2KΩ,1%,0603(丽智)(编带)(RoHS) | AI36: 报价中
A37: 37 | B37: 硬件 | C37: N30199000108 | D37: 片式电阻 1/10W,22KΩ,1%,0603(编带)(RoHS)(互换件) | E37: AB级替换 | F37: SMT | G37: 2 | H37: N30101003031 | I37: 片式电阻 RS-03K2202FT 1/10W,22KΩ,1%,0603(风华)(编带)(RoHS) | J37: 虞思旻 | K37: MHDZ2 | L37: 厦门美赫电子有限公司 | M37: 0.0018 | N37: 0 | O37: =G37*M37 -> 0.0036 | T37: 56 | U37: 5000 | Z37: R56,61 | AA37: N30101007422 | AB37: 片式电阻 0603WAF2202T5E 1/10W,22KΩ,1%,0603(厚声)(编带)(RoHS) | AC37: 0.0018 | AD37: N30101006238 | AE37: 片式电阻 RC0603FR-0722KL 1/10W,22KΩ,1%,0603(国巨)(编带)(RoHS) | AF37: 0.0026 | AG37: N30101003030 | AH37: 片式电阻 CR0603FA2202G 1/10W,22KΩ,1%,0603(丽智)(编带)(RoHS) | AI37: 报价中
A38: 38 | B38: 硬件 | C38: N30199000111 | D38: 片式电阻 1/10W,15KΩ,1%,0603(编带)(RoHS)(互换件) | E38: AB级替换 | F38: SMT | G38: 8 | H38: N30101003071 | I38: 片式电阻 RS-03K1502FT 1/10W,15KΩ,1%,0603(风华)(编带)(RoHS) | J38: 陈虹 | K38: MHDZ2 | L38: 厦门美赫电子有限公司 | M38: 0.0018 | N38: 0 | O38: =G38*M38 -> 0.0144 | T38: 56 | U38: 5000 | Z38: R148,149,174,175,248,249,274,275 | AA38: N30101007468 | AB38: 片式电阻 0603WAF1502T5E 1/10W,15KΩ,1%,0603(厚声)(编带)(RoHS) | AC38: 0.0018 | AD38: N30101006296 | AE38: 片式电阻 RC0603FR-0715KL 1/10W,15KΩ,1%,0603(国巨)(编带)(RoHS) | AF38: 0.0026 | AG38: N30101003070 | AH38: 片式电阻 CR0603FA1502G 1/10W,15KΩ,1%,0603(丽智)(编带)(RoHS) | AI38: 报价中
A39: 39 | B39: 硬件 | C39: N30199000117 | D39: 片式电阻 1/4W,100Ω,5%,1206(编带)(RoHS)(互换件) | E39: AB级替换 | F39: SMT | G39: 2 | H39: N30101003083 | I39: 片式电阻 RS-06K101JT 1/4W,100Ω,5%,1206(风华)(编带)(RoHS) | J39: 陈虹 | K39: MHDZ2 | L39: 厦门美赫电子有限公司 | M39: 0.0042 | N39: 0 | O39: =G39*M39 -> 0.0084 | T39: 56 | U39: 5000 | Z39: R228,230 | AA39: N30101006680 | AB39: 片式电阻 1206W4J0101T5E 1/4W,100Ω,5%,1206(厚声)(编带)(RoHS) | AC39: 0.0042 | AD39: N30101005376 | AE39: 片式电阻 RC1206JR-07100RL 1/4W,100Ω,5%,1206(国巨)(编带)(RoHS) | AF39: 0.0075 | AG39: N30101003082 | AH39: 片式电阻 CR1206J40101G 1/4W,100Ω,5%,1206(丽智)(编带)(RoHS) | AI39: 报价中
A40: 40 | B40: 硬件 | C40: N30199000127 | D40: 片式电阻 1/10W,5.6KΩ,1%,0603(编带)(RoHS)(互换件) | E40: AB级替换 | F40: SMT | G40: 1 | H40: N30101003103 | I40: 片式电阻 RS-03K5601FT 1/10W,5.6KΩ,1%,0603(风华)(编带)(RoHS) | J40: 陈虹 | K40: MHDZ2 | L40: 厦门美赫电子有限公司 | M40: 0.0018 | N40: 0 | O40: =G40*M40 -> 0.0018 | T40: 56 | U40: 5000 | Z40: R84 | AA40: N30101007296 | AB40: 片式电阻 0603WAF5601T5E 1/10W,5.6KΩ,1%,0603(厚声)(编带)(RoHS) | AC40: 0.0018 | AD40: N30101006101 | AE40: 片式电阻 RC0603FR-075K6L 1/10W,5.6KΩ,1%,0603(国巨)(编带)(RoHS) | AF40: 0.0026 | AG40: N30101003102 | AH40: 片式电阻 CR0603FA5601G 1/10W,5.6KΩ,1%,0603(丽智)(编带)(RoHS) | AI40: 报价中
A41: 41 | B41: 硬件 | C41: N30199000137 | D41: 片式电阻 1/10W,470Ω,1%,0603(编带)(RoHS)(互换件) | E41: AB级替换 | F41: SMT | G41: 1 | H41: N30101007322 | I41: 片式电阻 0603WAF4700T5E 1/10W,470Ω,1%,0603(厚声)(编带)(RoHS) | J41: 罗城 | K41: 10648 | L41: 厚声国际贸易（昆山）有限公司 | M41: 0.0018 | N41: 0 | O41: =G41*M41 -> 0.0018 | T41: 56 | U41: 0 | V41: 5000 | Z41: R13 | AA41: N30101006140 | AB41: 片式电阻 RC0603FR-07470RL 1/10W,470Ω,1%,0603(国巨)(编带)(RoHS) | AC41: 0.0025 | AD41: N30101003123 | AE41: 片式电阻 RS-03K4700FT 1/10W,470Ω,1%,0603(风华)(编带)(RoHS) | AF41: 0.0025 | AG41: 301H0471H1 | AH41: 片式电阻 RC0603FR-07470RL/0603WAF4700T5E 1/10W,470Ω,1%,0603(国巨/厚声)(编带)(RoHS) | AI41: 报价中
A42: 42 | B42: 硬件 | C42: N30199000146 | D42: 片式电阻 1/10W,3KΩ,1%,0603(编带)(RoHS)(互换件) | E42: AB级替换 | F42: SMT | G42: 8 | H42: N30101003140 | I42: 片式电阻 RS-03K3001FT 1/10W,3KΩ,1%,0603(风华)(编带)(RoHS) | J42: 虞思旻 | K42: MHDZ2 | L42: 厦门美赫电子有限公司 | M42: 0.0018 | N42: 0 | O42: =G42*M42 -> 0.0144 | T42: 56 | U42: 5000 | Z42: R146,147,150,151,172,173,176,177 | AA42: N30101007384 | AB42: 片式电阻 0603WAF3001T5E 1/10W,3KΩ,1%,0603(厚声)(编带)(RoHS) | AC42: 0.0018 | AD42: N30101006156 | AE42: 片式电阻 RC0603FR-073KL 1/10W,3KΩ,1%,0603(国巨)(编带)(RoHS) | AF42: 0.0026 | AG42: 301H0033H1 | AH42: 片式电阻 RC0603FR-073KL/0603WAF3001T5E 1/10W,3KΩ,1%,0603(国巨/厚声)(编带)(RoHS) | AI42: 报价中
A43: 43 | B43: 硬件 | C43: N30199000171 | D43: 片式电阻 1/10W,5.1KΩ,1%,0603(编带)(RoHS)(互换件) | E43: AB级替换 | F43: SMT | G43: 2 | H43: N30101007306 | I43: 片式电阻 0603WAF5101T5E 1/10W,5.1KΩ,1%,0603(厚声)(编带)(RoHS) | J43: 罗城 | K43: 10648 | L43: 厚声国际贸易（昆山）有限公司 | M43: 0.0018 | N43: 0 | O43: =G43*M43 -> 0.0036 | T43: 56 | U43: 0 | V43: 5000 | Z43: R137,138 | AA43: N30101003189 | AB43: 片式电阻 RS-03K5101FT 1/10W,5.1KΩ,1%,0603(风华)(编带)(RoHS) | AC43: 0.0024 | AD43: N30101006104 | AE43: 片式电阻 RC0603FR-075K1L 1/10W,5.1KΩ,1%,0603(国巨)(编带)(RoHS) | AF43: 0.0026 | AG43: 301H0512H1 | AH43: 片式电阻 RC0603FR-075K1L/0603WAF5101T5E 1/10W,5.1KΩ,1%,0603(国巨/厚声)(编带)(RoHS) | AI43: 报价中
A44: 44 | B44: 硬件 | C44: N30199000219 | D44: 片式电阻 1/10W,100Ω,1%,0603(编带)(RoHS)(互换件) | E44: AB级替换 | F44: SMT | G44: 29 | H44: N30101003284 | I44: 片式电阻 RS-03K1000FT 1/10W,100Ω,1%,0603(风华)(编带)(RoHS) | J44: 陈虹 | K44: MHDZ2 | L44: 厦门美赫电子有限公司 | M44: 0.0018 | N44: 0 | O44: =G44*M44 -> 0.0522 | T44: 56 | U44: 5000 | Z44: R18,24,25,32,33,106-111,119-130,212-217 | AA44: N30101007520 | AB44: 片式电阻 0603WAF1000T5E 1/10W,100Ω,1%,0603(厚声)(编带)(RoHS) | AC44: 0.0018 | AD44: N30101006338 | AE44: 片式电阻 RC0603FR-07100RL 1/10W,100Ω,1%,0603(国巨)(编带)(RoHS) | AF44: 0.0025 | AG44: 301H0101H1 | AH44: 片式电阻 RC0603FR-07100RL/0603WAF1000T5E 1/10W,100Ω,1%,0603(国巨/厚声)(编带)(RoHS) | AI44: 报价中
A45: 45 | B45: 硬件 | C45: N30199000237 | D45: 片式电阻 1/10W,510Ω,1%,0603(编带)(RoHS)(互换件) | E45: AB级替换 | F45: SMT | G45: 2 | H45: N30101003319 | I45: 片式电阻 RS-03K5100FT 1/10W,510Ω,1%,0603(风华)(编带)(RoHS) | J45: 虞思旻 | K45: MHDZ2 | L45: 厦门美赫电子有限公司 | M45: 0.0018 | N45: 0 | O45: =G45*M45 -> 0.0036 | T45: 56 | U45: 5000 | Z45: R66,78 | AA45: N30101007307 | AB45: 片式电阻 0603WAF5100T5E 1/10W,510Ω,1%,0603(厚声)(编带)(RoHS) | AC45: 0.0018 | AD45: N30101006120 | AE45: 片式电阻 RC0603FR-07510RL 1/10W,510Ω,1%,0603(国巨)(编带)(RoHS) | AF45: 0.0025 | AG45: 301H0511H1 | AH45: 片式电阻 RC0603FR-07510RL/0603WAF5100T5E 1/10W,510Ω,1%,0603(国巨/厚声)(编带)(RoHS) | AI45: 报价中
A46: 46 | B46: 硬件 | C46: N30199000335 | D46: 片式电阻 1/10W,1.5KΩ,1%,0603(编带)(RoHS)(互换件) | E46: AB级替换 | F46: SMT | G46: 1 | H46: N30101003511 | I46: 片式电阻 RS-03K1501FT 1/10W,1.5KΩ,1%,0603(风华)(编带)(RoHS) | J46: 虞思旻 | K46: MHDZ2 | L46: 厦门美赫电子有限公司 | M46: 0.0018 | N46: 0 | O46: =G46*M46 -> 0.0018 | T46: 56 | U46: 5000 | Z46: R54 | AA46: N30101007469 | AB46: 片式电阻 0603WAF1501T5E 1/10W,1.5KΩ,1%,0603(厚声)(编带)(RoHS) | AC46: 0.0018 | AD46: N30101006268 | AE46: 片式电阻 RC0603FR-071K5L 1/10W,1.5KΩ,1%,0603(国巨)(编带)(RoHS) | AF46: 0.0026 | AG46: N30101003510 | AH46: 片式电阻 CR0603FA1501G 1/10W,1.5KΩ,1%,0603(丽智)(编带)(RoHS) | AI46: 报价中
A47: 47 | B47: 硬件 | C47: N30199000342 | D47: 片式电阻 1/10W,51KΩ,1%,0603(编带)(RoHS)(互换件) | E47: AB级替换 | F47: SMT | G47: 2 | H47: N30101003525 | I47: 片式电阻 RS-03K5102FT 1/10W,51KΩ,1%,0603(风华)(编带)(RoHS) | J47: 虞思旻 | K47: MHDZ2 | L47: 厦门美赫电子有限公司 | M47: 0.0018 | N47: 0 | O47: =G47*M47 -> 0.0036 | T47: 56 | U47: 5000 | Z47: R15,36 | AA47: N30101007305 | AB47: 片式电阻 0603WAF5102T5E 1/10W,51KΩ,1%,0603(厚声)(编带)(RoHS) | AC47: 0.0018 | AD47: N30101006118 | AE47: 片式电阻 RC0603FR-0751KL 1/10W,51KΩ,1%,0603(国巨)(编带)(RoHS) | AF47: 0.0026 | AG47: N30101003524 | AH47: 片式电阻 CR0603FA5102G 1/10W,51KΩ,1%,0603(丽智)(编带)(RoHS) | AI47: 报价中
A48: 48 | B48: 硬件 | C48: N30199000397 | D48: 片式电阻 1/4W,20KΩ,1%,1206(编带)(RoHS)(互换件) | E48: AB级替换 | F48: SMT | G48: 1 | H48: N30101006792 | I48: 片式电阻 1206W4F2002T5E 1/4W,20KΩ,1%,1206(厚声)(编带)(RoHS) | J48: 陈虹 | K48: HSMY2 | L48: 厚声国际贸易（昆山）有限公司 | M48: 0.0058 | N48: 0 | O48: =G48*M48 -> 0.0058 | T48: 49 | U48: 1 | Z48: R57 | AA48: N30101003634 | AB48: 片式电阻 RS-06K2002FT 1/4W,20KΩ,1%,1206(风华)(编带)(RoHS) | AC48: 0.0069 | AD48: N30101005517 | AE48: 片式电阻 RC1206FR-0720KL 1/4W,20KΩ,1%,1206(国巨)(编带)(RoHS) | AF48: 0.008 | AG48: N30101003633 | AH48: 片式电阻 CR1206F42002G 1/4W,20KΩ,1%,1206(丽智)(编带)(RoHS) | AI48: 报价中
A49: 49 | B49: 硬件 | C49: N30199000444 | D49: 片式电阻 1/10W,6.2KΩ,1%,0603(编带)(RoHS)(互换件) | E49: AB级替换 | F49: SMT | G49: 1 | H49: N30101001125 | I49: 片式电阻 0603WAF6201T5E 1/10W,6.2KΩ,1%,0603(厚声)(编带)(RoHS) | J49: 陈虹 | K49: HSMY2 | L49: 厚声国际贸易（昆山）有限公司 | M49: 0.0018 | N49: 0 | O49: =G49*M49 -> 0.0018 | T49: 84 | U49: 5000 | Z49: R79 | AA49: N30101003728 | AB49: 片式电阻 RS-03K6201FT 1/10W,6.2KΩ,1%,0603(风华)(编带)(RoHS) | AC49: 0.0018 | AD49: 301H0622H1 | AE49: 片式电阻 RC0603FR-076K2L 1/10W,6.2KΩ,1%,0603(国巨)(编带)(RoHS) | AF49: 0.0025 | AG49: N30101003727 | AH49: 片式电阻 CR0603FA6201G 1/10W,6.2KΩ,1%,0603(丽智)(编带)(RoHS) | AI49: 报价中
A50: 50 | B50: 硬件 | C50: N30199000493 | D50: 片式电阻 1/4W,120Ω,5%,1206(编带)(RoHS)(互换件) | E50: AB级替换 | F50: SMT | G50: 2 | H50: N30101003826 | I50: 片式电阻 RS-06K121JT 1/4W,120Ω,5%,1206(风华)(编带)(RoHS) | J50: 陈虹 | K50: MHDZ2 | L50: 厦门美赫电子有限公司 | M50: 0.0043 | N50: 0 | O50: =G50*M50 -> 0.0086 | T50: 56 | U50: 5000 | V50: 5000 | Z50: R19,229 | AA50: N30101006672 | AB50: 片式电阻 1206W4J0121T5E 1/4W,120Ω,5%,1206(厚声)(编带)(RoHS) | AC50: 0.0043 | AD50: N30101005381 | AE50: 片式电阻 RC1206JR-07120RL 1/4W,120Ω,5%,1206(国巨)(编带)(RoHS) | AF50: 0.0075 | AG50: 301H012185 | AH50: 片式电阻 RC1206JR-07120RL/1206W4J0121T5E 1/4W,120Ω,5%,1206(国巨/厚声)(编带)(RoHS) | AI50: 报价中
A51: 51 | B51: 硬件 | C51: N30199000523 | D51: 片式电阻 1/4W,1KΩ,1%,1206(编带)(RoHS)(互换件) | E51: AB级替换 | F51: SMT | G51: 4 | H51: N30101003885 | I51: 片式电阻 RS-06K1001FT 1/4W,1KΩ,1%,1206(风华)(编带)(RoHS) | J51: 陈虹 | K51: MHDZ2 | L51: 厦门美赫电子有限公司 | M51: 0.0057 | N51: 0 | O51: =G51*M51 -> 0.0228 | T51: 56 | U51: 5000 | Z51: R37,86,88,91 | AA51: N30101006828 | AB51: 片式电阻 1206W4F1001T5E 1/4W,1KΩ,1%,1206(厚声)(编带)(RoHS) | AC51: 0.0057 | AD51: N30101005505 | AE51: 片式电阻 RC1206FR-071KL 1/4W,1KΩ,1%,1206(国巨)(编带)(RoHS) | AF51: 0.0075 | AG51: N30101003884 | AH51: 片式电阻 CR1206F41001G 1/4W,1KΩ,1%,1206(丽智)(编带)(RoHS) | AI51: 报价中
A52: 52 | B52: 硬件 | C52: N30199000561 | D52: 片式电阻 1/4W,47Ω,1%,1206(编带)(RoHS)(互换件) | E52: AB级替换 | F52: SMT | G52: 10 | H52: N30101006724 | I52: 片式电阻 1206W4F470JT5E 1/4W,47Ω,1%,1206(厚声)(编带)(RoHS) | J52: 罗城 | K52: 10648 | L52: 厚声国际贸易（昆山）有限公司 | M52: 0.0058 | N52: 0 | O52: =G52*M52 -> 0.058 | T52: 56 | U52: 0 | V52: 5000 | Z52: R1,3,59,72,131,133,135,204,206,208 | AA52: N30101003958 | AB52: 片式电阻 RS-06K47R0FT 1/4W,47Ω,1%,1206(风华)(编带)(RoHS) | AC52: 0.0069 | AD52: N30101005579 | AE52: 片式电阻 RC1206FR-0747RL 1/4W,47Ω,1%,1206(国巨)(编带)(RoHS) | AF52: 0.008 | AG52: N30101003957 | AH52: 片式电阻 CR1206F447R0G 1/4W,47Ω,1%,1206(丽智)(编带)(RoHS) | AI52: 报价中
A53: 53 | B53: 硬件 | C53: N30199000577 | D53: 片式电阻 1/4W,300KΩ,1%,1206(编带)(RoHS)(互换件) | E53: AB级替换 | F53: SMT | G53: 9 | H53: N30101006758 | I53: 片式电阻 1206W4F3003T5E 1/4W,300KΩ,1%,1206(厚声)(编带)(RoHS) | J53: 陈虹 | K53: HSMY2 | L53: 厚声国际贸易（昆山）有限公司 | M53: 0.0058 | N53: 0 | O53: =G53*M53 -> 0.0522 | T53: 49 | U53: 1 | Z53: R101,102,115,152,169-171,180,181 | AA53: N30101003990 | AB53: 片式电阻 RS-06K3003FT 1/4W,300KΩ,1%,1206(风华)(编带)(RoHS) | AC53: 0.0069 | AD53: N30101005551 | AE53: 片式电阻 RC1206FR-07300KL 1/4W,300KΩ,1%,1206(国巨)(编带)(RoHS) | AF53: 0.008 | AG53: N30101000672 | AH53: 片式电阻 RC1206FR-07300KL/1206W4F3003T5E 1/4W,300KΩ,1%,1206(国巨/厚声)(编带)(RoHS) | AI53: 报价中
A54: 54 | B54: 硬件 | C54: N30199000605 | D54: 片式电阻 1/4W,10Ω,1%,1206(编带)(RoHS)(互换件) | E54: AB级替换 | F54: SMT | G54: 6 | H54: N30101006824 | I54: 片式电阻 1206W4F100JT5E 1/4W,10Ω,1%,1206(厚声)(编带)(RoHS) | J54: 罗城 | K54: 10648 | L54: 厚声国际贸易（昆山）有限公司 | M54: 0.0058 | N54: 0 | O54: =G54*M54 -> 0.0348 | T54: 56 | U54: 0 | V54: 5000 | Z54: R132,134,136,203,205,207 | AA54: N30101004045 | AB54: 片式电阻 RS-06K10R0FT 1/4W,10Ω,1%,1206(风华)(编带)(RoHS) | AC54: 0.0072 | AD54: N30101005488 | AE54: 片式电阻 RC1206FR-0710RL 1/4W,10Ω,1%,1206(国巨)(编带)(RoHS) | AF54: 0.0279 | AG54: N30101004044 | AH54: 片式电阻 CR1206F410R0G 1/4W,10Ω,1%,1206(丽智)(编带)(RoHS) | AI54: 报价中
A55: 55 | B55: 硬件 | C55: N30199000614 | D55: 片式电阻 1/10W,7.5KΩ,1%,0603(编带)(RoHS)(互换件) | E55: AB级替换 | F55: SMT | G55: 13 | H55: N30101007264 | I55: 片式电阻 0603WAF7501T5E 1/10W,7.5KΩ,1%,0603(厚声)(编带)(RoHS) | J55: 陈虹 | K55: HSMY2 | L55: 厚声国际贸易（昆山）有限公司 | M55: 0.0018 | N55: 0 | O55: =G55*M55 -> 0.0234 | T55: 49 | U55: 1 | Z55: R53,55,85,139,140,157-162,239,240 | AA55: N30101004063 | AB55: 片式电阻 RS-03K7501FT 1/10W,7.5KΩ,1%,0603(风华)(编带)(RoHS) | AC55: 0.0022 | AD55: N30101006068 | AE55: 片式电阻 RC0603FR-077K5L 1/10W,7.5KΩ,1%,0603(国巨)(编带)(RoHS) | AF55: 0.0026 | AG55: N30101001061 | AH55: 片式电阻 RC0603FR-077K5L/0603WAF7501T5E 1/10W,7.5KΩ,1%,0603(国巨/厚声)(编带)(RoHS) | AI55: 报价中
A56: 56 | B56: 硬件 | C56: N30199000619 | D56: 片式电阻 1/10W,10.5KΩ,1%,0603(编带)(RoHS)(互换件) | E56: AB级替换 | F56: SMT | G56: 1 | H56: N30101007511 | I56: 片式电阻 0603WAF1052T5E 1/10W,10.5KΩ,1%,0603(厚声)(编带)(RoHS) | J56: 陈虹 | K56: HSMY2 | L56: 厚声国际贸易（昆山）有限公司 | M56: 0.0018 | N56: 0 | O56: =G56*M56 -> 0.0018 | T56: 42 | U56: 1 | Z56: R48 | AA56: N30101004220 | AB56: 片式电阻 RS-03K1052FT 1/10W,10.5KΩ,1%,0603(风华)(编带)(RoHS) | AC56: 0.0022 | AD56: N30101006332 | AE56: 片式电阻 RC0603FR-0710K5L 1/10W,10.5KΩ,1%,0603(国巨)(编带)(RoHS) | AF56: 0.0026 | AG56: N30101001496 | AH56: 片式电阻 RC0603FR-0710K5L/0603WAF1052T5E 1/10W,10.5KΩ,1%,0603(国巨/厚声)(编带)(RoHS) | AI56: 报价中
A57: 57 | B57: 硬件 | C57: N30199000620 | D57: 片式电阻 1/10W,1.2KΩ,1%,0603(编带)(RoHS)(互换件) | E57: AB级替换 | F57: SMT | G57: 2 | H57: N30101007498 | I57: 片式电阻 0603WAF1201T5E 1/10W,1.2KΩ,1%,0603(厚声)(编带)(RoHS) | J57: 罗城 | K57: 10648 | L57: 厚声国际贸易（昆山）有限公司 | M57: 0.0018 | N57: 0 | O57: =G57*M57 -> 0.0036 | T57: 56 | U57: 0 | V57: 5000 | Z57: R154,156 | AA57: N30101004224 | AB57: 片式电阻 RS-03K1201FT 1/10W,1.2KΩ,1%,0603(风华)(编带)(RoHS) | AC57: 0.0023 | AD57: N30101006272 | AE57: 片式电阻 RC0603FR-071K2L 1/10W,1.2KΩ,1%,0603(国巨)(编带)(RoHS) | AF57: 0.0026 | AG57: 301H0122H1 | AH57: 片式电阻 RC0603FR-071K2L/0603WAF1201T5E 1/10W,1.2KΩ,1%,0603(国巨/厚声)(编带)(RoHS) | AI57: 报价中
A58: 58 | B58: 硬件 | C58: N30199000693 | D58: 片式电阻 1/10W,0Ω,1%,0603(编带)(RoHS)(互换件) | E58: AB级替换 | F58: SMT | G58: 3 | H58: N30101004568 | I58: 片式电阻 RS-03K000FT 1/10W,0Ω,1%,0603(风华)(编带)(RoHS) | J58: 虞思旻 | K58: MHDZ2 | L58: 厦门美赫电子有限公司 | M58: 0.0018 | N58: 0 | O58: =G58*M58 -> 0.0054 | T58: 56 | U58: 1 | Z58: A0,R0,,R79A | AA58: N30101004534 | AB58: 片式电阻 0603WAF0000T5E 1/10W,0Ω,1%,0603(厚声)(编带)(RoHS) | AC58: 0.002 | AD58: N30101002504 | AE58: 片式电阻 RC0603FR-070RL 1/10W,0Ω,1%,0603(国巨)(编带)(RoHS) | AF58: 0.0026
A59: 59 | B59: 硬件 | C59: N30199000804 | D59: 片式电阻 1/4W,30Ω,1%,1206(编带)(RoHS)(互换件) | E59: AB级替换 | F59: SMT | G59: 3 | H59: N30101004863 | I59: 片式电阻 1206W4F300JT5E 1/4W,30Ω,1%,1206(厚声)(编带)(RoHS) | J59: 江华媛 | K59: 10648 | L59: 厚声国际贸易（昆山）有限公司 | M59: 0.0065 | N59: 0 | O59: =G59*M59 -> 0.0195 | T59: 42 | U59: 5000 | V59: 5000 | Z59: R209-211 | AA59: N30101004973 | AB59: 片式电阻 RS-06K30R0FT 1/4W,30Ω,1%,1206(风华)(编带)(RoHS) | AC59: 0.0072 | AD59: N30101002273 | AE59: 片式电阻 RC1206FR-0730RL 1/4W,30Ω,1%,1206(国巨)(编带)(RoHS) | AF59: 0.0076
A60: 60 | B60: 硬件 | C60: N30199000819 | D60: 片式电阻 1/10W,910Ω,1%,0603(编带)(RoHS)(互换件) | E60: AB级替换 | F60: SMT | G60: 2 | H60: N30101004847 | I60: 片式电阻 0603WAF9100T5E 1/10W,910Ω,1%,0603(厚声)(编带)(RoHS) | J60: 江华媛 | K60: 10648 | L60: 厚声国际贸易（昆山）有限公司 | M60: 0.002 | N60: 0 | O60: =G60*M60 -> 0.004 | T60: 42 | U60: 5000 | V60: 5000 | Z60: R153,155 | AA60: N30101004970 | AB60: 片式电阻 RS-03K9100FT 1/10W,910Ω,1%,0603(风华)(编带)(RoHS) | AC60: 0.0022 | AD60: N30101002401 | AE60: 片式电阻 RC0603FR-07910RL 1/10W,910Ω,1%,0603(国巨)(编带)(RoHS) | AF60: 0.0025
A61: 61 | B61: 硬件 | C61: N30301000078 | D61: 压敏电阻 561KD14 (君耀)(RoHS) | E61: AB级替换 | F61: 插焊 | G61: 2 | H61: N30301000078 | I61: 压敏电阻 561KD14 (君耀)(RoHS) | J61: 江华媛 | K61: 10266 | L61: 深圳市超利维实业有限公司 | M61: 0.286 | N61: 0 | O61: =G61*M61 -> 0.572 | T61: 84 | U61: 1200 | V61: 300 | Z61: RV5,6
A62: 62 | B62: 硬件 | C62: N30301000122 | D62: 压敏电阻 911KD14-TR 550Vac,10%,P=7.5,Φ14(175J)(君耀)(编带)(RoHS) | E62: AB级替换 | F62: 插焊 | G62: 3 | H62: N30301000122 | I62: 压敏电阻 911KD14-TR 550Vac,10%,P=7.5,Φ14(175J)(君耀)(编带)(RoHS) | J62: 521 | K62: 10266 | L62: 深圳市超利维实业有限公司 | M62: 0.4425 | N62: 0 | O62: =G62*M62 -> 1.3275 | T62: 70 | U62: 2000 | V62: 400 | Z62: RV2-4
A63: 63 | B63: 硬件 | C63: N30303000192 | D63: PTC热敏电阻 MZ32-47RHAGD03-C 280Vac,7A,47Ω,25%,P=8.5(安培龙)(RoHS) | E63: AB级替换 | F63: 插焊 | G63: 1 | H63: N30303000192 | I63: PTC热敏电阻 MZ32-47RHAGD03-C 280Vac,7A,47Ω,25%,P=8.5(安培龙)(RoHS) | J63: 521 | K63: 10666 | L63: 深圳安培龙科技股份有限公司 | M63: 1.0619 | N63: 0 | O63: =G63*M63 -> 1.0619 | T63: 42 | U63: 1 | V63: 1 | Z63: R405
A64: 64 | B64: 硬件 | C64: N30303000193 | D64: PTC热敏电阻 MZ32-68RNAGD01-C 440Vac,27A,68Ω,30%,P=8.5(安培龙)(RoHS) | E64: AB级替换 | F64: 插焊 | G64: 1 | H64: N30303000193 | I64: PTC热敏电阻 MZ32-68RNAGD01-C 440Vac,27A,68Ω,30%,P=8.5(安培龙)(RoHS) | J64: 521 | K64: 10666 | L64: 深圳安培龙科技股份有限公司 | M64: 2.1239 | N64: 0 | O64: =G64*M64 -> 2.1239 | T64: 42 | U64: 1 | V64: 1 | Z64: R404
A65: 65 | B65: 硬件 | C65: N30309000009 | D65: 电流传感器 STK-50PL (希磁)(JCI 专用)(RoHS) | E65: AB级替换 | F65: 插焊 | G65: 1 | H65: N30309000009 | I65: 电流传感器 STK-50PL (希磁)(JCI 专用)(RoHS) | J65: 江华媛 | K65: BBXC2 | L65: 安徽希磁科技股份有限公司（特采) | M65: 9.2 | N65: 0 | O65: =G65*M65 -> 9.2 | P65: 8.2 | R65: 46034 | S65: 希磁代理 | T65: 56 | U65: 2400 | Z65: H1
A66: 66 | B66: 硬件 | C66: N30501000394 | D66: 安规薄膜电容 (X2) HQX225K0275NAYCCL15S 2.2uF,10%,275Vac,26.5X13X23,P=22.5(昱电)(RoHS) | E66: AB级替换 | F66: 插焊 | G66: 3 | H66: N30501000394 | I66: 安规薄膜电容 (X2) HQX225K0275NAYCCL15S 2.2uF,10%,275Vac,26.5X13X23,P=22.5(昱电)(RoHS) | J66: 521 | K66: 10656 | L66: 厦门大毅电子有限公司 | M66: 1.2 | N66: 0 | O66: =G66*M66 -> 3.6 | T66: 30 | U66: 1 | V66: 1 | Z66: C130,131,133
A67: 67 | B67: 硬件 | C67: N30503000105 | D67: 聚丙烯膜电容 C372J105J6SC000 1uF,5%,630V,P=15(法拉)(RoHS) | E67: AB级替换 | F67: 插焊 | G67: 3 | H67: N30503000105 | I67: 聚丙烯膜电容 C372J105J6SC000 1uF,5%,630V,P=15(法拉)(RoHS) | J67: 江华媛 | K67: 10715 | L67: 厦门法拉电子股份有限公司 | M67: 0.65 | N67: 0 | O67: =G67*M67 -> 1.95 | T67: 63 | U67: 1500 | V67: 1500 | Z67: C98,99,208
A68: 68 | B68: 硬件 | C68: N30503000217 | D68: 聚丙烯膜电容 C322J222J30A301 2.2nF,5%,630Vdc,P=7.5(法拉)(编带)(RoHS) | E68: AB级替换 | F68: 插焊 | G68: 1 | H68: N30503000217 | I68: 聚丙烯膜电容 C322J222J30C000 2.2nF,5%,630Vdc,P=7.5(法拉)(编带)(RoHS) | J68: 521 | K68: 10715 | L68: 厦门法拉电子股份有限公司 | M68: 0.18 | N68: 0 | O68: =G68*M68 -> 0.18 | T68: 45 | U68: 1000 | V68: 1000 | Z68: C10
A69: 69 | B69: 硬件 | C69: N30503000218 | D69: 聚丙烯膜电容 C822J102J30A301 1nF,5%,630Vdc,P=7.5(法拉)(编带)(RoHS) | E69: AB级替换 | F69: 插焊 | G69: 1 | H69: N30503000218 | I69: 聚丙烯膜电容 C822J102J30C000 1nF,5%,630Vdc,P=7.5(法拉)(编带)(RoHS) | J69: 521 | K69: 10715 | L69: 厦门法拉电子股份有限公司 | M69: 0.22 | N69: 0 | O69: =G69*M69 -> 0.22 | T69: 70 | U69: 1000 | V69: 1000 | Z69: C124
A70: 70 | B70: 硬件 | C70: N30503000219 | D70: 聚丙烯膜电容 MKP21-1000V474K 470nF,10%,1KVdc,P=22.5(NJTJ专用)(华裕)(RoHS) | E70: AB级替换 | F70: 插焊 | G70: 1 | H70: N30503000219 | I70: 聚丙烯膜电容 MKP21-1000V474K 470nF,10%,1KVdc,P=22.5(NJTJ专用)(华裕)(RoHS) | J70: 521 | K70: 10250 | L70: 深圳市黑快能科技发展有限公司 | M70: 0.335 | N70: 0 | O70: =G70*M70 -> 0.335 | T70: 15 | U70: 1 | V70: 1 | Z70: C50
A71: 71 | B71: 硬件 | C71: N30503000244 | D71: 聚丙烯膜电容 EZPV1B406MTC 40uF,10%,1.1KVdc,57.5X56X35,P=52.5(国创提供)(符合AEC-Q200)(Panasonic)(RoHS) | E71: AB级替换 | F71: 插焊 | G71: 3 | H71: N30503000244 | I71: 聚丙烯膜电容 EZPV1B406MTC 40uF,10%,1.1KVdc,57.5X56X35,P=52.5(国创提供)(符合AEC-Q200)(Panasonic)(RoHS) | J71: 196386 | L71: 20251014业务邮件通知客供料 | M71: 0 | N71: 0 | O71: =G71*M71 -> 0 | T71: 0 | X71: 客供料 | Z71: C125-127
A72: 72 | B72: 硬件 | C72: N30506000898 | D72: 铝电解电容 YXJ 16YXJ220MT16.3X11 220uF,20%,16V,105℃,6.3X11,P=2.5(Rubycon)(编带)(RoHS) | E72: AB级替换 | F72: 插焊 | G72: 2 | H72: N30506000898 | I72: 铝电解电容 YXJ 16YXJ220MT16.3X11 220uF,20%,16V,105℃,6.3X11,P=2.5(Rubycon)(编带)(RoHS) | J72: 虞思旻 | K72: XMAEH | L72: 厦门埃尔华进出口有限公司 | M72: 0.145 | N72: 0 | O72: =G72*M72 -> 0.29 | T72: 77 | U72: 2000 | Z72: C143,147
A73: 73 | B73: 硬件 | C73: N30506001051 | D73: 铝电解电容 35YXJ100MT16.3X11 100uF,20%,35V,105℃,6.3X11,P=2.5(Rubycon)(编带)(RoHS) | E73: AB级替换 | F73: 插焊 | G73: 2 | H73: N30506001051 | I73: 铝电解电容 35YXJ100MT16.3X11 100uF,20%,35V,105℃,6.3X11,P=2.5(Rubycon)(编带)(RoHS) | J73: 陈伟环 | K73: 10364 | L73: 厦门埃尔华进出口有限公司 | M73: 0.1513 | N73: 0 | O73: =G73*M73 -> 0.3026 | T73: 97 | U73: 2000 | V73: 2000 | Z73: C150,158
A74: 74 | B74: 硬件 | C74: N30506001064 | D74: 铝电解电容 35YXJ470MT810X16 470uF,20%,35V,105℃,10X16,P=5(Rubycon)(编带)(RoHS) | E74: AB级替换 | F74: 插焊 | G74: 4 | H74: N30506001064 | I74: 铝电解电容 35YXJ470MT810X16 470uF,20%,35V,105℃,10X16,P=5(Rubycon)(编带)(RoHS) | J74: 陈伟环 | K74: xmaeh | L74: 厦门埃尔华进出口有限公司 | M74: 0.3969 | N74: 0 | O74: =G74*M74 -> 1.5876 | T74: 112 | U74: 1000 | Z74: C140,144-146
A75: 75 | B75: 硬件 | C75: N30506001069 | D75: 铝电解电容 50YXF47MT16.3X11 47uF,20%,50V,105℃,6.3X11,P=2.5(Rubycon)(编带)(RoHS) | E75: AB级替换 | F75: 插焊 | G75: 2 | H75: N30506001069 | I75: 铝电解电容 50YXF47MT16.3X11 47uF,20%,50V,105℃,6.3X11,P=2.5(Rubycon)(编带)(RoHS) | J75: 陈伟环 | K75: xmaeh | L75: 厦门埃尔华进出口有限公司 | M75: 0.1401 | N75: 0 | O75: =G75*M75 -> 0.2802 | T75: 91 | U75: 1000 | Z75: C138,139
A76: 76 | B76: 硬件 | C76: N30506002046 | D76: 铝电解电容 LB1E471MF160B35CE0 470uF,20%,25V,105℃,8X16,P=3.5,6000h(华威)(编带)(RoHS) | E76: AB级替换 | F76: 插焊 | G76: 1 | H76: N30506002046 | I76: 铝电解电容 LB1E471MF160B35CE0 470uF,20%,25V,105℃,8X16,P=3.5(华威)(编带)(RoHS) | J76: 陈伟环 | K76: 10033 | L76: 常州华威电子有限公司 | M76: 0.18 | N76: 0 | O76: =G76*M76 -> 0.18 | T76: 21 | U76: 20000 | V76: 1000 | Z76: C141
A77: 77 | B77: 硬件 | C77: N30506002166 | D77: 铝电解电容 ELT2WM152Y80LTSP 1500uF,20%,450V,105℃,40X80,P=14.2,5000h(艾华)(RoHS) | E77: AB级替换 | F77: 插焊 | G77: 1 | H77: N30506002166 | I77: 铝电解电容 ELT2WM152Y80LTSP 1500uF,20%,450V,105℃,40X80,P=14.2,5000h(艾华)(RoHS) | J77: 105935 | K77: 10003 | L77: 湖南艾华集团股份有限公司 | M77: 39.2 | N77: 0 | O77: =G77*M77 -> 39.2 | P77: 31.5 | R77: 46211 | S77: 艾华报价 | T77: 56 | U77: 0 | V77: 1000 | Z77: C132
A78: 78 | B78: 硬件 | C78: N30508000060 | D78: 安规陶瓷电容 (X1Y1) CD45-E2GA222M-VKA 2.2nF,20%,(X1)440Vac,(Y1)400Vac,P=10(TDK)(编带)(RoHS) | E78: AB级替换 | F78: 插焊 | G78: 2 | H78: N30508000060 | I78: 安规陶瓷电容 (X1Y1) CD45-E2GA222M-VKA 2.2nF,20%,(X1)440Vac,(Y1)400Vac,P=10(TDK)(编带)(RoHS) | J78: 罗城 | K78: 10758 | L78: 瑞瑜国际贸易（上海）有限公司 | M78: 0.1647 | N78: 0 | O78: =G78*M78 -> 0.3294 | T78: 112 | U78: 0 | V78: 1000 | Z78: C136,137
A79: 79 | B79: 硬件 | C79: N30515002473 | D79: 片式瓷介电容 0805B475K500NT X7R,4.7uF,10%,50V,0805(风华)(编带)(RoHS) | E79: AB级替换 | F79: SMT | G79: 2 | H79: N30515002473 | I79: 片式瓷介电容 0805B475K500NT X7R,4.7uF,10%,50V,0805(风华)(编带)(RoHS) | J79: 521 | K79: 10178 | L79: 厦门美赫电子有限公司 | M79: 0.1 | N79: 0 | O79: =G79*M79 -> 0.2 | T79: 56 | U79: 2000 | V79: 2000 | Z79: C9,20
A80: 80 | B80: 硬件 | C80: N30599000004 | D80: 片式瓷介电容 X7R,100nF,10%,50V,0603(编带)(RoHS)(互换件) | E80: AB级替换 | F80: SMT | G80: 45 | H80: N30515001005 | I80: 片式瓷介电容 0603B104K500NT X7R,100nF,10%,50V,0603(风华)(编带)(RoHS) | J80: 陈虹 | K80: MHDZ2 | L80: 厦门美赫电子有限公司 | M80: 0.0051 | N80: 0 | O80: =G80*M80 -> 0.2295 | T80: 70 | U80: 4000 | Z80: C1,3,5-8,13,16-18,21-24,26-31,33-35,37,43,45,47,48,65-70,78-80,88,109-111,122,123,160,188 | AA80: N30515000714 | AB80: 片式瓷介电容 TCC0603X7R104K500CT X7R,100nF,10%,50V,0603(三环)(编带)(RoHS) | AC80: 0.0057 | AD80: N30515000736 | AE80: 片式瓷介电容 0603B104K500CT X7R,100nF,10%,50V,0603(华新科技)(编带)(RoHS) | AF80: 0.0064 | AG80: N30515000279 | AH80: 片式瓷介电容 CC0603KRX7R9BB104 X7R,100nF,10%,50V,0603(国巨)(编带)(RoHS) | AI80: 0.0066
A81: 81 | B81: 硬件 | C81: N30599000010 | D81: 片式瓷介电容 NP0,100pF,5%,50V,0603(编带)(RoHS)(互换件) | E81: AB级替换 | F81: SMT | G81: 31 | H81: N30515001156 | I81: 片式瓷介电容 0603CG101J500NT NP0,100pF,5%,50V,0603(风华)(编带)(RoHS) | J81: 521 | K81: 10178 | L81: 厦门美赫电子有限公司 | M81: 0.005 | N81: 0 | O81: =G81*M81 -> 0.155 | T81: 56 | U81: 1 | V81: 1 | Z81: C14,56-61,72-77,82-87,91-93,100-102,115-120 | AA81: N30515001358 | AB81: 片式瓷介电容 TCC0603COG101J500CT NP0,100pF,5%,50V,0603(三环)(编带)(RoHS) | AC81: 0.0053 | AD81: 31012101J4N01 | AE81: 片式瓷介电容 CC0603JRNPO9BN101 NP0,100pF,5%,50V,0603(国巨)(编带)(RoHS) | AF81: 0.0055 | AG81: N30515002843 | AH81: 片式瓷介电容 C1608C0G1H101J080AA C0G,100pF,5%,50V,0603(TDK)(编带)(RoHS) | AI81: 0.0206
A82: 82 | B82: 硬件 | C82: N30599000011 | D82: 片式瓷介电容 X7R,1nF,10%,50V,0603(编带)(RoHS)(互换件) | E82: AB级替换 | F82: SMT | G82: 10 | H82: N30515001074 | I82: 片式瓷介电容 0603B102K500NT X7R,1nF,10%,50V,0603(风华)(编带)(RoHS) | J82: 陈虹 | K82: MHDZ2 | L82: 厦门美赫电子有限公司 | M82: 0.0048 | N82: 0 | O82: =G82*M82 -> 0.048 | T82: 70 | U82: 4000 | Z82: C15,32,38,42,44,55,94,95,142,155 | AA82: 31012102K4X01 | AB82: 片式瓷介电容 CC0603KRX7R9BB102 X7R,1nF,10%,50V,0603(国巨)(编带)(RoHS) | AC82: 0.005 | AD82: N30515000613 | AE82: 片式瓷介电容 0603B102K500CT X7R,1nF,10%,50V,0603(华新科技)(编带)(RoHS) | AF82: 0.0057 | AG82: N30515000782 | AH82: 片式瓷介电容 TCC0603X7R102K500CT X7R,1nF,10%,50V,0603(三环)(编带)(RoHS) | AI82: 0.0058
A83: 83 | B83: 硬件 | C83: N30599000014 | D83: 片式瓷介电容 X7R,10nF,10%,50V,0603(编带)(RoHS)(互换件) | E83: AB级替换 | F83: SMT | G83: 7 | H83: N30515001150 | I83: 片式瓷介电容 0603B103K500NT X7R,10nF,10%,50V,0603(风华)(编带)(RoHS) | J83: 陈虹 | K83: MHDZ2 | L83: 厦门美赫电子有限公司 | M83: 0.0048 | N83: 0 | O83: =G83*M83 -> 0.0336 | T83: 70 | U83: 4000 | Z83: C39-41,51-54 | AA83: 31011031-1 | AB83: 片式瓷介电容 CC0603KRX7R9BB103 X7R,10nF,10%,50V,0603(国巨)(编带)(RoHS) | AC83: 0.0049 | AD83: N30515000735 | AE83: 片式瓷介电容 0603B103K500CT X7R,10nF,10%,50V,0603(华新科技)(编带)(RoHS) | AF83: 0.0058 | AG83: N30515000713 | AH83: 片式瓷介电容 TCC0603X7R103K500CT X7R,10nF,10%,50V,0603(三环)(编带)(RoHS) | AI83: 0.0063
A84: 84 | B84: 硬件 | C84: N30599000017 | D84: 片式瓷介电容 X7R,100nF,10%,50V,1206(编带)(RoHS)(互换件) | E84: AB级替换 | F84: SMT | G84: 1 | H84: N30515001169 | I84: 片式瓷介电容 1206B104K500NT X7R,100nF,10%,50V,1206(风华)(编带)(RoHS) | J84: 陈虹 | K84: MHDZ2 | L84: 厦门美赫电子有限公司 | M84: 0.0217 | N84: 0 | O84: =G84*M84 -> 0.0217 | T84: 84 | U84: 4000 | Z84: C25 | AA84: N30515001366 | AB84: 片式瓷介电容 TCC1206X7R104K500DT X7R,100nF,10%,50V,1206(三环)(编带)(RoHS) | AC84: 0.0226 | AD84: N30515002509 | AE84: 片式瓷介电容 1206B104K500CT X7R,100nF,10%,50V,1206(华新科技)(编带)(RoHS) | AF84: 0.0274 | AG84: N30515002520 | AH84: 片式瓷介电容 CC1206KRX7R9BB104 X7R,100nF,10%,50V,1206(国巨)(编带)(RoHS) | AI84: 0.0275
A85: 85 | B85: 硬件 | C85: N30599000047 | D85: 片式瓷介电容 X7R,3.3nF,10%,50V,0603(编带)(RoHS)(互换件) | E85: AB级替换 | F85: SMT | G85: 2 | H85: N30515001415 | I85: 片式瓷介电容 0603B332K500NT X7R,3.3nF,10%,50V,0603(风华)(编带)(RoHS) | J85: 陈虹 | K85: MHDZ2 | L85: 厦门美赫电子有限公司 | M85: 0.0052 | N85: 0 | O85: =G85*M85 -> 0.0104 | T85: 77 | U85: 4000 | Z85: C46,49 | AA85: N30515002529 | AB85: 片式瓷介电容 CC0603KRX7R9BB332 X7R,3.3nF,10%,50V,0603(国巨)(编带)(RoHS) | AC85: 0.0055 | AD85: N30515001414 | AE85: 片式瓷介电容 TCC0603X7R332K500CT X7R,3.3nF,10%,50V,0603(三环)(编带)(RoHS) | AF85: 0.0069 | AG85: N30515002511 | AH85: 片式瓷介电容 0603B332K500CT X7R,3.3nF,10%,50V,0603(华新科技)(编带)(RoHS) | AI85: 0.0089
A86: 86 | B86: 硬件 | C86: N30599000063 | D86: 片式瓷介电容 X7R,220nF,10%,50V,0603(编带)(RoHS)(互换件) | E86: AB级替换 | F86: SMT | G86: 2 | H86: N30515001445 | I86: 片式瓷介电容 0603B224K500NT X7R,220nF,10%,50V,0603(风华)(编带)(RoHS) | J86: 陈虹 | K86: SJC2 | L86: 深圳市集财实业有限公司（ZZ） | M86: 0.0165 | N86: 0 | O86: =G86*M86 -> 0.033 | T86: 63 | U86: 4000 | Z86: C71,81 | AA86: N30515000358 | AB86: 片式瓷介电容 CC0603KRX7R9BB224 X7R,220nF,10%,50V,0603(国巨)(编带)(RoHS) | AC86: 0.0181 | AD86: N30515001444 | AE86: 片式瓷介电容 TCC0603X7R224K500CT X7R,220nF,10%,50V,0603(三环)(编带)(RoHS) | AF86: 0.0207 | AG86: N30515000948 | AH86: 片式瓷介电容 GRM188R71H224KAC4D X7R,220nF,10%,50V,0603(Murata)(编带)(RoHS) | AI86: 0.055
A87: 87 | B87: 硬件 | C87: N30599000084 | D87: 片式瓷介电容 X7R,470pF,10%,250V,1206(编带)(RoHS)(互换件) | E87: AB级替换 | F87: SMT | G87: 2 | H87: N30515001484 | I87: 片式瓷介电容 TCC1206X7R471K251DT X7R,470pF,10%,250V,1206(三环)(编带)(RoHS) | J87: 504 | K87: 10829 | L87: 厦门翔烨云供应链科技有限公司 | M87: 0.0313 | N87: 0 | O87: =G87*M87 -> 0.0626 | T87: 7 | U87: 1 | V87: 4000 | Z87: C2,19 | AA87: N30515001175 | AB87: 片式瓷介电容 1206B471K251NT X7R,470pF,10%,250V,1206(风华)(编带)(RoHS) | AC87: 0.0314 | AD87: N30515000572 | AE87: 片式瓷介电容 CC1206KRX7RYBB471 X7R,470pF,10%,250V,1206(国巨)(编带)(RoHS) | AF87: 0.047
A88: 88 | B88: 硬件 | C88: N30599000125 | D88: 片式瓷介电容 X7R,1uF,10%,50V,0603(编带)(RoHS)(互换件) | E88: AB级替换 | F88: SMT | G88: 8 | H88: N30515001987 | I88: 片式瓷介电容 CL10B105KB8NQNC X7R,1uF,10%,50V,0603(Samsung)(编带)(RoHS) | J88: 521 | K88: 10265 | L88: 北天星电子(深圳)有限公司 | M88: 0.0168 | N88: 0 | O88: =G88*M88 -> 0.1344 | T88: 90 | U88: 1 | V88: 4000 | Z88: C4,11,62-64,112-114 | AA88: N30515001569 | AB88: 片式瓷介电容 0603B105K500NT X7R,1uF,10%,50V,0603(风华)(编带)(RoHS) | AC88: 0.028 | AD88: N30515001106 | AE88: 片式瓷介电容 UMK107AB7105KA-T X7R,1uF,10%,50V,0603(Taiyo Yuden)(编带)(RoHS) | AF88: 0.031 | AG88: N30515001568 | AH88: 片式瓷介电容 TCC0603X7R105K500CT X7R,1uF,10%,50V,0603(三环)(编带)(RoHS) | AI88: 0.0598
A89: 89 | B89: 硬件 | C89: N30599000312 | D89: 片式瓷介电容 X7R,470pF,10%,50V,0603(编带)(RoHS)(互换件) | E89: AB级替换 | F89: SMT | G89: 1 | H89: N30515002089 | I89: 片式瓷介电容 CC0603KRX7R9BB471 X7R,470pF,10%,50V,0603(国巨)(编带)(RoHS) | J89: 陈虹 | K89: SZCLW2 | L89: 深圳市超利维实业有限公司 | M89: 0.0054 | N89: 0 | O89: =G89*M89 -> 0.0054 | T89: 56 | U89: 4000 | Z89: C12 | AA89: N30515002299 | AB89: 片式瓷介电容 0603B471K500NT X7R,470pF,10%,50V,0603(风华)(编带)(RoHS) | AC89: 0.0058 | AD89: N30515002326 | AE89: 片式瓷介电容 C1608X7R1H471KT000N X7R,470pF,10%,50V,0603(TDK)(编带)(RoHS) | AF89: 0.015
A90: 90 | B90: 硬件 | C90: N30599000342 | D90: 片式瓷介电容 X6S,10uF,10%,35V,0805(编带)(RoHS)(互换件) | E90: AB级替换 | F90: SMT | G90: 28 | H90: N30515002399 | I90: 片式瓷介电容 TCC0805X6S106K350FT X6S,10uF,10%,35V,0805(三环)(编带)(RoHS) | J90: 江华媛 | K90: 10667 | L90: 苏州巨宏达电工科技有限公司 | M90: 0.1689 | N90: 0 | O90: =G90*M90 -> 4.7292 | T90: 56 | U90: 3000 | V90: 3000 | Z90: C103,,C103AA,C104,,C104AA,C105,,C105AA,C106,,C106AA,C107,,C107AA,C108,,C108AA,C121,,C121A,C148,,C148A,C149,,C149A,C151,,C151AA,C152,,C152AA,C153,,C153AA,C154,,C154AA,C156,,C156A | AA90: N30515000642 | AB90: 片式瓷介电容 GRM21BC8YA106KE11L X6S,10uF,10%,35V,0805(Murata)(编带)(RoHS) | AC90: 0.27
A91: 91 | B91: 硬件 | C91: N31301000176 | D91: 光耦 PC817X3NIP SOP4(RankC)(Sharp)(编带)(RoHS) | E91: AB级替换 | F91: SMT | G91: 2 | H91: N31301000176 | I91: 光耦 PC817X3NIP SOP4(RankC)(Sharp)(编带)(RoHS) | J91: 504 | K91: 10829 | L91: 厦门翔烨云供应链科技有限公司 | M91: 0.4178 | N91: 0 | O91: =G91*M91 -> 0.8356 | T91: 7 | U91: 2000 | V91: 2001 | Z91: B1,2
A92: 92 | B92: 硬件 | C92: N31306000294 | D92: 发光二极管 LTST-C191KRKT-EL 红色,0603(亮度:M,N,波长:630nm,电压:ALL)(光宝)(编带)(RoHS) | E92: AB级替换 | F92: SMT | G92: 2 | H92: N31306000294 | I92: 发光二极管 LTST-C191KRKT-EL 红色,0603(亮度:M,N,波长:630nm,电压:ALL)(光宝)(编带)(RoHS) | J92: 王临泽 | K92: SZCLW2 | L92: 深圳市超利维实业有限公司 | M92: 0.0355 | N92: 0 | O92: =G92*M92 -> 0.071 | T92: 84 | U92: 25000 | Z92: V54,56
A93: 93 | B93: 硬件 | C93: N31306000469 | D93: 发光二极管 LTST-C191TBKT-5A 蓝色,0603(亮度:M1/M2,波长:ALL,电压:ALL)(光宝)(编带)(RoHS) | E93: AB级替换 | F93: SMT | G93: 4 | H93: N31306000469 | I93: 发光二极管 LTST-C191TBKT-5A 蓝色,0603(亮度:M1/M2,波长:ALL,电压:ALL)(光宝)(编带)(RoHS) | J93: 196656 | K93: 10848 | L93: PAN Elektron (Hong-Kong) Co., Limited | M93: 0.062883 | N93: 0 | O93: =G93*M93 -> 0.251532 | T93: 84 | U93: 0 | V93: 25000 | Z93: V20,22,39,59
A94: 94 | B94: 硬件 | C94: N31306000791 | D94: 发光二极管 RF-GNB191TS-CF 翠绿色,0603(亮度:430-1000mcd,波长:520-526nm,电压:2.7-3.3V)(瑞丰)(编带)(RoHS) | E94: AB级替换 | F94: SMT | G94: 2 | H94: N31306000791 | I94: 发光二极管 RF-GNB191TS-CF 翠绿色,0603(亮度:430-1000mcd,波长:520-526nm,电压:2.7-3.3V)(瑞丰)(编带)(RoHS) | J94: 王临泽 | K94: SZRFGD2 | L94: 深圳市瑞丰光电子股份有限公司（ZZ） | M94: 0.0417 | N94: 0 | O94: =G94*M94 -> 0.0834 | T94: 28 | U94: 4000 | Z94: V55,57
A95: 95 | B95: 硬件 | C95: N31501000361 | D95: 超快恢复二极管 US1D 1A,200V,SMA(强茂)(编带)(RoHS) | E95: AB级替换 | F95: SMT | G95: 9 | H95: N31501000361 | I95: 超快恢复二极管 US1D 1A,200V,SMA(强茂)(编带)(RoHS) | J95: 吴巧明 | K95: GZGY2 | L95: 广州市洲光源电子有限公司（ZZ） | M95: 0.094 | N95: 0 | O95: =G95*M95 -> 0.846 | T95: 84 | U95: 1800 | Z95: V3,6,12,13,18,23-26
A96: 96 | B96: 硬件 | C96: N31503000090 | D96: 整流桥 GBJ25M 25A,1KV(固锝)(RoHS) | E96: AB级替换 | F96: 插焊 | G96: 1 | H96: N31503000090 | I96: 整流桥 GBJ25M 25A,1KV(固锝)(RoHS) | J96: 赖淑琴 | K96: XMLD2 | L96: 厦门立锝电子有限公司 | M96: 1.8 | N96: 0 | O96: =G96*M96 -> 1.8 | T96: 56 | U96: 400 | Z96: V15
A97: 97 | B97: 硬件 | C97: N31504000059 | D97: 开关二极管 1N4148WX-TP 150mA,100V,SOD323(MCC)(编带)(RoHS) | E97: AB级替换 | F97: SMT | G97: 6 | H97: N31504000059 | I97: 开关二极管 1N4148WX-TP 150mA,100V,SOD323(MCC)(编带)(RoHS) | J97: 赖淑琴 | K97: XMKL2 | L97: 厦门科力通电子科技有公司（ZZ） | M97: 0.02 | N97: 0 | O97: =G97*M97 -> 0.12 | T97: 56 | U97: 3000 | Z97: V27,30,33,36-38
A98: 98 | B98: 硬件 | C98: N31504000155 | D98: 开关二极管 BAV99 200mA,70V,SOT23(晶导微)(编带)(RoHS) | E98: AB级替换 | F98: SMT | G98: 9 | H98: N31504000155 | I98: 开关二极管 BAV99 200mA,70V,SOT23(晶导微)(编带)(RoHS) | J98: 514 | K98: 10382 | L98: 厦门镁富莱工贸有限公司 | M98: 0.02 | N98: 0 | O98: =G98*M98 -> 0.18 | T98: 35 | U98: 1 | V98: 1 | Z98: V7,11,44-47,51-53
A99: 99 | B99: 硬件 | C99: N31507000185 | D99: TVS SMBJ20A-13 600W,20V,SMB(Diodes)(编带)(RoHS) | E99: AB级替换 | F99: SMT | G99: 3 | H99: N31507000578 | I99: TVS SMBJ20A 600W,20V,SMB(扬杰)(编带)(RoHS) | J99: 1100 | K99: 10084 | L99: 厦门格亚电子科技有限公司 | M99: 0.133 | N99: 0 | O99: =G99*M99 -> 0.399 | T99: 42 | U99: 3000 | V99: 3000 | Z99: V28,31,34 | AA99: N31507000185 | AB99: TVS SMBJ20A-13 600W,20V,SMB(Diodes)(编带)(RoHS) | AC99: 0.45
A100: 100 | B100: 硬件 | C100: N31507000282 | D100: TVS P6SMB200A 600W,171V,SMB(固锝)(编带)(RoHS) | E100: AB级替换 | F100: SMT | G100: 1 | H100: N31507000282 | I100: TVS P6SMB200A 600W,171V,SMB(固锝)(编带)(RoHS) | J100: 吴巧明 | K100: SWSC2 | L100: 深圳市威斯创电子有限公司（ZZ） | M100: 0.2 | N100: 0 | O100: =G100*M100 -> 0.2 | T100: 56 | U100: 3000 | Z100: V17 | AA100: N31507000241 | AB100: TVS P6SMB200A 600W,171V,SMB(强茂)(编带)(RoHS) | AC100: 0.28
...

Sheet Sheet3
A1: (Q251020183811524 / N10305002124 / DRV-26P-NJTJ(RoHS)中央式空调控制器驱动板组件(D5A13H000000))产品加工成本核算报表 | J1: (Q260105085808046 / N10305002124 / DRV-26P-NJTJ(RoHS)中央式空调控制器驱动板组件(D5A13H000000))产品加工成本核算报表
A3: 贴片、机插加工成本 | J3: 贴片、机插加工成本
A4: 工序 | B4: 点数 | C4: 单点成本 | D4: 金额 | J4: 工序 | K4: 点数 | L4: 单点成本 | M4: 金额
A5: 贴片 | B5: 1101.001 | C5: 0.0056 | D5: 6.1656 | J5: 贴片 | K5: 1101.001 | L5: 0.0056 | M5: 6.1656
A6: 机插 | B6: 14 | C6: 0.0171 | D6: =B6*C6 -> 0.2394 | J6: 机插 | K6: 14 | L6: 0.0171 | M6: =K6*L6 -> 0.2394
A7: 预烧写 | B7: 0 | C7: 0.0498 | D7: 0 | J7: 预烧写 | K7: 0 | L7: 0.0498 | M7: 0
A10: 人工成本 | J10: 人工成本
A11: 分段名称 | B11: 工序类别 | C11: 生产定额 | D11: 工序 | E11: 人数 | F11: 人工成本 | J11: 分段名称 | K11: 工序类别 | L11: 生产定额 | M11: 工序 | N11: 人数 | O11: 人工成本
A12: 装配段 | B12: 装配 | C12: 8 | E12: 10 | F12: / | J12: 装配段 | K12: 装配 | L12: 12 | N12: 10 | O12: /
A13: 装配段 | B13: FCT | C13: 8 | E13: 2 | F13: / | J13: 装配段 | K13: FCT | L13: 12 | N13: 2 | O13: /
A14: 装配段 | B14: 外观检验 | C14: 8 | E14: 2 | F14: / | J14: 装配段 | K14: 外观检验 | L14: 12 | N14: 2 | O14: /
A15: 装配段 | B15: OQC | C15: 8 | E15: 0.24 | F15: / | J15: 装配段 | K15: OQC | L15: 12 | N15: 0.24 | O15: /
A16: 装配段 | B16: 产前准备 | C16: 8 | E16: 0.6 | F16: / | J16: 装配段 | K16: 产前准备 | L16: 12 | N16: 0.6 | O16: /
A17: 装配段 | B17: 杂项设备 | C17: 8 | E17: 0.6 | F17: / | J17: 装配段 | K17: 杂项设备 | L17: 12 | N17: 0.6 | O17: /
A18: 装配段 | B18: 维修清尾 | C18: 8 | E18: 0.36 | F18: / | J18: 装配段 | K18: 维修清尾 | L18: 12 | N18: 0.36 | O18: /
A19: 装配段 | B19: 包装 | C19: 8 | E19: 2 | F19: / | J19: 装配段 | K19: 包装 | L19: 12 | N19: 2 | O19: /
A20: 插焊段 | B20: 插件 | C20: 80 | E20: 9 | F20: / | J20: 插焊段 | K20: 焊接 | L20: 80 | N20: 5 | O20: /
A21: 插焊段 | B21: 焊接 | C21: 80 | E21: 5 | F21: / | J21: 插焊段 | K21: 插件 | L21: 80 | N21: 9 | O21: /
A22: 插焊段 | B22: 维修清尾 | C22: 80 | E22: 0.5 | F22: / | J22: 插焊段 | K22: 维修清尾 | L22: 80 | N22: 0.5 | O22: /
A23: 插焊段 | B23: 喷漆 | C23: 80 | E23: 0.6 | F23: / | J23: 插焊段 | K23: 喷漆 | L23: 80 | N23: 0.6 | O23: /
... A63: 测试段 | B63: 外观检验 | C63: 200 | E63: 1 | F63: / | J63: 插焊段 | K63: 产前准备 | L63: 240 | N63: 0.6 | O63: /
A64: 测试段 | B64: FCT | C64: 200 | E64: 3 | F64: / | J64: 总人工成本（含辅助人员） | O64: 82.0882
A65: 总人工成本（含辅助人员） | F65: 111.0501
A68: 工装成本 | J68: 工装成本
A69: 工艺 | B69: 工装名称 | C69: 数量 | D69: 单价 | E69: 年需求 | F69: 工装成本 | G69: 金额 | J69: 工艺 | K69: 工装名称 | L69: 数量 | M69: 单价 | N69: 年需求 | O69: 工装成本 | P69: 金额
A70: 装配 | B70: 装配工装 | C70: 2 | D70: 2000 | E70: 5000 | F70: 0.2667 | G70: =C70*D70 -> 4000 | J70: 装配 | K70: 装配工装 | L70: 2 | M70: 2000 | N70: 5000 | O70: 0.2667 | P70: =L70*M70 -> 4000
A71: 自动测试 | B71: 测试工装 | C71: 2 | D71: 4000 | E71: 5000 | F71: 0.5333 | G71: =C71*D71 -> 8000 | J71: 自动测试 | K71: 测试工装 | L71: 2 | M71: 4000 | N71: 5000 | O71: 0.5333 | P71: =L71*M71 -> 8000
A72: 波峰焊 | B72: 波峰焊托盘 | C72: 15 | D72: 300 | E72: 5000 | F72: 0.3 | G72: =C72*D72 -> 4500 | J72: 波峰焊 | K72: 波峰焊托盘 | L72: 15 | M72: 300 | N72: 5000 | O72: 0.3 | P72: =L72*M72 -> 4500
A73: 双面喷漆 | B73: 喷漆托盘 | C73: 0 | D73: 0 | E73: 5000 | F73: 0 | G73: =C73*D73 -> 0 | J73: 双面喷漆 | K73: 喷漆托盘 | L73: 0 | M73: 0 | N73: 5000 | O73: 0 | P73: =L73*M73 -> 0
A74: 自动测试 | B74: 自动测试工装 | C74: 2 | D74: 4000 | E74: 5000 | F74: 0.5333 | G74: =C74*D74 -> 8000 | J74: 自动测试 | K74: 自动测试工装 | L74: 2 | M74: 4000 | N74: 5000 | O74: 0.5333 | P74: =L74*M74 -> 8000
A75: ICT | B75: ICT针床 | C75: 1 | D75: 0 | E75: 5000 | F75: 0 | G75: =C75*D75 -> 0 | J75: ICT | K75: ICT针床 | L75: 1 | M75: 0 | N75: 5000 | O75: 0 | P75: =L75*M75 -> 0
A76: 装配 | B76: 装配工装 | C76: 3 | D76: 0 | E76: 5000 | F76: 0 | G76: =C76*D76 -> 0 | J76: 装配 | K76: 装配工装 | L76: 3 | M76: 0 | N76: 5000 | O76: 0 | P76: =L76*M76 -> 0
A77: 自动焊锡机 | B77: 自动焊接 | C77: 3 | D77: 400 | E77: 5000 | F77: 0.08 | G77: =C77*D77 -> 1200 | J77: 自动焊锡机 | K77: 自动焊接 | L77: 3 | M77: 400 | N77: 5000 | O77: 0.08 | P77: =L77*M77 -> 1200
A78: 双面喷漆 | B78: 喷漆托盘 | C78: 15 | D78: 0 | E78: 5000 | F78: 0 | G78: =C78*D78 -> 0 | J78: 双面喷漆 | K78: 喷漆托盘 | L78: 15 | M78: 0 | N78: 5000 | O78: 0 | P78: =L78*M78 -> 0
A79: ICT | B79: ICT针床 | C79: 1 | D79: 0 | E79: 5000 | F79: 0 | G79: =C79*D79 -> 0 | J79: ICT | K79: ICT针床 | L79: 1 | M79: 0 | N79: 5000 | O79: 0 | P79: =L79*M79 -> 0
A80: 自动测试 | B80: 自动测试 | C80: 3 | D80: 0 | E80: 5000 | F80: 0 | G80: =C80*D80 -> 0 | J80: 自动测试 | K80: 自动测试 | L80: 3 | M80: 0 | N80: 5000 | O80: 0 | P80: =L80*M80 -> 0
A81: 波峰焊 | B81: 波峰焊托盘 | C81: 0 | D81: 0 | E81: 0 | F81: 0 | G81: =C81*D81 -> 0 | J81: 波峰焊 | K81: 波峰焊托盘 | L81: 0 | M81: 0 | N81: 0 | O81: 0 | P81: =L81*M81 -> 0
... A85: ICT | B85: ICT针床 | C85: 1 | D85: 3500 | E85: 5000 | F85: 0.2333 | G85: =C85*D85 -> 3500 | J85: ICT | K85: ICT针床 | L85: 1 | M85: 3500 | N85: 5000 | O85: 0.2333 | P85: =L85*M85 -> 3500
A86: 合计 | F86: 直接向客户收取 | G86: =SUM(G70:G85) -> 48700 | J86: 合计 | O86: 直接向客户收取 | P86: =SUM(P70:P85) -> 48700
A88: 加工成本汇总 | J88: 加工成本汇总
A89: 工序类别 | B89: 成本组成 | D89: 金额 | J89: 工序类别 | K89: 成本组成 | M89: 金额
A90: 贴片、机插 | B90: 1 | C90: 贴片加工成本 | D90: 6.1656 | J90: 贴片、机插 | K90: 1 | L90: 贴片加工成本 | M90: 6.1656
B91: 2 | C91: 机插加工成本 | D91: 0.2394 | K91: 2 | L91: 机插加工成本 | M91: 0.2394
C92: 预烧写加工成本 | D92: 0 | L92: 预烧写加工成本 | M92: 0
A93: 插焊、测试及其他工序 | B93: 3 | C93: 人工成本 | D93: 111.0501 | J93: 插焊、测试及其他工序 | K93: 3 | L93: 人工成本 | M93: 82.0882
B94: 4 | C94: 折旧（专用） | D94: 0.8424 | K94: 4 | L94: 折旧（专用） | M94: 0.8424
B95: 5 | C95: 折旧（公共） | D95: 2.9761 | K95: 5 | L95: 折旧（公共） | M95: 2.2
B96: 6 | C96: 水电（专用） | D96: 1.4745 | K96: 6 | L96: 水电（专用） | M96: 1.4745
B97: 7 | C97: 水电（公共） | D97: 1.9989 | K97: 7 | L97: 水电（公共） | M97: 1.4776
B98: 8 | C98: 工装 | D98: 0 | K98: 8 | L98: 工装 | M98: 0
B99: 9 | C99: 低耗 | D99: 6.1522 | K99: 9 | L99: 低耗 | M99: 4.5477
B100: 10 | C100: 管理人员工资 | D100: 31.9713 | K100: 10 | L100: 管理人员工资 | M100: 21.3676
B101: 11 | C101: 其他 | D101: 8.1511 | K101: 11 | L101: 其他 | M101: 6.0253
B102: 12 | C102: 检验成本 | D102: 0 | K102: 12 | L102: 检验成本 | M102: 0
A103: 合计 | D103: =SUM(D90:D102) -> 171.0216 | J103: 合计 | M103: =SUM(M90:M102) -> 126.4283
A106: 模具开发费用 | J106: 模具开发费用
A107: 物料代码 | B107: 物料名称 | C107: 用量 | D107: 单价 | E107: 金额 | J107: 物料代码 | K107: 物料名称 | L107: 用量 | M107: 单价 | N107: 金额
E108: =C108*D108 -> 0 | J108: N40511000095 | K108: 泡沫 660×399×115 (EPS料,右侧，DRV-20P,26P包装用)(RoHS) | L108: 1 | M108: =16667/1.13 -> 14749.558 | N108: =L108*M108 -> 14749.558
E109: =C109*D109 -> 0 | J109: N40511000096 | K109: 泡沫 660×399×146 (EPS料,左侧，DRV-20P,26P包装用)(RoHS) | L109: 1 | M109: =16667/1.13 -> 14749.558 | N109: =L109*M109 -> 14749.558
E110: =C110*D110 -> 0 | N110: =L110*M110 -> 0
D111: 合计 | E111: =SUM(E108:E110) -> 0 | M111: 合计 | N111: =SUM(N108:N110) -> 29499.115
A113: 软件开发费用 | J113: 软件开发费用
A114: 序号 | B114: 项目 | C114: 工作量（人天) | D114: 单价(元/人天) | E114: 金额 | J114: 序号 | K114: 项目 | L114: 工作量（人天) | M114: 单价(元/人天) | N114: 金额
E115: =C115*D115 -> 0 | N115: =L115*M115 -> 0
E116: =C116*D116 -> 0 | N116: =L116*M116 -> 0
E117: =C117*D117 -> 0 | N117: =L117*M117 -> 0
D118: 合计 | E118: =SUM(E115:E117) -> 0 | M118: 合计 | N118: =SUM(N115:N117) -> 0
A120: 硬件开发费用 | J120: 硬件开发费用
A121: 序号 | B121: 项目 | C121: 工作量（人天) | D121: 单价(元/人天) | E121: 金额 | J121: 序号 | K121: 项目 | L121: 工作量（人天) | M121: 单价(元/人天) | N121: 金额
E122: =C122*D122 -> 0 | N122: =L122*M122 -> 0
E123: =C123*D123 -> 0 | N123: =L123*M123 -> 0
E124: =C124*D124 -> 0 | N124: =L124*M124 -> 0
D125: 合计 | E125: =SUM(E122:E124) -> 0 | M125: 合计 | N125: =SUM(N122:N124) -> 0
A127: 实验费用 | J127: 实验费用
A128: 序号 | B128: 项目 | C128: 时间（小时) | D128: 单价 | E128: 金额 | J128: 序号 | K128: 项目 | L128: 时间（小时) | M128: 单价 | N128: 金额
E129: =C129*D129 -> 0 | N129: =L129*M129 -> 0
E130: =C130*D130 -> 0 | N130: =L130*M130 -> 0
E131: =C131*D131 -> 0 | N131: =L131*M131 -> 0
D132: 合计 | E132: =SUM(E129:E131) -> 0 | M132: 合计 | N132: =SUM(N129:N131) -> 0

Sheet Sheet4
A1: 项目名称 | C1: 汽车与工控控制器-DRV-20P-NJTJ(RoHS)中央式空调控制器驱动板组件(D5A13G000000)--二次重新报价！！ | E1: 客户名称 | F1: 青岛国创智能家电研究院有限公司 | K1: 报价项目类型 | L1: 已立项产品报价 | Q1: 王前良 | U1: 销售公司/国内销售部/汽控国内部
A2: 产品编码 | C2: N10305002124 | E2: 产品名称 | F2: DRV-26P-NJTJ(RoHS)中央式空调控制器驱动板组件(D5A13H000000) | K2: 硬件设计师 | L2: 李沁峰 | Q2: 陈可璜 | U2: 45950
A3: 硬件 | E3: 结构件 | K3: 包装材料 | R3: 0 | V3: 0
A4: 序号 | B4: 物料类型 | C4: 物料编码 | D4: 物料名称 | E4: 物料级别 | F4: 装配形式 | G4: 单机用量 | H4: 最低价物料编码 | I4: 最低价物料名称 | J4: 采购员 | K4: 供应商代码 | L4: 供应商名称 | M4: 未税单价 | N4: 最新未税单价 | O4: 涨价合计金额 | P4: 损耗率 | Q4: 金额 | R4: 提前期 | S4: 最小订货量 | T4: 最小包装量 | U4: 模具费（含税13%） | V4: 价格说明 | W4: 备注 | X4: 位号 | Y4: 替代料编码1 | Z4: 替代料名称1 | AA4: 未税单价1 | AB4: 替代料编码2 | AC4: 替代料名称2 | AD4: 未税单价2 | AE4: 替代料编码3 | AF4: 替代料名称3 | AG4: 未税单价3
A5: 16 | B5: 硬件 | C5: 301H030491 | D5: 片式电阻 RC0805FR-07300KL/0805W8F3003T5E 1/8W,300KΩ,1%,0805(国巨/厚声)(编带)(RoHS) | E5: AB级替换 | F5: SMT | G5: 18 | H5: N30101005840 | I5: 片式电阻 RC0805FR-07300KL 1/8W,300KΩ,1%,0805(国巨)(编带)(RoHS) | J5: 196386 | K5: 10266 | L5: 深圳市超利维实业有限公司 | M5: 0.0045 | P5: 0 | Q5: =G5*M5 -> 0.081 | R5: 56 | S5: 5000 | T5: 5000 | X5: R163-168,178,179,182-191 | Y5: N30101007034 | Z5: 片式电阻 0805W8F3003T5E 1/8W,300KΩ,1%,0805(厚声)(编带)(RoHS) | AA5: 0.0049 | AB5: 301H030491 | AC5: 片式电阻 RC0805FR-07300KL/0805W8F3003T5E 1/8W,300KΩ,1%,0805(国巨/厚声)(编带)(RoHS) | AD5: 报价中
A6: 17 | B6: 硬件 | C6: 306110396 | D6: 高压陶瓷电容 HGK3AF103ZG3AW 10nF,1KV,P=7.5(万明)(编带)(RoHS) | E6: AB级替换 | F6: 插焊 | G6: 1 | H6: 306110396 | I6: 高压陶瓷电容 HGK3AF103ZG3AW 10nF,1KV,P=7.5(万明)(编带)(RoHS) | J6: 196386 | K6: 10423 | L6: 厦门万明电子有限公司 | M6: 0.1331 | P6: 0 | Q6: =G6*M6 -> 0.1331 | R6: 50 | S6: 20000 | T6: 2000 | W6: 生产后按万明回复交期出货，不接受按贵司需求数量出货 | X6: C50A
A7: 18 | B7: 硬件 | C7: 3155US1M | D7: 超快恢复二极管 US1M 1A,1KV,SMA(强茂)(编带)(RoHS) | E7: AB级替换 | F7: SMT | G7: 1 | H7: N31511000061 | I7: 超快恢复二极管 US1M 1A,1KV,SMA(晶导微)(编带)(RoHS) | J7: 514 | K7: 10382 | L7: 厦门镁富莱工贸有限公司 | M7: 0.0274 | P7: 0 | Q7: =G7*M7 -> 0.0274 | R7: 35 | S7: 1 | T7: 1 | X7: V16 | Y7: 3155US1M | Z7: 超快恢复二极管 US1M 1A,1KV,SMA(强茂)(编带)(RoHS) | AA7: 0.084
A8: 19 | B8: 硬件 | C8: 604B03VHZ51R | D8: 端子 B3P-VH (JST)(RoHS) | E8: AB级替换 | F8: 插焊 | G8: 1 | H8: 604B03VHZ51R | I8: 端子 B3P-VH (JST)(RoHS) | J8: 王临泽 | K8: HYDZ2 | L8: 深圳市恒有电子有限公司 | M8: 0.222 | P8: 0 | Q8: =G8*M8 -> 0.222 | R8: 150 | S8: 1000 | X8: X5
A9: 20 | B9: 硬件 | C9: 604B05VHZ51R | D9: 端子 B5P-VH (JST)(RoHS) | E9: AB级替换 | F9: 插焊 | G9: 2 | H9: 604B05VHZ51R | I9: 端子 B5P-VH (JST)(RoHS) | J9: 王临泽 | K9: HYDZ2 | L9: 深圳市恒有电子有限公司 | M9: 0.322 | P9: 0 | Q9: =G9*M9 -> 0.644 | R9: 112 | S9: 1000 | X9: X12,16
A10: 21 | B10: 硬件 | C10: N30101000615 | D10: 片式电阻 RC1206JR-0775RL/1206W4J0750T5E 1/4W,75Ω,5%,1206(国巨/厚声)(编带)(RoHS) | E10: AB级替换 | F10: SMT | G10: 1 | H10: N30101006583 | I10: 片式电阻 1206W4J0750T5E 1/4W,75Ω,5%,1206(厚声)(编带)(RoHS) | J10: 罗城 | K10: 10648 | L10: 厚声国际贸易（昆山）有限公司 | M10: 0.0045 | N10: 0.0057 | O10: =(N10-M10)*G10 -> 0.0012 | P10: 0 | Q10: =G10*M10 -> 0.0045 | R10: 56 | S10: 0 | T10: 5000 | X10: R118 | Y10: N30101005467 | Z10: 片式电阻 RC1206JR-0775RL 1/4W,75Ω,5%,1206(国巨)(编带)(RoHS) | AA10: 0.0077 | AB10: N30101000615 | AC10: 片式电阻 RC1206JR-0775RL/1206W4J0750T5E 1/4W,75Ω,5%,1206(国巨/厚声)(编带)(RoHS) | AD10: 报价中
A11: 22 | B11: 硬件 | C11: N30101000894 | D11: 片式电阻 RC1206FR-0722RL/1206W4F220JT5E 1/4W,22Ω,1%,1206(国巨/厚声)(编带)(RoHS) | E11: AB级替换 | F11: SMT | G11: 2 | H11: N30101006783 | I11: 片式电阻 1206W4F220JT5E 1/4W,22Ω,1%,1206(厚声)(编带)(RoHS) | J11: 罗城 | K11: 10648 | L11: 厚声国际贸易（昆山）有限公司 | M11: 0.0058 | N11: 0.0075 | O11: =(N11-M11)*G11 -> 0.0034 | P11: 0 | Q11: =G11*M11 -> 0.0116 | R11: 56 | S11: 0 | T11: 5000 | X11: R10,30 | Y11: N30101005525 | Z11: 片式电阻 RC1206FR-0722RL 1/4W,22Ω,1%,1206(国巨)(编带)(RoHS) | AA11: 0.0086 | AB11: N30101000894 | AC11: 片式电阻 RC1206FR-0722RL/1206W4F220JT5E 1/4W,22Ω,1%,1206(国巨/厚声)(编带)(RoHS) | AD11: 报价中
A12: 23 | B12: 硬件 | C12: N30101001049 | D12: 片式电阻 RC1206FR-076R8L/1206W4F680KT5E 1/4W,6.8Ω,1%,1206(国巨/厚声)(编带)(RoHS) | E12: AB级替换 | F12: SMT | G12: 2 | H12: N30101006696 | I12: 片式电阻 1206W4F680KT5E 1/4W,6.8Ω,1%,1206(厚声)(编带)(RoHS) | J12: 罗城 | K12: 10648 | L12: 厚声国际贸易（昆山）有限公司 | M12: 0.0083 | N12: 0.0112 | O12: =(N12-M12)*G12 -> 0.0058 | P12: 0 | Q12: =G12*M12 -> 0.0166 | R12: 56 | S12: 0 | T12: 5000 | X12: R47,65 | Y12: N30101005600 | Z12: 片式电阻 RC1206FR-076R8L 1/4W,6.8Ω,1%,1206(国巨)(编带)(RoHS) | AA12: 0.0279 | AB12: N30101001049 | AC12: 片式电阻 RC1206FR-076R8L/1206W4F680KT5E 1/4W,6.8Ω,1%,1206(国巨/厚声)(编带)(RoHS) | AD12: 报价中
A13: 24 | B13: 硬件 | C13: N30101005306 | D13: 片式电阻 GMR320HJCFAR100 7W,100mΩ,1%,2817(Rohm)(编带)(RoHS) | E13: AB级替换 | F13: SMT | G13: 2 | H13: N30101005306 | I13: 片式电阻 GMR320HJCFAR100 7W,100mΩ,1%,2817(Rohm)(编带)(RoHS) | J13: 521 | K13: 10265 | L13: 北天星电子(深圳)有限公司 | M13: 2.38 | P13: 0 | Q13: =G13*M13 -> 4.76 | R13: 120 | S13: 1 | T13: 1 | X13: R92,241
A14: 25 | B14: 硬件 | C14: N30101005309 | D14: 片式电阻 1210W2F3003T5E 1/2W,300KΩ,1%,1210(厚声)(编带)(RoHS) | E14: AB级替换 | F14: SMT | G14: 8 | H14: N30101005309 | I14: 片式电阻 1210W2F3003T5E 1/2W,300KΩ,1%,1210(厚声)(编带)(RoHS) | J14: 罗城 | K14: 10648 | L14: 厚声国际贸易（昆山）有限公司 | M14: 0.023 | P14: 0 | Q14: =G14*M14 -> 0.184 | R14: 91 | S14: 0 | T14: 20000 | X14: R192-199
A15: 26 | B15: 硬件 | C15: N30103000520 | D15: 金属膜电阻 MF02SJJ0364A10 2WS,360KΩ,5%(厚声)(HF;RoHS) | E15: AB级替换 | F15: 插焊 | G15: 3 | H15: N30103000520 | I15: 金属膜电阻 MF02SJJ0364A10 2WS,360KΩ,5%(厚声)(HF;RoHS) | J15: 罗城 | K15: 10648 | L15: 厚声国际贸易（昆山）有限公司 | M15: 0.065 | P15: 0 | Q15: =G15*M15 -> 0.195 | R15: 91 | S15: 0 | T15: 20000 | X15: R295,296,365
A16: 27 | B16: 硬件 | C16: N30103000526 | D16: 金属膜电阻 MF01WFF3003A10 1W,300KΩ,1%(厚声)(编带)(HF;RoHS) | E16: AB级替换 | F16: 插焊 | G16: 1 | H16: N30103000526 | I16: 金属膜电阻 MF01WFF3003A10 1W,300KΩ,1%(厚声)(编带)(RoHS) | J16: 陈虹 | K16: HSMY2 | L16: 厚声国际贸易（昆山）有限公司 | M16: 0.0828 | P16: 0 | Q16: =G16*M16 -> 0.0828 | R16: 42 | S16: 1000 | T16: 1000 | X16: R11
A17: 28 | B17: 硬件 | C17: N30103000527 | D17: 金属膜电阻 MF02WJJ0753A10 2W,75KΩ,5%(厚声)(编带)(HF;RoHS) | E17: AB级替换 | F17: 插焊 | G17: 1 | H17: N30103000527 | I17: 金属膜电阻 MF02WJJ0753A10 2W,75KΩ,5%(厚声)(编带)(HF;RoHS) | J17: 罗城 | K17: 10648 | L17: 厚声国际贸易（昆山）有限公司 | M17: 0.092 | P17: 0 | Q17: =G17*M17 -> 0.092 | R17: 91 | S17: 0 | T17: 20000 | X17: R34
A18: 29 | B18: 硬件 | C18: N30111000138 | D18: 合金电阻 DSLR-K-7-3F 7W,3mΩ,1%,5930(业展)(编带)(REACH;RoHS) | E18: AB级替换 | F18: SMT | G18: 3 | H18: N30111000138 | I18: 合金电阻 DSLR-K-7-3F 7W,3mΩ,1%,5930(业展)(编带)(REACH;RoHS) | J18: 521 | K18: 10265 | L18: 北天星电子(深圳)有限公司 | M18: 0.9 | P18: 0 | Q18: =G18*M18 -> 2.7 | R18: 120 | S18: 1 | T18: 1 | X18: R87,89,90
A19: 30 | B19: 硬件 | C19: N30111000139 | D19: 合金电阻 LR123WF200LT4E 3W,200mΩ,1%,2512(厚声)(编带)(RoHS) | E19: AB级替换 | F19: SMT | G19: 8 | H19: N30111000139 | I19: 合金电阻 LR123WF200LT4E 3W,200mΩ,1%,2512(厚声)(编带)(RoHS) | J19: 521 | K19: 10648 | L19: 厚声国际贸易（昆山）有限公司 | M19: 0.22 | P19: 0 | Q19: =G19*M19 -> 1.76 | R19: 1 | S19: 1 | T19: 4000 | X19: R233-236,293,294,297,298
A20: 31 | B20: 硬件 | C20: N30199000015 | D20: 片式电阻 1/4W,0Ω,5%,1206(编带)(RoHS)(互换件) | E20: AB级替换 | F20: SMT | G20: 1 | H20: N30101002864 | I20: 片式电阻 RS-06000JT 1/4W,0Ω,5%,1206(风华)(编带)(RoHS) | J20: 陈虹 | K20: MHDZ2 | L20: 厦门美赫电子有限公司 | M20: 0.0042 | N20: 0.0057 | O20: =(N20-M20)*G20 -> 0.0015 | P20: 0 | Q20: =G20*M20 -> 0.0042 | R20: 56 | S20: 5000 | X20: R144 | Y20: N30101006682 | Z20: 片式电阻 1206W4J0000T5E 1/4W,0Ω,5%,1206(厚声)(编带)(RoHS) | AA20: 0.0042 | AB20: N30101005366 | AC20: 片式电阻 RC1206JR-070RL 1/4W,0Ω,5%,1206(国巨)(编带)(RoHS) | AD20: 0.0075 | AE20: N30101002359 | AF20: 片式电阻 CR1206J40000G 1/4W,0Ω,5%,1206(丽智)(编带)(RoHS) | AG20: 报价中
A21: 32 | B21: 硬件 | C21: N30199000022 | D21: 片式电阻 1/10W,10KΩ,1%,0603(编带)(RoHS)(互换件) | E21: AB级替换 | F21: SMT | G21: 49 | H21: N30101002483 | I21: 片式电阻 0603WAF1002T5E 1/10W,10KΩ,1%,0603(厚声)(编带)(RoHS) | J21: 陈虹 | K21: HSMY2 | L21: 厚声国际贸易（昆山）有限公司 | M21: 0.0018 | N21: 0.0024 | O21: =(N21-M21)*G21 -> 0.0294 | P21: 0 | Q21: =G21*M21 -> 0.0882 | R21: 56 | S21: 5000 | X21: R4,5,7,14,16,20,21,23,26,27,31,38,39,42,52,62,63,73,75,77,80,82,83,98-100,112-114,116,141-143,145,200-202,218-223,225-227,231,232,260 | Y21: N30101002583 | Z21: 片式电阻 RS-03K1002FT 1/10W,10KΩ,1%,0603(风华)(编带)(RoHS) | AA21: 0.0018 | AB21: 301H0103H1 | AC21: 片式电阻 RC0603FR-0710KL 1/10W,10KΩ,1%,0603(国巨)(编带)(RoHS) | AD21: 0.0025 | AE21: N30101002366 | AF21: 片式电阻 CR0603FA1002G 1/10W,10KΩ,1%,0603(丽智)(编带)(RoHS) | AG21: 报价中
A22: 33 | B22: 硬件 | C22: N30199000047 | D22: 片式电阻 1/10W,1KΩ,1%,0603(编带)(RoHS)(互换件) | E22: AB级替换 | F22: SMT | G22: 25 | H22: N30101002910 | I22: 片式电阻 RS-03K1001FT 1/10W,1KΩ,1%,0603(风华)(编带)(RoHS) | J22: 陈虹 | K22: MHDZ2 | L22: 厦门美赫电子有限公司 | M22: 0.0018 | N22: 0.0024 | O22: =(N22-M22)*G22 -> 0.015 | P22: 0 | Q22: =G22*M22 -> 0.045 | R22: 56 | S22: 5000 | X22: R6,12,41,43-45,58,60,64,67-71,76,93-97,224,261,270,299,456 | Y22: N30101007519 | Z22: 片式电阻 0603WAF1001T5E 1/10W,1KΩ,1%,0603(厚声)(编带)(RoHS) | AA22: 0.0018 | AB22: N30101006259 | AC22: 片式电阻 RC0603FR-071KL 1/10W,1KΩ,1%,0603(国巨)(编带)(RoHS) | AD22: 0.0025 | AE22: N30101002909 | AF22: 片式电阻 CR0603FA1001G 1/10W,1KΩ,1%,0603(丽智)(编带)(RoHS) | AG22: 报价中
A23: 34 | B23: 硬件 | C23: N30199000075 | D23: 片式电阻 1/10W,4.7KΩ,1%,0603(编带)(RoHS)(互换件) | E23: AB级替换 | F23: SMT | G23: 9 | H23: N30101002965 | I23: 片式电阻 RS-03K4701FT 1/10W,4.7KΩ,1%,0603(风华)(编带)(RoHS) | J23: 陈虹 | K23: MHDZ2 | L23: 厦门美赫电子有限公司 | M23: 0.0018 | N23: 0.0024 | O23: =(N23-M23)*G23 -> 0.0054 | P23: 0 | Q23: =G23*M23 -> 0.0162 | R23: 56 | S23: 5000 | X23: R2,8,46,49-51,103-105 | Y23: N30101007321 | Z23: 片式电阻 0603WAF4701T5E 1/10W,4.7KΩ,1%,0603(厚声)(编带)(RoHS) | AA23: 0.0018 | AB23: N30101006127 | AC23: 片式电阻 RC0603FR-074K7L 1/10W,4.7KΩ,1%,0603(国巨)(编带)(RoHS) | AD23: 0.0026 | AE23: N30101002964 | AF23: 片式电阻 CR0603FA4701G 1/10W,4.7KΩ,1%,0603(丽智)(编带)(RoHS) | AG23: 报价中
A24: 35 | B24: 硬件 | C24: N30199000085 | D24: 片式电阻 1/10W,20KΩ,1%,0603(编带)(RoHS)(互换件) | E24: AB级替换 | F24: SMT | G24: 2 | H24: N30101002985 | I24: 片式电阻 RS-03K2002FT 1/10W,20KΩ,1%,0603(风华)(编带)(RoHS) | J24: 陈虹 | K24: MHDZ2 | L24: 厦门美赫电子有限公司 | M24: 0.0018 | N24: 0.0024 | O24: =(N24-M24)*G24 -> 0.0012 | P24: 0 | Q24: =G24*M24 -> 0.0036 | R24: 56 | S24: 5000 | X24: R74,81 | Y24: N30101007433 | Z24: 片式电阻 0603WAF2002T5E 1/10W,20KΩ,1%,0603(厚声)(编带)(RoHS) | AA24: 0.0018 | AB24: N30101006246 | AC24: 片式电阻 RC0603FR-0720KL 1/10W,20KΩ,1%,0603(国巨)(编带)(RoHS) | AD24: 0.0026 | AE24: N30101002984 | AF24: 片式电阻 CR0603FA2002G 1/10W,20KΩ,1%,0603(丽智)(编带)(RoHS) | AG24: 报价中
A25: 36 | B25: 硬件 | C25: N30199000101 | D25: 片式电阻 1/10W,2.2KΩ,1%,0603(编带)(RoHS)(互换件) | E25: AB级替换 | F25: SMT | G25: 7 | H25: N30101003017 | I25: 片式电阻 RS-03K2201FT 1/10W,2.2KΩ,1%,0603(风华)(编带)(RoHS) | J25: 陈虹 | K25: MHDZ2 | L25: 厦门美赫电子有限公司 | M25: 0.0018 | N25: 0.0024 | O25: =(N25-M25)*G25 -> 0.0042 | P25: 0 | Q25: =G25*M25 -> 0.0126 | R25: 56 | S25: 5000 | X25: R17,22,28,29,35,40,117 | Y25: N30101007423 | Z25: 片式电阻 0603WAF2201T5E 1/10W,2.2KΩ,1%,0603(厚声)(编带)(RoHS) | AA25: 0.0018 | AB25: N30101006208 | AC25: 片式电阻 RC0603FR-072K2L 1/10W,2.2KΩ,1%,0603(国巨)(编带)(RoHS) | AD25: 0.0025 | AE25: N30101003016 | AF25: 片式电阻 CR0603FA2201G 1/10W,2.2KΩ,1%,0603(丽智)(编带)(RoHS) | AG25: 报价中
A26: 37 | B26: 硬件 | C26: N30199000108 | D26: 片式电阻 1/10W,22KΩ,1%,0603(编带)(RoHS)(互换件) | E26: AB级替换 | F26: SMT | G26: 2 | H26: N30101003031 | I26: 片式电阻 RS-03K2202FT 1/10W,22KΩ,1%,0603(风华)(编带)(RoHS) | J26: 虞思旻 | K26: MHDZ2 | L26: 厦门美赫电子有限公司 | M26: 0.0018 | N26: 0.0024 | O26: =(N26-M26)*G26 -> 0.0012 | P26: 0 | Q26: =G26*M26 -> 0.0036 | R26: 56 | S26: 5000 | X26: R56,61 | Y26: N30101007422 | Z26: 片式电阻 0603WAF2202T5E 1/10W,22KΩ,1%,0603(厚声)(编带)(RoHS) | AA26: 0.0018 | AB26: N30101006238 | AC26: 片式电阻 RC0603FR-0722KL 1/10W,22KΩ,1%,0603(国巨)(编带)(RoHS) | AD26: 0.0026 | AE26: N30101003030 | AF26: 片式电阻 CR0603FA2202G 1/10W,22KΩ,1%,0603(丽智)(编带)(RoHS) | AG26: 报价中
A27: 38 | B27: 硬件 | C27: N30199000111 | D27: 片式电阻 1/10W,15KΩ,1%,0603(编带)(RoHS)(互换件) | E27: AB级替换 | F27: SMT | G27: 8 | H27: N30101003071 | I27: 片式电阻 RS-03K1502FT 1/10W,15KΩ,1%,0603(风华)(编带)(RoHS) | J27: 陈虹 | K27: MHDZ2 | L27: 厦门美赫电子有限公司 | M27: 0.0018 | N27: 0.0024 | O27: =(N27-M27)*G27 -> 0.0048 | P27: 0 | Q27: =G27*M27 -> 0.0144 | R27: 56 | S27: 5000 | X27: R148,149,174,175,248,249,274,275 | Y27: N30101007468 | Z27: 片式电阻 0603WAF1502T5E 1/10W,15KΩ,1%,0603(厚声)(编带)(RoHS) | AA27: 0.0018 | AB27: N30101006296 | AC27: 片式电阻 RC0603FR-0715KL 1/10W,15KΩ,1%,0603(国巨)(编带)(RoHS) | AD27: 0.0026 | AE27: N30101003070 | AF27: 片式电阻 CR0603FA1502G 1/10W,15KΩ,1%,0603(丽智)(编带)(RoHS) | AG27: 报价中
A28: 39 | B28: 硬件 | C28: N30199000117 | D28: 片式电阻 1/4W,100Ω,5%,1206(编带)(RoHS)(互换件) | E28: AB级替换 | F28: SMT | G28: 2 | H28: N30101003083 | I28: 片式电阻 RS-06K101JT 1/4W,100Ω,5%,1206(风华)(编带)(RoHS) | J28: 陈虹 | K28: MHDZ2 | L28: 厦门美赫电子有限公司 | M28: 0.0042 | N28: 0.0057 | O28: =(N28-M28)*G28 -> 0.003 | P28: 0 | Q28: =G28*M28 -> 0.0084 | R28: 56 | S28: 5000 | X28: R228,230 | Y28: N30101006680 | Z28: 片式电阻 1206W4J0101T5E 1/4W,100Ω,5%,1206(厚声)(编带)(RoHS) | AA28: 0.0042 | AB28: N30101005376 | AC28: 片式电阻 RC1206JR-07100RL 1/4W,100Ω,5%,1206(国巨)(编带)(RoHS) | AD28: 0.0075 | AE28: N30101003082 | AF28: 片式电阻 CR1206J40101G 1/4W,100Ω,5%,1206(丽智)(编带)(RoHS) | AG28: 报价中
A29: 40 | B29: 硬件 | C29: N30199000127 | D29: 片式电阻 1/10W,5.6KΩ,1%,0603(编带)(RoHS)(互换件) | E29: AB级替换 | F29: SMT | G29: 1 | H29: N30101003103 | I29: 片式电阻 RS-03K5601FT 1/10W,5.6KΩ,1%,0603(风华)(编带)(RoHS) | J29: 陈虹 | K29: MHDZ2 | L29: 厦门美赫电子有限公司 | M29: 0.0018 | N29: 0.0024 | O29: =(N29-M29)*G29 -> 0.0006 | P29: 0 | Q29: =G29*M29 -> 0.0018 | R29: 56 | S29: 5000 | X29: R84 | Y29: N30101007296 | Z29: 片式电阻 0603WAF5601T5E 1/10W,5.6KΩ,1%,0603(厚声)(编带)(RoHS) | AA29: 0.0018 | AB29: N30101006101 | AC29: 片式电阻 RC0603FR-075K6L 1/10W,5.6KΩ,1%,0603(国巨)(编带)(RoHS) | AD29: 0.0026 | AE29: N30101003102 | AF29: 片式电阻 CR0603FA5601G 1/10W,5.6KΩ,1%,0603(丽智)(编带)(RoHS) | AG29: 报价中
A30: 41 | B30: 硬件 | C30: N30199000137 | D30: 片式电阻 1/10W,470Ω,1%,0603(编带)(RoHS)(互换件) | E30: AB级替换 | F30: SMT | G30: 1 | H30: N30101007322 | I30: 片式电阻 0603WAF4700T5E 1/10W,470Ω,1%,0603(厚声)(编带)(RoHS) | J30: 罗城 | K30: 10648 | L30: 厚声国际贸易（昆山）有限公司 | M30: 0.0018 | N30: 0.0024 | O30: =(N30-M30)*G30 -> 0.0006 | P30: 0 | Q30: =G30*M30 -> 0.0018 | R30: 56 | S30: 0 | T30: 5000 | X30: R13 | Y30: N30101006140 | Z30: 片式电阻 RC0603FR-07470RL 1/10W,470Ω,1%,0603(国巨)(编带)(RoHS) | AA30: 0.0025 | AB30: N30101003123 | AC30: 片式电阻 RS-03K4700FT 1/10W,470Ω,1%,0603(风华)(编带)(RoHS) | AD30: 0.0025 | AE30: 301H0471H1 | AF30: 片式电阻 RC0603FR-07470RL/0603WAF4700T5E 1/10W,470Ω,1%,0603(国巨/厚声)(编带)(RoHS) | AG30: 报价中
A31: 42 | B31: 硬件 | C31: N30199000146 | D31: 片式电阻 1/10W,3KΩ,1%,0603(编带)(RoHS)(互换件) | E31: AB级替换 | F31: SMT | G31: 8 | H31: N30101003140 | I31: 片式电阻 RS-03K3001FT 1/10W,3KΩ,1%,0603(风华)(编带)(RoHS) | J31: 虞思旻 | K31: MHDZ2 | L31: 厦门美赫电子有限公司 | M31: 0.0018 | N31: 0.0024 | O31: =(N31-M31)*G31 -> 0.0048 | P31: 0 | Q31: =G31*M31 -> 0.0144 | R31: 56 | S31: 5000 | X31: R146,147,150,151,172,173,176,177 | Y31: N30101007384 | Z31: 片式电阻 0603WAF3001T5E 1/10W,3KΩ,1%,0603(厚声)(编带)(RoHS) | AA31: 0.0018 | AB31: N30101006156 | AC31: 片式电阻 RC0603FR-073KL 1/10W,3KΩ,1%,0603(国巨)(编带)(RoHS) | AD31: 0.0026 | AE31: 301H0033H1 | AF31: 片式电阻 RC0603FR-073KL/0603WAF3001T5E 1/10W,3KΩ,1%,0603(国巨/厚声)(编带)(RoHS) | AG31: 报价中
A32: 43 | B32: 硬件 | C32: N30199000171 | D32: 片式电阻 1/10W,5.1KΩ,1%,0603(编带)(RoHS)(互换件) | E32: AB级替换 | F32: SMT | G32: 2 | H32: N30101007306 | I32: 片式电阻 0603WAF5101T5E 1/10W,5.1KΩ,1%,0603(厚声)(编带)(RoHS) | J32: 罗城 | K32: 10648 | L32: 厚声国际贸易（昆山）有限公司 | M32: 0.0018 | N32: 0.0024 | O32: =(N32-M32)*G32 -> 0.0012 | P32: 0 | Q32: =G32*M32 -> 0.0036 | R32: 56 | S32: 0 | T32: 5000 | X32: R137,138 | Y32: N30101003189 | Z32: 片式电阻 RS-03K5101FT 1/10W,5.1KΩ,1%,0603(风华)(编带)(RoHS) | AA32: 0.0024 | AB32: N30101006104 | AC32: 片式电阻 RC0603FR-075K1L 1/10W,5.1KΩ,1%,0603(国巨)(编带)(RoHS) | AD32: 0.0026 | AE32: 301H0512H1 | AF32: 片式电阻 RC0603FR-075K1L/0603WAF5101T5E 1/10W,5.1KΩ,1%,0603(国巨/厚声)(编带)(RoHS) | AG32: 报价中
A33: 44 | B33: 硬件 | C33: N30199000219 | D33: 片式电阻 1/10W,100Ω,1%,0603(编带)(RoHS)(互换件) | E33: AB级替换 | F33: SMT | G33: 29 | H33: N30101003284 | I33: 片式电阻 RS-03K1000FT 1/10W,100Ω,1%,0603(风华)(编带)(RoHS) | J33: 陈虹 | K33: MHDZ2 | L33: 厦门美赫电子有限公司 | M33: 0.0018 | N33: 0.0024 | O33: =(N33-M33)*G33 -> 0.0174 | P33: 0 | Q33: =G33*M33 -> 0.0522 | R33: 56 | S33: 5000 | X33: R18,24,25,32,33,106-111,119-130,212-217 | Y33: N30101007520 | Z33: 片式电阻 0603WAF1000T5E 1/10W,100Ω,1%,0603(厚声)(编带)(RoHS) | AA33: 0.0018 | AB33: N30101006338 | AC33: 片式电阻 RC0603FR-07100RL 1/10W,100Ω,1%,0603(国巨)(编带)(RoHS) | AD33: 0.0025 | AE33: 301H0101H1 | AF33: 片式电阻 RC0603FR-07100RL/0603WAF1000T5E 1/10W,100Ω,1%,0603(国巨/厚声)(编带)(RoHS) | AG33: 报价中
A34: 45 | B34: 硬件 | C34: N30199000237 | D34: 片式电阻 1/10W,510Ω,1%,0603(编带)(RoHS)(互换件) | E34: AB级替换 | F34: SMT | G34: 2 | H34: N30101003319 | I34: 片式电阻 RS-03K5100FT 1/10W,510Ω,1%,0603(风华)(编带)(RoHS) | J34: 虞思旻 | K34: MHDZ2 | L34: 厦门美赫电子有限公司 | M34: 0.0018 | N34: 0.0024 | O34: =(N34-M34)*G34 -> 0.0012 | P34: 0 | Q34: =G34*M34 -> 0.0036 | R34: 56 | S34: 5000 | X34: R66,78 | Y34: N30101007307 | Z34: 片式电阻 0603WAF5100T5E 1/10W,510Ω,1%,0603(厚声)(编带)(RoHS) | AA34: 0.0018 | AB34: N30101006120 | AC34: 片式电阻 RC0603FR-07510RL 1/10W,510Ω,1%,0603(国巨)(编带)(RoHS) | AD34: 0.0025 | AE34: 301H0511H1 | AF34: 片式电阻 RC0603FR-07510RL/0603WAF5100T5E 1/10W,510Ω,1%,0603(国巨/厚声)(编带)(RoHS) | AG34: 报价中
A35: 46 | B35: 硬件 | C35: N30199000335 | D35: 片式电阻 1/10W,1.5KΩ,1%,0603(编带)(RoHS)(互换件) | E35: AB级替换 | F35: SMT | G35: 1 | H35: N30101003511 | I35: 片式电阻 RS-03K1501FT 1/10W,1.5KΩ,1%,0603(风华)(编带)(RoHS) | J35: 虞思旻 | K35: MHDZ2 | L35: 厦门美赫电子有限公司 | M35: 0.0018 | N35: 0.0024 | O35: =(N35-M35)*G35 -> 0.0006 | P35: 0 | Q35: =G35*M35 -> 0.0018 | R35: 56 | S35: 5000 | X35: R54 | Y35: N30101007469 | Z35: 片式电阻 0603WAF1501T5E 1/10W,1.5KΩ,1%,0603(厚声)(编带)(RoHS) | AA35: 0.0018 | AB35: N30101006268 | AC35: 片式电阻 RC0603FR-071K5L 1/10W,1.5KΩ,1%,0603(国巨)(编带)(RoHS) | AD35: 0.0026 | AE35: N30101003510 | AF35: 片式电阻 CR0603FA1501G 1/10W,1.5KΩ,1%,0603(丽智)(编带)(RoHS) | AG35: 报价中
A36: 47 | B36: 硬件 | C36: N30199000342 | D36: 片式电阻 1/10W,51KΩ,1%,0603(编带)(RoHS)(互换件) | E36: AB级替换 | F36: SMT | G36: 2 | H36: N30101003525 | I36: 片式电阻 RS-03K5102FT 1/10W,51KΩ,1%,0603(风华)(编带)(RoHS) | J36: 虞思旻 | K36: MHDZ2 | L36: 厦门美赫电子有限公司 | M36: 0.0018 | N36: 0.0024 | O36: =(N36-M36)*G36 -> 0.0012 | P36: 0 | Q36: =G36*M36 -> 0.0036 | R36: 56 | S36: 5000 | X36: R15,36 | Y36: N30101007305 | Z36: 片式电阻 0603WAF5102T5E 1/10W,51KΩ,1%,0603(厚声)(编带)(RoHS) | AA36: 0.0018 | AB36: N30101006118 | AC36: 片式电阻 RC0603FR-0751KL 1/10W,51KΩ,1%,0603(国巨)(编带)(RoHS) | AD36: 0.0026 | AE36: N30101003524 | AF36: 片式电阻 CR0603FA5102G 1/10W,51KΩ,1%,0603(丽智)(编带)(RoHS) | AG36: 报价中
A37: 48 | B37: 硬件 | C37: N30199000397 | D37: 片式电阻 1/4W,20KΩ,1%,1206(编带)(RoHS)(互换件) | E37: AB级替换 | F37: SMT | G37: 1 | H37: N30101006792 | I37: 片式电阻 1206W4F2002T5E 1/4W,20KΩ,1%,1206(厚声)(编带)(RoHS) | J37: 陈虹 | K37: HSMY2 | L37: 厚声国际贸易（昆山）有限公司 | M37: 0.0058 | P37: 0 | Q37: =G37*M37 -> 0.0058 | R37: 49 | S37: 1 | X37: R57 | Y37: N30101003634 | Z37: 片式电阻 RS-06K2002FT 1/4W,20KΩ,1%,1206(风华)(编带)(RoHS) | AA37: 0.0069 | AB37: N30101005517 | AC37: 片式电阻 RC1206FR-0720KL 1/4W,20KΩ,1%,1206(国巨)(编带)(RoHS) | AD37: 0.008 | AE37: N30101003633 | AF37: 片式电阻 CR1206F42002G 1/4W,20KΩ,1%,1206(丽智)(编带)(RoHS) | AG37: 报价中
A38: 49 | B38: 硬件 | C38: N30199000444 | D38: 片式电阻 1/10W,6.2KΩ,1%,0603(编带)(RoHS)(互换件) | E38: AB级替换 | F38: SMT | G38: 1 | H38: N30101001125 | I38: 片式电阻 0603WAF6201T5E 1/10W,6.2KΩ,1%,0603(厚声)(编带)(RoHS) | J38: 陈虹 | K38: HSMY2 | L38: 厚声国际贸易（昆山）有限公司 | M38: 0.0018 | N38: 0.0024 | O38: =(N38-M38)*G38 -> 0.0006 | P38: 0 | Q38: =G38*M38 -> 0.0018 | R38: 84 | S38: 5000 | X38: R79 | Y38: N30101003728 | Z38: 片式电阻 RS-03K6201FT 1/10W,6.2KΩ,1%,0603(风华)(编带)(RoHS) | AA38: 0.0018 | AB38: 301H0622H1 | AC38: 片式电阻 RC0603FR-076K2L 1/10W,6.2KΩ,1%,0603(国巨)(编带)(RoHS) | AD38: 0.0025 | AE38: N30101003727 | AF38: 片式电阻 CR0603FA6201G 1/10W,6.2KΩ,1%,0603(丽智)(编带)(RoHS) | AG38: 报价中
A39: 50 | B39: 硬件 | C39: N30199000493 | D39: 片式电阻 1/4W,120Ω,5%,1206(编带)(RoHS)(互换件) | E39: AB级替换 | F39: SMT | G39: 2 | H39: N30101003826 | I39: 片式电阻 RS-06K121JT 1/4W,120Ω,5%,1206(风华)(编带)(RoHS) | J39: 陈虹 | K39: MHDZ2 | L39: 厦门美赫电子有限公司 | M39: 0.0043 | N39: 0.0057 | O39: =(N39-M39)*G39 -> 0.0028 | P39: 0 | Q39: =G39*M39 -> 0.0086 | R39: 56 | S39: 5000 | T39: 5000 | X39: R19,229 | Y39: N30101006672 | Z39: 片式电阻 1206W4J0121T5E 1/4W,120Ω,5%,1206(厚声)(编带)(RoHS) | AA39: 0.0043 | AB39: N30101005381 | AC39: 片式电阻 RC1206JR-07120RL 1/4W,120Ω,5%,1206(国巨)(编带)(RoHS) | AD39: 0.0075 | AE39: 301H012185 | AF39: 片式电阻 RC1206JR-07120RL/1206W4J0121T5E 1/4W,120Ω,5%,1206(国巨/厚声)(编带)(RoHS) | AG39: 报价中
A40: 51 | B40: 硬件 | C40: N30199000523 | D40: 片式电阻 1/4W,1KΩ,1%,1206(编带)(RoHS)(互换件) | E40: AB级替换 | F40: SMT | G40: 4 | H40: N30101003885 | I40: 片式电阻 RS-06K1001FT 1/4W,1KΩ,1%,1206(风华)(编带)(RoHS) | J40: 陈虹 | K40: MHDZ2 | L40: 厦门美赫电子有限公司 | M40: 0.0057 | N40: 0.0075 | O40: =(N40-M40)*G40 -> 0.0072 | P40: 0 | Q40: =G40*M40 -> 0.0228 | R40: 56 | S40: 5000 | X40: R37,86,88,91 | Y40: N30101006828 | Z40: 片式电阻 1206W4F1001T5E 1/4W,1KΩ,1%,1206(厚声)(编带)(RoHS) | AA40: 0.0057 | AB40: N30101005505 | AC40: 片式电阻 RC1206FR-071KL 1/4W,1KΩ,1%,1206(国巨)(编带)(RoHS) | AD40: 0.0075 | AE40: N30101003884 | AF40: 片式电阻 CR1206F41001G 1/4W,1KΩ,1%,1206(丽智)(编带)(RoHS) | AG40: 报价中
A41: 52 | B41: 硬件 | C41: N30199000561 | D41: 片式电阻 1/4W,47Ω,1%,1206(编带)(RoHS)(互换件) | E41: AB级替换 | F41: SMT | G41: 10 | H41: N30101006724 | I41: 片式电阻 1206W4F470JT5E 1/4W,47Ω,1%,1206(厚声)(编带)(RoHS) | J41: 罗城 | K41: 10648 | L41: 厚声国际贸易（昆山）有限公司 | M41: 0.0058 | N41: 0.0075 | O41: =(N41-M41)*G41 -> 0.017 | P41: 0 | Q41: =G41*M41 -> 0.058 | R41: 56 | S41: 0 | T41: 5000 | X41: R1,3,59,72,131,133,135,204,206,208 | Y41: N30101003958 | Z41: 片式电阻 RS-06K47R0FT 1/4W,47Ω,1%,1206(风华)(编带)(RoHS) | AA41: 0.0069 | AB41: N30101005579 | AC41: 片式电阻 RC1206FR-0747RL 1/4W,47Ω,1%,1206(国巨)(编带)(RoHS) | AD41: 0.008 | AE41: N30101003957 | AF41: 片式电阻 CR1206F447R0G 1/4W,47Ω,1%,1206(丽智)(编带)(RoHS) | AG41: 报价中
A42: 53 | B42: 硬件 | C42: N30199000577 | D42: 片式电阻 1/4W,300KΩ,1%,1206(编带)(RoHS)(互换件) | E42: AB级替换 | F42: SMT | G42: 9 | H42: N30101006758 | I42: 片式电阻 1206W4F3003T5E 1/4W,300KΩ,1%,1206(厚声)(编带)(RoHS) | J42: 陈虹 | K42: HSMY2 | L42: 厚声国际贸易（昆山）有限公司 | M42: 0.0058 | N42: 0.0075 | O42: =(N42-M42)*G42 -> 0.0153 | P42: 0 | Q42: =G42*M42 -> 0.0522 | R42: 49 | S42: 1 | X42: R101,102,115,152,169-171,180,181 | Y42: N30101003990 | Z42: 片式电阻 RS-06K3003FT 1/4W,300KΩ,1%,1206(风华)(编带)(RoHS) | AA42: 0.0069 | AB42: N30101005551 | AC42: 片式电阻 RC1206FR-07300KL 1/4W,300KΩ,1%,1206(国巨)(编带)(RoHS) | AD42: 0.008 | AE42: N30101000672 | AF42: 片式电阻 RC1206FR-07300KL/1206W4F3003T5E 1/4W,300KΩ,1%,1206(国巨/厚声)(编带)(RoHS) | AG42: 报价中
A43: 54 | B43: 硬件 | C43: N30199000605 | D43: 片式电阻 1/4W,10Ω,1%,1206(编带)(RoHS)(互换件) | E43: AB级替换 | F43: SMT | G43: 6 | H43: N30101006824 | I43: 片式电阻 1206W4F100JT5E 1/4W,10Ω,1%,1206(厚声)(编带)(RoHS) | J43: 罗城 | K43: 10648 | L43: 厚声国际贸易（昆山）有限公司 | M43: 0.0058 | N43: 0.0075 | O43: =(N43-M43)*G43 -> 0.0102 | P43: 0 | Q43: =G43*M43 -> 0.0348 | R43: 56 | S43: 0 | T43: 5000 | X43: R132,134,136,203,205,207 | Y43: N30101004045 | Z43: 片式电阻 RS-06K10R0FT 1/4W,10Ω,1%,1206(风华)(编带)(RoHS) | AA43: 0.0072 | AB43: N30101005488 | AC43: 片式电阻 RC1206FR-0710RL 1/4W,10Ω,1%,1206(国巨)(编带)(RoHS) | AD43: 0.0279 | AE43: N30101004044 | AF43: 片式电阻 CR1206F410R0G 1/4W,10Ω,1%,1206(丽智)(编带)(RoHS) | AG43: 报价中
A44: 55 | B44: 硬件 | C44: N30199000614 | D44: 片式电阻 1/10W,7.5KΩ,1%,0603(编带)(RoHS)(互换件) | E44: AB级替换 | F44: SMT | G44: 13 | H44: N30101007264 | I44: 片式电阻 0603WAF7501T5E 1/10W,7.5KΩ,1%,0603(厚声)(编带)(RoHS) | J44: 陈虹 | K44: HSMY2 | L44: 厚声国际贸易（昆山）有限公司 | M44: 0.0018 | N44: 0.0024 | O44: =(N44-M44)*G44 -> 0.0078 | P44: 0 | Q44: =G44*M44 -> 0.0234 | R44: 49 | S44: 1 | X44: R53,55,85,139,140,157-162,239,240 | Y44: N30101004063 | Z44: 片式电阻 RS-03K7501FT 1/10W,7.5KΩ,1%,0603(风华)(编带)(RoHS) | AA44: 0.0022 | AB44: N30101006068 | AC44: 片式电阻 RC0603FR-077K5L 1/10W,7.5KΩ,1%,0603(国巨)(编带)(RoHS) | AD44: 0.0026 | AE44: N30101001061 | AF44: 片式电阻 RC0603FR-077K5L/0603WAF7501T5E 1/10W,7.5KΩ,1%,0603(国巨/厚声)(编带)(RoHS) | AG44: 报价中
A45: 56 | B45: 硬件 | C45: N30199000619 | D45: 片式电阻 1/10W,10.5KΩ,1%,0603(编带)(RoHS)(互换件) | E45: AB级替换 | F45: SMT | G45: 1 | H45: N30101007511 | I45: 片式电阻 0603WAF1052T5E 1/10W,10.5KΩ,1%,0603(厚声)(编带)(RoHS) | J45: 陈虹 | K45: HSMY2 | L45: 厚声国际贸易（昆山）有限公司 | M45: 0.0018 | N45: 0.0024 | O45: =(N45-M45)*G45 -> 0.0006 | P45: 0 | Q45: =G45*M45 -> 0.0018 | R45: 42 | S45: 1 | X45: R48 | Y45: N30101004220 | Z45: 片式电阻 RS-03K1052FT 1/10W,10.5KΩ,1%,0603(风华)(编带)(RoHS) | AA45: 0.0022 | AB45: N30101006332 | AC45: 片式电阻 RC0603FR-0710K5L 1/10W,10.5KΩ,1%,0603(国巨)(编带)(RoHS) | AD45: 0.0026 | AE45: N30101001496 | AF45: 片式电阻 RC0603FR-0710K5L/0603WAF1052T5E 1/10W,10.5KΩ,1%,0603(国巨/厚声)(编带)(RoHS) | AG45: 报价中
A46: 57 | B46: 硬件 | C46: N30199000620 | D46: 片式电阻 1/10W,1.2KΩ,1%,0603(编带)(RoHS)(互换件) | E46: AB级替换 | F46: SMT | G46: 2 | H46: N30101007498 | I46: 片式电阻 0603WAF1201T5E 1/10W,1.2KΩ,1%,0603(厚声)(编带)(RoHS) | J46: 罗城 | K46: 10648 | L46: 厚声国际贸易（昆山）有限公司 | M46: 0.0018 | N46: 0.0024 | O46: =(N46-M46)*G46 -> 0.0012 | P46: 0 | Q46: =G46*M46 -> 0.0036 | R46: 56 | S46: 0 | T46: 5000 | X46: R154,156 | Y46: N30101004224 | Z46: 片式电阻 RS-03K1201FT 1/10W,1.2KΩ,1%,0603(风华)(编带)(RoHS) | AA46: 0.0023 | AB46: N30101006272 | AC46: 片式电阻 RC0603FR-071K2L 1/10W,1.2KΩ,1%,0603(国巨)(编带)(RoHS) | AD46: 0.0026 | AE46: 301H0122H1 | AF46: 片式电阻 RC0603FR-071K2L/0603WAF1201T5E 1/10W,1.2KΩ,1%,0603(国巨/厚声)(编带)(RoHS) | AG46: 报价中
A47: 58 | B47: 硬件 | C47: N30199000693 | D47: 片式电阻 1/10W,0Ω,1%,0603(编带)(RoHS)(互换件) | E47: AB级替换 | F47: SMT | G47: 3 | H47: N30101004568 | I47: 片式电阻 RS-03K000FT 1/10W,0Ω,1%,0603(风华)(编带)(RoHS) | J47: 虞思旻 | K47: MHDZ2 | L47: 厦门美赫电子有限公司 | M47: 0.0018 | N47: 0.0024 | O47: =(N47-M47)*G47 -> 0.0018 | P47: 0 | Q47: =G47*M47 -> 0.0054 | R47: 56 | S47: 1 | X47: A0,R0,,R79A | Y47: N30101004534 | Z47: 片式电阻 0603WAF0000T5E 1/10W,0Ω,1%,0603(厚声)(编带)(RoHS) | AA47: 0.002 | AB47: N30101002504 | AC47: 片式电阻 RC0603FR-070RL 1/10W,0Ω,1%,0603(国巨)(编带)(RoHS) | AD47: 0.0026
A48: 59 | B48: 硬件 | C48: N30199000804 | D48: 片式电阻 1/4W,30Ω,1%,1206(编带)(RoHS)(互换件) | E48: AB级替换 | F48: SMT | G48: 3 | H48: N30101004863 | I48: 片式电阻 1206W4F300JT5E 1/4W,30Ω,1%,1206(厚声)(编带)(RoHS) | J48: 江华媛 | K48: 10648 | L48: 厚声国际贸易（昆山）有限公司 | M48: 0.0065 | N48: 0.0075 | O48: =(N48-M48)*G48 -> 0.003 | P48: 0 | Q48: =G48*M48 -> 0.0195 | R48: 42 | S48: 5000 | T48: 5000 | X48: R209-211 | Y48: N30101004973 | Z48: 片式电阻 RS-06K30R0FT 1/4W,30Ω,1%,1206(风华)(编带)(RoHS) | AA48: 0.0072 | AB48: N30101002273 | AC48: 片式电阻 RC1206FR-0730RL 1/4W,30Ω,1%,1206(国巨)(编带)(RoHS) | AD48: 0.0076
A49: 60 | B49: 硬件 | C49: N30199000819 | D49: 片式电阻 1/10W,910Ω,1%,0603(编带)(RoHS)(互换件) | E49: AB级替换 | F49: SMT | G49: 2 | H49: N30101004847 | I49: 片式电阻 0603WAF9100T5E 1/10W,910Ω,1%,0603(厚声)(编带)(RoHS) | J49: 江华媛 | K49: 10648 | L49: 厚声国际贸易（昆山）有限公司 | M49: 0.002 | N49: 0.0024 | O49: =(N49-M49)*G49 -> 0.0008 | P49: 0 | Q49: =G49*M49 -> 0.004 | R49: 42 | S49: 5000 | T49: 5000 | X49: R153,155 | Y49: N30101004970 | Z49: 片式电阻 RS-03K9100FT 1/10W,910Ω,1%,0603(风华)(编带)(RoHS) | AA49: 0.0022 | AB49: N30101002401 | AC49: 片式电阻 RC0603FR-07910RL 1/10W,910Ω,1%,0603(国巨)(编带)(RoHS) | AD49: 0.0025
A50: 61 | B50: 硬件 | C50: N30301000078 | D50: 压敏电阻 561KD14 (君耀)(RoHS) | E50: AB级替换 | F50: 插焊 | G50: 2 | H50: N30301000078 | I50: 压敏电阻 561KD14 (君耀)(RoHS) | J50: 江华媛 | K50: 10266 | L50: 深圳市超利维实业有限公司 | M50: 0.286 | N50: 0.3432 | O50: =(N50-M50)*G50 -> 0.1144 | P50: 0 | Q50: =G50*M50 -> 0.572 | R50: 84 | S50: 1200 | T50: 300 | X50: RV5,6
A51: 62 | B51: 硬件 | C51: N30301000122 | D51: 压敏电阻 911KD14-TR 550Vac,10%,P=7.5,Φ14(175J)(君耀)(编带)(RoHS) | E51: AB级替换 | F51: 插焊 | G51: 3 | H51: N30301000122 | I51: 压敏电阻 911KD14-TR 550Vac,10%,P=7.5,Φ14(175J)(君耀)(编带)(RoHS) | J51: 521 | K51: 10266 | L51: 深圳市超利维实业有限公司 | M51: 0.4425 | N51: 0.5069 | O51: =(N51-M51)*G51 -> 0.1932 | P51: 0 | Q51: =G51*M51 -> 1.3275 | R51: 70 | S51: 2000 | T51: 400 | X51: RV2-4
A52: 63 | B52: 硬件 | C52: N30303000192 | D52: PTC热敏电阻 MZ32-47RHAGD03-C 280Vac,7A,47Ω,25%,P=8.5(安培龙)(RoHS) | E52: AB级替换 | F52: 插焊 | G52: 1 | H52: N30303000192 | I52: PTC热敏电阻 MZ32-47RHAGD03-C 280Vac,7A,47Ω,25%,P=8.5(安培龙)(RoHS) | J52: 521 | K52: 10666 | L52: 深圳安培龙科技股份有限公司 | M52: 1.0619 | P52: 0 | Q52: =G52*M52 -> 1.0619 | R52: 42 | S52: 1 | T52: 1 | X52: R405
A53: 64 | B53: 硬件 | C53: N30303000193 | D53: PTC热敏电阻 MZ32-68RNAGD01-C 440Vac,27A,68Ω,30%,P=8.5(安培龙)(RoHS) | E53: AB级替换 | F53: 插焊 | G53: 1 | H53: N30303000193 | I53: PTC热敏电阻 MZ32-68RNAGD01-C 440Vac,27A,68Ω,30%,P=8.5(安培龙)(RoHS) | J53: 521 | K53: 10666 | L53: 深圳安培龙科技股份有限公司 | M53: 2.1239 | P53: 0 | Q53: =G53*M53 -> 2.1239 | R53: 42 | S53: 1 | T53: 1 | X53: R404
A54: 65 | B54: 硬件 | C54: N30309000009 | D54: 电流传感器 STK-50PL (希磁)(JCI 专用)(RoHS) | E54: AB级替换 | F54: 插焊 | G54: 1 | H54: N30309000009 | I54: 电流传感器 STK-50PL (希磁)(JCI 专用)(RoHS) | J54: 江华媛 | K54: BBXC2 | L54: 安徽希磁科技股份有限公司（特采) | M54: 9.2 | P54: 0 | Q54: =G54*M54 -> 9.2 | R54: 56 | S54: 2400 | X54: H1
A55: 66 | B55: 硬件 | C55: N30501000394 | D55: 安规薄膜电容 (X2) HQX225K0275NAYCCL15S 2.2uF,10%,275Vac,26.5X13X23,P=22.5(昱电)(RoHS) | E55: AB级替换 | F55: 插焊 | G55: 3 | H55: N30501000394 | I55: 安规薄膜电容 (X2) HQX225K0275NAYCCL15S 2.2uF,10%,275Vac,26.5X13X23,P=22.5(昱电)(RoHS) | J55: 521 | K55: 10656 | L55: 厦门大毅电子有限公司 | M55: 1.2 | P55: 0 | Q55: =G55*M55 -> 3.6 | R55: 30 | S55: 1 | T55: 1 | X55: C130,131,133
A56: 67 | B56: 硬件 | C56: N30503000105 | D56: 聚丙烯膜电容 C372J105J6SC000 1uF,5%,630V,P=15(法拉)(RoHS) | E56: AB级替换 | F56: 插焊 | G56: 3 | H56: N30503000105 | I56: 聚丙烯膜电容 C372J105J6SC000 1uF,5%,630V,P=15(法拉)(RoHS) | J56: 江华媛 | K56: 10715 | L56: 厦门法拉电子股份有限公司 | M56: 0.65 | P56: 0 | Q56: =G56*M56 -> 1.95 | R56: 63 | S56: 1500 | T56: 1500 | X56: C98,99,208
A57: 68 | B57: 硬件 | C57: N30503000217 | D57: 聚丙烯膜电容 C322J222J30A301 2.2nF,5%,630Vdc,P=7.5(法拉)(编带)(RoHS) | E57: AB级替换 | F57: 插焊 | G57: 1 | H57: N30503000217 | I57: 聚丙烯膜电容 C322J222J30C000 2.2nF,5%,630Vdc,P=7.5(法拉)(编带)(RoHS) | J57: 521 | K57: 10715 | L57: 厦门法拉电子股份有限公司 | M57: 0.18 | P57: 0 | Q57: =G57*M57 -> 0.18 | R57: 45 | S57: 1000 | T57: 1000 | X57: C10
A58: 69 | B58: 硬件 | C58: N30503000218 | D58: 聚丙烯膜电容 C822J102J30A301 1nF,5%,630Vdc,P=7.5(法拉)(编带)(RoHS) | E58: AB级替换 | F58: 插焊 | G58: 1 | H58: N30503000218 | I58: 聚丙烯膜电容 C822J102J30C000 1nF,5%,630Vdc,P=7.5(法拉)(编带)(RoHS) | J58: 521 | K58: 10715 | L58: 厦门法拉电子股份有限公司 | M58: 0.22 | P58: 0 | Q58: =G58*M58 -> 0.22 | R58: 70 | S58: 1000 | T58: 1000 | X58: C124
A59: 70 | B59: 硬件 | C59: N30503000219 | D59: 聚丙烯膜电容 MKP21-1000V474K 470nF,10%,1KVdc,P=22.5(NJTJ专用)(华裕)(RoHS) | E59: AB级替换 | F59: 插焊 | G59: 1 | H59: N30503000219 | I59: 聚丙烯膜电容 MKP21-1000V474K 470nF,10%,1KVdc,P=22.5(NJTJ专用)(华裕)(RoHS) | J59: 521 | K59: 10250 | L59: 深圳市黑快能科技发展有限公司 | M59: 0.335 | P59: 0 | Q59: =G59*M59 -> 0.335 | R59: 15 | S59: 1 | T59: 1 | X59: C50
A60: 71 | B60: 硬件 | C60: N30503000244 | D60: 聚丙烯膜电容 EZPV1B406MTC 40uF,10%,1.1KVdc,57.5X56X35,P=52.5(国创提供)(符合AEC-Q200)(Panasonic)(RoHS) | E60: AB级替换 | F60: 插焊 | G60: 3 | H60: N30503000244 | I60: 聚丙烯膜电容 EZPV1B406MTC 40uF,10%,1.1KVdc,57.5X56X35,P=52.5(国创提供)(符合AEC-Q200)(Panasonic)(RoHS) | J60: 196386 | L60: 20251014业务邮件通知客供料 | M60: 0 | P60: 0 | Q60: =G60*M60 -> 0 | R60: 0 | V60: 客供料 | X60: C125-127
A61: 72 | B61: 硬件 | C61: N30506000898 | D61: 铝电解电容 YXJ 16YXJ220MT16.3X11 220uF,20%,16V,105℃,6.3X11,P=2.5(Rubycon)(编带)(RoHS) | E61: AB级替换 | F61: 插焊 | G61: 2 | H61: N30506000898 | I61: 铝电解电容 YXJ 16YXJ220MT16.3X11 220uF,20%,16V,105℃,6.3X11,P=2.5(Rubycon)(编带)(RoHS) | J61: 虞思旻 | K61: XMAEH | L61: 厦门埃尔华进出口有限公司 | M61: 0.145 | P61: 0 | Q61: =G61*M61 -> 0.29 | R61: 77 | S61: 2000 | X61: C143,147
A62: 73 | B62: 硬件 | C62: N30506001051 | D62: 铝电解电容 35YXJ100MT16.3X11 100uF,20%,35V,105℃,6.3X11,P=2.5(Rubycon)(编带)(RoHS) | E62: AB级替换 | F62: 插焊 | G62: 2 | H62: N30506001051 | I62: 铝电解电容 35YXJ100MT16.3X11 100uF,20%,35V,105℃,6.3X11,P=2.5(Rubycon)(编带)(RoHS) | J62: 陈伟环 | K62: 10364 | L62: 厦门埃尔华进出口有限公司 | M62: 0.1513 | P62: 0 | Q62: =G62*M62 -> 0.3026 | R62: 97 | S62: 2000 | T62: 2000 | X62: C150,158
A63: 74 | B63: 硬件 | C63: N30506001064 | D63: 铝电解电容 35YXJ470MT810X16 470uF,20%,35V,105℃,10X16,P=5(Rubycon)(编带)(RoHS) | E63: AB级替换 | F63: 插焊 | G63: 4 | H63: N30506001064 | I63: 铝电解电容 35YXJ470MT810X16 470uF,20%,35V,105℃,10X16,P=5(Rubycon)(编带)(RoHS) | J63: 陈伟环 | K63: xmaeh | L63: 厦门埃尔华进出口有限公司 | M63: 0.3969 | P63: 0 | Q63: =G63*M63 -> 1.5876 | R63: 112 | S63: 1000 | X63: C140,144-146
A64: 75 | B64: 硬件 | C64: N30506001069 | D64: 铝电解电容 50YXF47MT16.3X11 47uF,20%,50V,105℃,6.3X11,P=2.5(Rubycon)(编带)(RoHS) | E64: AB级替换 | F64: 插焊 | G64: 2 | H64: N30506001069 | I64: 铝电解电容 50YXF47MT16.3X11 47uF,20%,50V,105℃,6.3X11,P=2.5(Rubycon)(编带)(RoHS) | J64: 陈伟环 | K64: xmaeh | L64: 厦门埃尔华进出口有限公司 | M64: 0.1401 | P64: 0 | Q64: =G64*M64 -> 0.2802 | R64: 91 | S64: 1000 | X64: C138,139
A65: 76 | B65: 硬件 | C65: N30506002046 | D65: 铝电解电容 LB1E471MF160B35CE0 470uF,20%,25V,105℃,8X16,P=3.5,6000h(华威)(编带)(RoHS) | E65: AB级替换 | F65: 插焊 | G65: 1 | H65: N30506002046 | I65: 铝电解电容 LB1E471MF160B35CE0 470uF,20%,25V,105℃,8X16,P=3.5(华威)(编带)(RoHS) | J65: 陈伟环 | K65: 10033 | L65: 常州华威电子有限公司 | M65: 0.18 | P65: 0 | Q65: =G65*M65 -> 0.18 | R65: 21 | S65: 20000 | T65: 1000 | X65: C141
A66: 77 | B66: 硬件 | C66: N30506002166 | D66: 铝电解电容 ELT2WM152Y80LTSP 1500uF,20%,450V,105℃,40X80,P=14.2,5000h(艾华)(RoHS) | E66: AB级替换 | F66: 插焊 | G66: 1 | H66: N30506002166 | I66: 铝电解电容 ELT2WM152Y80LTSP 1500uF,20%,450V,105℃,40X80,P=14.2,5000h(艾华)(RoHS) | J66: 105935 | K66: 10003 | L66: 湖南艾华集团股份有限公司 | M66: 39.2 | P66: 0 | Q66: =G66*M66 -> 39.2 | R66: 56 | S66: 0 | T66: 1000 | X66: C132
A67: 78 | B67: 硬件 | C67: N30508000060 | D67: 安规陶瓷电容 (X1Y1) CD45-E2GA222M-VKA 2.2nF,20%,(X1)440Vac,(Y1)400Vac,P=10(TDK)(编带)(RoHS) | E67: AB级替换 | F67: 插焊 | G67: 2 | H67: N30508000060 | I67: 安规陶瓷电容 (X1Y1) CD45-E2GA222M-VKA 2.2nF,20%,(X1)440Vac,(Y1)400Vac,P=10(TDK)(编带)(RoHS) | J67: 罗城 | K67: 10758 | L67: 瑞瑜国际贸易（上海）有限公司 | M67: 0.1647 | P67: 0 | Q67: =G67*M67 -> 0.3294 | R67: 112 | S67: 0 | T67: 1000 | X67: C136,137
A68: 79 | B68: 硬件 | C68: N30515002473 | D68: 片式瓷介电容 0805B475K500NT X7R,4.7uF,10%,50V,0805(风华)(编带)(RoHS) | E68: AB级替换 | F68: SMT | G68: 2 | H68: N30515002473 | I68: 片式瓷介电容 0805B475K500NT X7R,4.7uF,10%,50V,0805(风华)(编带)(RoHS) | J68: 521 | K68: 10178 | L68: 厦门美赫电子有限公司 | M68: 0.1 | N68: 0.1386 | O68: =(N68-M68)*G68 -> 0.0772 | P68: 0 | Q68: =G68*M68 -> 0.2 | R68: 56 | S68: 2000 | T68: 2000 | X68: C9,20
A69: 80 | B69: 硬件 | C69: N30599000004 | D69: 片式瓷介电容 X7R,100nF,10%,50V,0603(编带)(RoHS)(互换件) | E69: AB级替换 | F69: SMT | G69: 45 | H69: N30515001005 | I69: 片式瓷介电容 0603B104K500NT X7R,100nF,10%,50V,0603(风华)(编带)(RoHS) | J69: 陈虹 | K69: MHDZ2 | L69: 厦门美赫电子有限公司 | M69: 0.0051 | N69: 0.0052 | O69: =(N69-M69)*G69 -> 0.0045 | P69: 0 | Q69: =G69*M69 -> 0.2295 | R69: 70 | S69: 4000 | X69: C1,3,5-8,13,16-18,21-24,26-31,33-35,37,43,45,47,48,65-70,78-80,88,109-111,122,123,160,188 | Y69: N30515000714 | Z69: 片式瓷介电容 TCC0603X7R104K500CT X7R,100nF,10%,50V,0603(三环)(编带)(RoHS) | AA69: 0.0057 | AB69: N30515000736 | AC69: 片式瓷介电容 0603B104K500CT X7R,100nF,10%,50V,0603(华新科技)(编带)(RoHS) | AD69: 0.0064 | AE69: N30515000279 | AF69: 片式瓷介电容 CC0603KRX7R9BB104 X7R,100nF,10%,50V,0603(国巨)(编带)(RoHS) | AG69: 0.0066
A70: 81 | B70: 硬件 | C70: N30599000010 | D70: 片式瓷介电容 NP0,100pF,5%,50V,0603(编带)(RoHS)(互换件) | E70: AB级替换 | F70: SMT | G70: 31 | H70: N30515001156 | I70: 片式瓷介电容 0603CG101J500NT NP0,100pF,5%,50V,0603(风华)(编带)(RoHS) | J70: 521 | K70: 10178 | L70: 厦门美赫电子有限公司 | M70: 0.005 | N70: 0.0053 | O70: =(N70-M70)*G70 -> 0.0093 | P70: 0 | Q70: =G70*M70 -> 0.155 | R70: 56 | S70: 1 | T70: 1 | X70: C14,56-61,72-77,82-87,91-93,100-102,115-120 | Y70: N30515001358 | Z70: 片式瓷介电容 TCC0603COG101J500CT NP0,100pF,5%,50V,0603(三环)(编带)(RoHS) | AA70: 0.0053 | AB70: 31012101J4N01 | AC70: 片式瓷介电容 CC0603JRNPO9BN101 NP0,100pF,5%,50V,0603(国巨)(编带)(RoHS) | AD70: 0.0055 | AE70: N30515002843 | AF70: 片式瓷介电容 C1608C0G1H101J080AA C0G,100pF,5%,50V,0603(TDK)(编带)(RoHS) | AG70: 0.0206
A71: 82 | B71: 硬件 | C71: N30599000011 | D71: 片式瓷介电容 X7R,1nF,10%,50V,0603(编带)(RoHS)(互换件) | E71: AB级替换 | F71: SMT | G71: 10 | H71: N30515001074 | I71: 片式瓷介电容 0603B102K500NT X7R,1nF,10%,50V,0603(风华)(编带)(RoHS) | J71: 陈虹 | K71: MHDZ2 | L71: 厦门美赫电子有限公司 | M71: 0.0048 | N71: 0.0049 | O71: =(N71-M71)*G71 -> 0.001 | P71: 0 | Q71: =G71*M71 -> 0.048 | R71: 70 | S71: 4000 | X71: C15,32,38,42,44,55,94,95,142,155 | Y71: 31012102K4X01 | Z71: 片式瓷介电容 CC0603KRX7R9BB102 X7R,1nF,10%,50V,0603(国巨)(编带)(RoHS) | AA71: 0.005 | AB71: N30515000613 | AC71: 片式瓷介电容 0603B102K500CT X7R,1nF,10%,50V,0603(华新科技)(编带)(RoHS) | AD71: 0.0057 | AE71: N30515000782 | AF71: 片式瓷介电容 TCC0603X7R102K500CT X7R,1nF,10%,50V,0603(三环)(编带)(RoHS) | AG71: 0.0058
A72: 83 | B72: 硬件 | C72: N30599000014 | D72: 片式瓷介电容 X7R,10nF,10%,50V,0603(编带)(RoHS)(互换件) | E72: AB级替换 | F72: SMT | G72: 7 | H72: N30515001150 | I72: 片式瓷介电容 0603B103K500NT X7R,10nF,10%,50V,0603(风华)(编带)(RoHS) | J72: 陈虹 | K72: MHDZ2 | L72: 厦门美赫电子有限公司 | M72: 0.0048 | N72: 0.005 | O72: =(N72-M72)*G72 -> 0.0014 | P72: 0 | Q72: =G72*M72 -> 0.0336 | R72: 70 | S72: 4000 | X72: C39-41,51-54 | Y72: 31011031-1 | Z72: 片式瓷介电容 CC0603KRX7R9BB103 X7R,10nF,10%,50V,0603(国巨)(编带)(RoHS) | AA72: 0.0049 | AB72: N30515000735 | AC72: 片式瓷介电容 0603B103K500CT X7R,10nF,10%,50V,0603(华新科技)(编带)(RoHS) | AD72: 0.0058 | AE72: N30515000713 | AF72: 片式瓷介电容 TCC0603X7R103K500CT X7R,10nF,10%,50V,0603(三环)(编带)(RoHS) | AG72: 0.0063
A73: 84 | B73: 硬件 | C73: N30599000017 | D73: 片式瓷介电容 X7R,100nF,10%,50V,1206(编带)(RoHS)(互换件) | E73: AB级替换 | F73: SMT | G73: 1 | H73: N30515001169 | I73: 片式瓷介电容 1206B104K500NT X7R,100nF,10%,50V,1206(风华)(编带)(RoHS) | J73: 陈虹 | K73: MHDZ2 | L73: 厦门美赫电子有限公司 | M73: 0.0217 | P73: 0 | Q73: =G73*M73 -> 0.0217 | R73: 84 | S73: 4000 | X73: C25 | Y73: N30515001366 | Z73: 片式瓷介电容 TCC1206X7R104K500DT X7R,100nF,10%,50V,1206(三环)(编带)(RoHS) | AA73: 0.0226 | AB73: N30515002509 | AC73: 片式瓷介电容 1206B104K500CT X7R,100nF,10%,50V,1206(华新科技)(编带)(RoHS) | AD73: 0.0274 | AE73: N30515002520 | AF73: 片式瓷介电容 CC1206KRX7R9BB104 X7R,100nF,10%,50V,1206(国巨)(编带)(RoHS) | AG73: 0.0275
A74: 85 | B74: 硬件 | C74: N30599000047 | D74: 片式瓷介电容 X7R,3.3nF,10%,50V,0603(编带)(RoHS)(互换件) | E74: AB级替换 | F74: SMT | G74: 2 | H74: N30515001415 | I74: 片式瓷介电容 0603B332K500NT X7R,3.3nF,10%,50V,0603(风华)(编带)(RoHS) | J74: 陈虹 | K74: MHDZ2 | L74: 厦门美赫电子有限公司 | M74: 0.0052 | N74: 0.0053 | O74: =(N74-M74)*G74 -> 0.0002 | P74: 0 | Q74: =G74*M74 -> 0.0104 | R74: 77 | S74: 4000 | X74: C46,49 | Y74: N30515002529 | Z74: 片式瓷介电容 CC0603KRX7R9BB332 X7R,3.3nF,10%,50V,0603(国巨)(编带)(RoHS) | AA74: 0.0055 | AB74: N30515001414 | AC74: 片式瓷介电容 TCC0603X7R332K500CT X7R,3.3nF,10%,50V,0603(三环)(编带)(RoHS) | AD74: 0.0069 | AE74: N30515002511 | AF74: 片式瓷介电容 0603B332K500CT X7R,3.3nF,10%,50V,0603(华新科技)(编带)(RoHS) | AG74: 0.0089
A75: 86 | B75: 硬件 | C75: N30599000063 | D75: 片式瓷介电容 X7R,220nF,10%,50V,0603(编带)(RoHS)(互换件) | E75: AB级替换 | F75: SMT | G75: 2 | H75: N30515001445 | I75: 片式瓷介电容 0603B224K500NT X7R,220nF,10%,50V,0603(风华)(编带)(RoHS) | J75: 陈虹 | K75: SJC2 | L75: 深圳市集财实业有限公司（ZZ） | M75: 0.0165 | P75: 0 | Q75: =G75*M75 -> 0.033 | R75: 63 | S75: 4000 | X75: C71,81 | Y75: N30515000358 | Z75: 片式瓷介电容 CC0603KRX7R9BB224 X7R,220nF,10%,50V,0603(国巨)(编带)(RoHS) | AA75: 0.0181 | AB75: N30515001444 | AC75: 片式瓷介电容 TCC0603X7R224K500CT X7R,220nF,10%,50V,0603(三环)(编带)(RoHS) | AD75: 0.0207 | AE75: N30515000948 | AF75: 片式瓷介电容 GRM188R71H224KAC4D X7R,220nF,10%,50V,0603(Murata)(编带)(RoHS) | AG75: 0.055
A76: 87 | B76: 硬件 | C76: N30599000084 | D76: 片式瓷介电容 X7R,470pF,10%,250V,1206(编带)(RoHS)(互换件) | E76: AB级替换 | F76: SMT | G76: 2 | H76: N30515001484 | I76: 片式瓷介电容 TCC1206X7R471K251DT X7R,470pF,10%,250V,1206(三环)(编带)(RoHS) | J76: 504 | K76: 10829 | L76: 厦门翔烨云供应链科技有限公司 | M76: 0.0313 | P76: 0 | Q76: =G76*M76 -> 0.0626 | R76: 7 | S76: 1 | T76: 4000 | X76: C2,19 | Y76: N30515001175 | Z76: 片式瓷介电容 1206B471K251NT X7R,470pF,10%,250V,1206(风华)(编带)(RoHS) | AA76: 0.0314 | AB76: N30515000572 | AC76: 片式瓷介电容 CC1206KRX7RYBB471 X7R,470pF,10%,250V,1206(国巨)(编带)(RoHS) | AD76: 0.047
A77: 88 | B77: 硬件 | C77: N30599000125 | D77: 片式瓷介电容 X7R,1uF,10%,50V,0603(编带)(RoHS)(互换件) | E77: AB级替换 | F77: SMT | G77: 8 | H77: N30515001987 | I77: 片式瓷介电容 CL10B105KB8NQNC X7R,1uF,10%,50V,0603(Samsung)(编带)(RoHS) | J77: 521 | K77: 10265 | L77: 北天星电子(深圳)有限公司 | M77: 0.0168 | P77: 0 | Q77: =G77*M77 -> 0.1344 | R77: 90 | S77: 1 | T77: 4000 | X77: C4,11,62-64,112-114 | Y77: N30515001569 | Z77: 片式瓷介电容 0603B105K500NT X7R,1uF,10%,50V,0603(风华)(编带)(RoHS) | AA77: 0.028 | AB77: N30515001106 | AC77: 片式瓷介电容 UMK107AB7105KA-T X7R,1uF,10%,50V,0603(Taiyo Yuden)(编带)(RoHS) | AD77: 0.031 | AE77: N30515001568 | AF77: 片式瓷介电容 TCC0603X7R105K500CT X7R,1uF,10%,50V,0603(三环)(编带)(RoHS) | AG77: 0.0598
A78: 89 | B78: 硬件 | C78: N30599000312 | D78: 片式瓷介电容 X7R,470pF,10%,50V,0603(编带)(RoHS)(互换件) | E78: AB级替换 | F78: SMT | G78: 1 | H78: N30515002089 | I78: 片式瓷介电容 CC0603KRX7R9BB471 X7R,470pF,10%,50V,0603(国巨)(编带)(RoHS) | J78: 陈虹 | K78: SZCLW2 | L78: 深圳市超利维实业有限公司 | M78: 0.0054 | N78: 0.00648 | O78: =(N78-M78)*G78 -> 0.00108 | P78: 0 | Q78: =G78*M78 -> 0.0054 | R78: 56 | S78: 4000 | X78: C12 | Y78: N30515002299 | Z78: 片式瓷介电容 0603B471K500NT X7R,470pF,10%,50V,0603(风华)(编带)(RoHS) | AA78: 0.0058 | AB78: N30515002326 | AC78: 片式瓷介电容 C1608X7R1H471KT000N X7R,470pF,10%,50V,0603(TDK)(编带)(RoHS) | AD78: 0.015
A79: 90 | B79: 硬件 | C79: N30599000342 | D79: 片式瓷介电容 X6S,10uF,10%,35V,0805(编带)(RoHS)(互换件) | E79: AB级替换 | F79: SMT | G79: 28 | H79: N30515002399 | I79: 片式瓷介电容 TCC0805X6S106K350FT X6S,10uF,10%,35V,0805(三环)(编带)(RoHS) | J79: 江华媛 | K79: 10667 | L79: 苏州巨宏达电工科技有限公司 | M79: 0.1689 | N79: 0.192 | O79: =(N79-M79)*G79 -> 0.6468 | P79: 0 | Q79: =G79*M79 -> 4.7292 | R79: 56 | S79: 3000 | T79: 3000 | X79: C103,,C103AA,C104,,C104AA,C105,,C105AA,C106,,C106AA,C107,,C107AA,C108,,C108AA,C121,,C121A,C148,,C148A,C149,,C149A,C151,,C151AA,C152,,C152AA,C153,,C153AA,C154,,C154AA,C156,,C156A | Y79: N30515000642 | Z79: 片式瓷介电容 GRM21BC8YA106KE11L X6S,10uF,10%,35V,0805(Murata)(编带)(RoHS) | AA79: 0.27
A80: 91 | B80: 硬件 | C80: N31301000176 | D80: 光耦 PC817X3NIP SOP4(RankC)(Sharp)(编带)(RoHS) | E80: AB级替换 | F80: SMT | G80: 2 | H80: N31301000176 | I80: 光耦 PC817X3NIP SOP4(RankC)(Sharp)(编带)(RoHS) | J80: 504 | K80: 10829 | L80: 厦门翔烨云供应链科技有限公司 | M80: 0.4178 | P80: 0 | Q80: =G80*M80 -> 0.8356 | R80: 7 | S80: 2000 | T80: 2001 | X80: B1,2
A81: 92 | B81: 硬件 | C81: N31306000294 | D81: 发光二极管 LTST-C191KRKT-EL 红色,0603(亮度:M,N,波长:630nm,电压:ALL)(光宝)(编带)(RoHS) | E81: AB级替换 | F81: SMT | G81: 2 | H81: N31306000294 | I81: 发光二极管 LTST-C191KRKT-EL 红色,0603(亮度:M,N,波长:630nm,电压:ALL)(光宝)(编带)(RoHS) | J81: 王临泽 | K81: SZCLW2 | L81: 深圳市超利维实业有限公司 | M81: 0.0355 | N81: 0.0361332 | O81: =(N81-M81)*G81 -> 0.0012664 | P81: 0 | Q81: =G81*M81 -> 0.071 | R81: 84 | S81: 25000 | X81: V54,56
A82: 93 | B82: 硬件 | C82: N31306000469 | D82: 发光二极管 LTST-C191TBKT-5A 蓝色,0603(亮度:M1/M2,波长:ALL,电压:ALL)(光宝)(编带)(RoHS) | E82: AB级替换 | F82: SMT | G82: 4 | H82: N31306000469 | I82: 发光二极管 LTST-C191TBKT-5A 蓝色,0603(亮度:M1/M2,波长:ALL,电压:ALL)(光宝)(编带)(RoHS) | J82: 196656 | K82: 10848 | L82: PAN Elektron (Hong-Kong) Co., Limited | M82: 0.062883 | N82: 0.0722676 | O82: =(N82-M82)*G82 -> 0.0375384 | P82: 0 | Q82: =G82*M82 -> 0.251532 | R82: 84 | S82: 0 | T82: 25000 | X82: V20,22,39,59
A83: 94 | B83: 硬件 | C83: N31306000791 | D83: 发光二极管 RF-GNB191TS-CF 翠绿色,0603(亮度:430-1000mcd,波长:520-526nm,电压:2.7-3.3V)(瑞丰)(编带)(RoHS) | E83: AB级替换 | F83: SMT | G83: 2 | H83: N31306000791 | I83: 发光二极管 RF-GNB191TS-CF 翠绿色,0603(亮度:430-1000mcd,波长:520-526nm,电压:2.7-3.3V)(瑞丰)(编带)(RoHS) | J83: 王临泽 | K83: SZRFGD2 | L83: 深圳市瑞丰光电子股份有限公司（ZZ） | M83: 0.0417 | P83: 0 | Q83: =G83*M83 -> 0.0834 | R83: 28 | S83: 4000 | X83: V55,57
A84: 95 | B84: 硬件 | C84: N31501000361 | D84: 超快恢复二极管 US1D 1A,200V,SMA(强茂)(编带)(RoHS) | E84: AB级替换 | F84: SMT | G84: 9 | H84: N31501000361 | I84: 超快恢复二极管 US1D 1A,200V,SMA(强茂)(编带)(RoHS) | J84: 吴巧明 | K84: GZGY2 | L84: 广州市洲光源电子有限公司（ZZ） | M84: 0.094 | N84: 0.1116 | O84: =(N84-M84)*G84 -> 0.1584 | P84: 0 | Q84: =G84*M84 -> 0.846 | R84: 84 | S84: 1800 | X84: V3,6,12,13,18,23-26
A85: 96 | B85: 硬件 | C85: N31503000090 | D85: 整流桥 GBJ25M 25A,1KV(固锝)(RoHS) | E85: AB级替换 | F85: 插焊 | G85: 1 | H85: N31503000090 | I85: 整流桥 GBJ25M 25A,1KV(固锝)(RoHS) | J85: 赖淑琴 | K85: XMLD2 | L85: 厦门立锝电子有限公司 | M85: 1.8 | N85: 1.9602 | O85: =(N85-M85)*G85 -> 0.1602 | P85: 0 | Q85: =G85*M85 -> 1.8 | R85: 56 | S85: 400 | X85: V15
A86: 97 | B86: 硬件 | C86: N31504000059 | D86: 开关二极管 1N4148WX-TP 150mA,100V,SOD323(MCC)(编带)(RoHS) | E86: AB级替换 | F86: SMT | G86: 6 | H86: N31504000059 | I86: 开关二极管 1N4148WX-TP 150mA,100V,SOD323(MCC)(编带)(RoHS) | J86: 赖淑琴 | K86: XMKL2 | L86: 厦门科力通电子科技有公司（ZZ） | M86: 0.02 | P86: 0 | Q86: =G86*M86 -> 0.12 | R86: 56 | S86: 3000 | X86: V27,30,33,36-38
A87: 98 | B87: 硬件 | C87: N31504000155 | D87: 开关二极管 BAV99 200mA,70V,SOT23(晶导微)(编带)(RoHS) | E87: AB级替换 | F87: SMT | G87: 9 | H87: N31504000155 | I87: 开关二极管 BAV99 200mA,70V,SOT23(晶导微)(编带)(RoHS) | J87: 514 | K87: 10382 | L87: 厦门镁富莱工贸有限公司 | M87: 0.02 | P87: 0 | Q87: =G87*M87 -> 0.18 | R87: 35 | S87: 1 | T87: 1 | X87: V7,11,44-47,51-53
A88: 99 | B88: 硬件 | C88: N31507000185 | D88: TVS SMBJ20A-13 600W,20V,SMB(Diodes)(编带)(RoHS) | E88: AB级替换 | F88: SMT | G88: 3 | H88: N31507000578 | I88: TVS SMBJ20A 600W,20V,SMB(扬杰)(编带)(RoHS) | J88: 1100 | K88: 10084 | L88: 厦门格亚电子科技有限公司 | M88: 0.133 | N88: 0.19 | O88: =(N88-M88)*G88 -> 0.171 | P88: 0 | Q88: =G88*M88 -> 0.399 | R88: 42 | S88: 3000 | T88: 3000 | X88: V28,31,34 | Y88: N31507000185 | Z88: TVS SMBJ20A-13 600W,20V,SMB(Diodes)(编带)(RoHS) | AA88: 0.45
A89: 100 | B89: 硬件 | C89: N31507000282 | D89: TVS P6SMB200A 600W,171V,SMB(固锝)(编带)(RoHS) | E89: AB级替换 | F89: SMT | G89: 1 | H89: N31507000282 | I89: TVS P6SMB200A 600W,171V,SMB(固锝)(编带)(RoHS) | J89: 吴巧明 | K89: SWSC2 | L89: 深圳市威斯创电子有限公司（ZZ） | M89: 0.2 | N89: 0.22035398 | O89: =(N89-M89)*G89 -> 0.020353982 | P89: 0 | Q89: =G89*M89 -> 0.2 | R89: 56 | S89: 3000 | X89: V17 | Y89: N31507000241 | Z89: TVS P6SMB200A 600W,171V,SMB(强茂)(编带)(RoHS) | AA89: 0.28
A90: 101 | B90: 硬件 | C90: N31507000686 | D90: TVS SMF20CA 200W,20V,SOD123FL(扬杰)(编带)(RoHS) | E90: AB级替换 | F90: SMT | G90: 6 | H90: N31507000686 | I90: TVS SMF20CA 200W,20V,SOD-123FL(扬杰)(RoHS) | J90: 朱建南 | K90: MHDZ2 | L90: 厦门美赫电子有限公司 | M90: 0.0929 | P90: 0 | Q90: =G90*M90 -> 0.5574 | R90: 56 | S90: 3000 | T90: 3000 | X90: V41-43,48-50
A91: 102 | B91: 硬件 | C91: N31511000054 | D91: 超快恢复二极管 US1Q-TP 1A,1.2KV,SMA(MCC)(编带)(RoHS) | E91: AB级替换 | F91: SMT | G91: 6 | H91: N31511000054 | I91: 超快恢复二极管 US1Q-TP 1A,1.2KV,SMA(MCC)(编带)(RoHS) | J91: 106166 | K91: 10265 | L91: 北天星电子(深圳)有限公司 | M91: 0.0885 | P91: 0 | Q91: =G91*M91 -> 0.531 | R91: 56 | S91: 0 | T91: 3000 | X91: V8-10,29,32,35
A92: 103 | B92: 硬件 | C92: N31513000020 | D92: ESD保护二极管 ASM712H 12V,SOT23(扬杰)(编带)(RoHS) | E92: AB级替换 | F92: SMT | G92: 2 | H92: N31513000020 | I92: ESD保护二极管 ASM712H 12V,SOT23(扬杰)(编带)(RoHS) | J92: 106166 | K92: 10178 | L92: 厦门美赫电子有限公司 | M92: 0.3325 | P92: 0 | Q92: =G92*M92 -> 0.665 | R92: 56 | S92: 0 | T92: 3000 | X92: V1,2
A93: 104 | B93: 硬件 | C93: N31599000074 | D93: 超快恢复二极管 ES2D 2A,200V,SMB(编带)(RoHS)(互换件) | E93: AB级替换 | F93: SMT | G93: 2 | H93: N31511000048 | I93: 超快恢复二极管 ES2D 2A,200V,SMB(扬杰)(编带)(RoHS) | J93: 106166 | K93: 10178 | L93: 厦门美赫电子有限公司 | M93: 0.079 | P93: 0 | Q93: =G93*M93 -> 0.158 | R93: 70 | S93: 0 | T93: 3000 | X93: V19,21 | Y93: N31511000028 | Z93: 超快恢复二极管 ES2DHE3_A/H 2A,200V,SMB(符合AEC-Q101)(Vishay)(编带)(RoHS) | AA93: 0.536505 | AB93: N31502000078 | AC93: 超快恢复二极管 STTH2R02U 2A,200V,SMB(ST)(RoHS) | AD93: 0.817
A94: 105 | B94: 硬件 | C94: N31701000323 | D94: 三极管 DTC143ECA-TP SOT23,NPN(内置电阻4.7K)(MCC)(编带)(RoHS) | E94: AB级替换 | F94: SMT | G94: 1 | H94: N31701000323 | I94: 三极管 DTC143ECA-TP SOT23,NPN(内置电阻4.7K)(MCC)(编带)(RoHS) | J94: 106166 | K94: 10804 | L94: 厦门科力通电子科技有限公司 | M94: 0.048 | P94: 0 | Q94: =G94*M94 -> 0.048 | R94: 56 | S94: 0 | T94: 3000 | X94: V40 | Y94: N31701000290 | Z94: 三极管 DDTC143ECA-7-F NPN,SOT23(内置电阻4.7K)(Diodes)(RoHS) | AA94: 0.104
A95: 106 | B95: 硬件 | C95: N31701000756 | D95: 三极管 SS8050-H NPN,25V,HFE=200-350,1.5A,SOT23(晶导微)(编带)(RoHS) | E95: AB级替换 | F95: SMT | G95: 3 | H95: N31701000756 | I95: 三极管 SS8050-H NPN,25V,HFE=200-350,1.5A,SOT23(晶导微)(编带)(RoHS) | J95: 514 | K95: 10829 | L95: 厦门翔烨云供应链科技有限公司 | M95: 0.0246 | N95: 0.02691 | O95: =(N95-M95)*G95 -> 0.00693 | P95: 0 | Q95: =G95*M95 -> 0.0738 | R95: 35 | S95: 1 | T95: 1 | X95: V4,5,14
A96: 107 | B96: 硬件 | C96: N31800000736 | D96: 通信电路 ISO3082DWR SOIC16(TI)(编带)(RoHS) | E96: AB级替换 | F96: SMT | G96: 2 | H96: N31800000736 | I96: 通信电路 ISO3082DWR SOIC16(TI)(编带)(RoHS) | J96: 504 | K96: 10829 | L96: 厦门翔烨云供应链科技有限公司 | M96: 5.9486 | P96: 0 | Q96: =G96*M96 -> 11.8972 | R96: 1 | S96: 1 | T96: 0 | X96: N1,2
A97: 108 | B97: 硬件 | C97: N31801001593 | D97: 微处理器 R5F526T8ADFM LFQFP64(国创提供)(Renesas)(盘式)(RoHS) | E97: AB级替换 | F97: SMT | G97: 2 | H97: N31801001593 | I97: 微处理器 R5F526T8ADFM LFQFP64(国创提供)(Renesas)(盘式)(RoHS) | J97: 105878 | L97: 20251014业务邮件通知客供料 | M97: 0 | N97: 0 | O97: =(N97-M97)*G97 -> 0 | P97: 0 | Q97: =G97*M97 -> 0 | R97: 0 | V97: 客供料 | X97: N22,23
A98: 109 | B98: 硬件 | C98: N31805000269 | D98: 存贮器 M24C08-RMN6TP SO8(ST)(编带)(RoHS) | E98: AB级替换 | F98: SMT | G98: 1 | H98: N31805000269 | I98: 存贮器 M24C08-RMN6TP SO8(ST)(编带)(RoHS) | J98: 514 | K98: 10867 | L98: WT MICROELECTRONICS SINGAPORE PTE. LTD. | M98: 0.241526 | P98: 0 | Q98: =G98*M98 -> 0.241526 | R98: 140 | S98: 3000 | T98: 3000 | X98: N21
A99: 110 | B99: 硬件 | C99: N31805000274 | D99: 存贮器 M24C16-RMN6TP SO8(ST)(编带)(RoHS) | E99: AB级替换 | F99: SMT | G99: 1 | H99: N31805000274 | I99: 存贮器 M24C16-RMN6TP SO8(ST)(编带)(RoHS) | J99: 514 | K99: 10265 | L99: 北天星电子(深圳)有限公司 | M99: 0.267 | P99: 0 | Q99: =G99*M99 -> 0.267 | R99: 70 | S99: 2500 | T99: 2500 | X99: N20
A100: 111 | B100: 硬件 | C100: N31806000081 | D100: 稳压器 L78M05ABDT-TR DPAK(ST)(RoHS) | E100: AB级替换 | F100: SMT | G100: 2 | H100: N31806000081 | I100: 稳压器 L78M05ABDT-TR DPAK(ST)(RoHS) | J100: 504 | K100: 10829 | L100: 厦门翔烨云供应链科技有限公司 | M100: 0.6039 | P100: 0 | Q100: =G100*M100 -> 1.2078 | R100: 7 | S100: 1 | T100: 1 | X100: N5,7
...

Sheet 客供料
A1: 26P | B1: D5A13H000000 | E1: TIMS735EXV/9A4A | P1: 8月 | Q1: 9月 | R1: 10月 | S1: 11月 | T1: 12月
A2: 序号 | B2: 物料 | C2: 型号 | D2: 位号 | E2: 数量 | F2: 工艺 | G2: 品牌 | H2: 备注 | I2: 单价 | J2: 渠道 | K2: 交期 | L2: 降后价 | M2: 供应商 | N2: 2026-3-24降价 | P2: 200 | Q2: 200 | R2: 200 | S2: 150 | T2: 150 | U2: 合计 | V2: 累计降幅
A3: 2 | B3: 薄膜电容 | C3: 40μF/1100V/4Pin | D3: C125, C126, C127 | E3: 3 | F3: HI | G3: 松下 | H3: 家中机也用 | I3: 23.98 | J3: 港德 | K3: 4W | L3: 20.3739 | P3: 600 | Q3: 600 | R3: 600 | S3: 450 | T3: 450 | U3: 61.1217 | V3: 10.8183
A4: 3 | B4: 共模滤波器 | C4: CMF50F04QX1 4mH,50A(赛特勒)(RoHS) | D4: L1,2 | E4: 2 | F4: N32302000353 | G4: 菲尔泰科 | I4: 45.8 | J4: 菲尔泰科 | K4: 3W | L4: 20 | P4: 400 | Q4: 400 | R4: 400 | S4: 300 | T4: 300 | U4: 91.6 | V4: 51.6
A5: 4 | B5: 共模电感 | C5: CM10100ZJ-1/9A/15mH | D5: L2 | E5: 1 | F5: HI | G5: 菲尔泰科 | I5: 7 | J5: 菲尔泰科 | K5: 2W | L5: 7 | P5: 200 | Q5: 200 | R5: 200 | S5: 150 | T5: 150 | U5: 7 | V5: 0
A6: 5 | B6: PIM | C6: 100A/1200V/FP100R12N2T7 | D6: A1 | E6: 1 | F6: HI | G6: 英飞凌 | I6: 307.3 | J6: 晶川 | K6: 4-6W | L6: 305 | M6: 芯硕 | N6: 302 | O6: 晶川2026-3-24降价 | P6: 200 | Q6: 200 | R6: 200 | S6: 150 | T6: 150 | U6: 307.3 | V6: 5.3
A7: 6 | B7: 栅极驱动IC | C7: 1EDI20I12MF/SOP-8 | D7: N8, N9, N10, N11, N12, N13 | E7: 6 | F7: SMT | G7: 英飞凌 | I7: 3.83 | J7: 晶川 | K7: 4-6W | L7: 3.73 | M7: 芯硕 | N7: 3.7 | O7: 晶川2026-3-24降价 | P7: 1200 | Q7: 1200 | R7: 1200 | S7: 900 | T7: 900 | U7: 22.98 | V7: 0.78
A8: 7 | B8: IPM | C8: 功率模块 RCI20C60D6U (20A,600V)(IPM模块)(NJTJ专用)(银河边缘)(RoHS) | D8: A2, A3 | E8: 2 | F8: HI | G8: 国创 | I8: 23 | J8: 银河 | K8: 4W | N8: 18.9049 | O8: 2026-3-26降价 由银河转京西 | P8: 400 | Q8: 400 | R8: 400 | S8: 300 | T8: 300 | U8: 46 | V8: 8.1902
A9: 8 | B9: ACDC | C9: TOP264K/ESOP-12B | D9: N3 | E9: 1 | F9: HI | G9: PI | I9: 2.818 | J9: 北高智 | K9: 4-6W | P9: 200 | Q9: 200 | R9: 200 | S9: 150 | T9: 150 | U9: 2.818 | V9: 0
A10: 9 | B10: MCU | C10: R5F526T8ADFM/LQFP64 | D10: N22, N23 | E10: 2 | F10: SMT | G10: 瑞萨 | H10: 家中机也用 | I10: 7.75 | J10: 新晔 | K10: 12W | P10: 400 | Q10: 400 | R10: 400 | S10: 300 | T10: 300 | U10: 15.5 | V10: 0
I11: 554.3197 | U11: 554.3197 | V11: 76.69
A12: 20P | B12: D5A13G000000 | E12: TIMS560EXV9B4A | P12: 8月 | Q12: 9月 | R12: 10月 | S12: 11月 | T12: 12月 | U12: 490.5484 | V12: 10.531
I13: 单价 | J13: 渠道 | K13: 交期 | P13: 150 | Q13: 150 | R13: 150 | S13: 120 | T13: 120
A14: 2 | B14: 薄膜电容 | C14: 40μF/1100V/4Pin | D14: C125, C126, C127 | E14: 3 | F14: HI | G14: 松下 | H14: 家中机通用 | I14: 23.98 | J14: 港德 | K14: 4W | L14: 20.3739 | P14: 450 | Q14: 450 | R14: 450 | S14: 360 | T14: 360 | U14: 71.94 | V14: 10.8183
A15: 3 | B15: 共模滤波器 | C15: CMF50F04QX1 4mH,50A(赛特勒)(RoHS) | D15: L1,2 | E15: 2 | F15: N32302000353 | G15: 菲尔泰科 | I15: 45.8 | J15: 菲尔泰科 | K15: 3W | L15: 20 | P15: 300 | Q15: 300 | R15: 300 | S15: 240 | T15: 240 | U15: 91.6 | V15: 51.6
A16: 4 | B16: 共模电感 | C16: CM10100ZJ-1/9A/15mH | D16: L2 | E16: 1 | F16: HI | G16: 菲尔泰科 | I16: 7 | J16: 菲尔泰科 | K16: 2W | L16: 7 | P16: 150 | Q16: 150 | R16: 150 | S16: 120 | T16: 120 | U16: 7 | V16: 0
A17: 5 | B17: PIM | C17: 功率模块 FP75R12N2T7 (1.2KV,75A)(PIM模块)(Infineon)(RoHS) | D17: A1 | E17: 1 | F17: HI | G17: 英飞凌 | I17: 276 | J17: 晶川 | K17: 4-6W | L17: 273 | M17: 芯硕 | N17: 270 | O17: 晶川 | P17: 150 | Q17: 150 | R17: 150 | S17: 120 | T17: 120 | U17: 276 | V17: 6
A18: 6 | B18: 栅极驱动IC | C18: 1EDI20I12MF/SOP-8 | D18: N8, N9, N10, N11, N12, N13 | E18: 6 | F18: SMT | G18: 英飞凌 | I18: 3.83 | J18: 晶川 | K18: 4-6W | L18: 3.73 | M18: 芯硕 | N18: 3.7 | O18: 晶川 | P18: 900 | Q18: 900 | R18: 900 | S18: 720 | T18: 720 | U18: 22.98 | V18: 0.78
A19: 7 | B19: IPM | C19: 功率模块 RCI20C60D6U (20A,600V)(IPM模块)(NJTJ专用)(银河边缘)(RoHS) | D19: A2, A3 | E19: 2 | F19: HI | G19: 国创 | I19: 23 | J19: 银河 | K19: 4W | N19: 18.9049 | O19: 2026-3-26降价 由银河转京西 | P19: 300 | Q19: 300 | R19: 300 | S19: 240 | T19: 240 | U19: 46 | V19: 8.1902
A20: 8 | B20: ACDC | C20: TOP264K/ESOP-12B | D20: N3 | E20: 1 | F20: HI | G20: PI | I20: 2.818 | J20: 北高智 | K20: 4-6W | L20: 2.818 | P20: 150 | Q20: 150 | R20: 150 | S20: 120 | T20: 120 | U20: 2.818 | V20: 2.818
A21: 9 | B21: MCU | C21: R5F526T8ADFM/LQFP64 | D21: N22, N23 | E21: 2 | F21: SMT | G21: 瑞萨 | H21: 家中机也用 | I21: 7.75 | J21: 新晔 | K21: 12W | P21: 300 | Q21: 300 | R21: 300 | S21: 240 | T21: 240 | U21: 15.5
I22: 533.838 | U22: 533.838
U23: 472.423 | V23: 80.21
